Workbook

Sheet Introduction
A1: INTRODUCTION
A2: Main Company | F2: Competitor
A3: Radico Khaitan Ltd | F3: United Spirits Ltd

Sheet Sales Trend
A1: Trend in Sales
A3: Radico Khaitan Ltd.
A4: Year | B4: 45741 | C4: 46105 | D4: 46104 | E4: 46103 | F4: 46102
A5: Net Sales (Rs. In crores) | B5: 4851.2 | C5: 4118.5 | D5: 3142.8 | E5: 2868 | F5: 2398.8
A6: YOY Sales Growth | B6: =(B5-C5)/C5 -> 0.17790458 | C6: =(C5-D5)/D5 -> 0.31045564 | D6: =(D5-E5)/E5 -> 0.0958159 | E6: =(E5-F5)/F5 -> 0.1955978 | F6: -
A9: United Spirits Ltd.
A10: Year | B10: 45741 | C10: 46105 | D10: 46104 | E10: 46103 | F10: 46102
A11: Net Sales (Rs. In crores) | B11: 11573 | C11: 10692 | D11: 10373.7 | E11: 9423.7 | F11: 9405.5
A12: YOY Sales Growth | B12: =(B11-C11)/C11 -> 0.082398055 | C12: =(C11-D11)/D11 -> 0.030683363 | D12: =(D11-E11)/E11 -> 0.10080966 | E12: =(E11-F11)/F11 -> 0.001935038 | F12: -

Sheet Asset Growth Rate
A1: ASSET GROWTH RATE
A2: Radico Khaitan Ltd.
A3: Year | B3: 45741 | C3: 46105 | D3: 46104 | E3: 46103 | F3: 46102
A4: Total Assets(in Cr) | B4: 4638.956 | C4: 4094.983 | D4: 3719.088 | E4: 2781.192 | F4: 2714.362
A5: YOY Growth | B5: =(B4-C4)/C4 -> 0.13283889 | C5: =(C4-D4)/D4 -> 0.10107182 | D5: =(D4-E4)/E4 -> 0.33722807 | E5: =(E4-F4)/F4 -> 0.024620887 | F5: -
A8: United Spirits Ltd.
A9: Year | B9: 45741 | C9: 46105 | D9: 46104 | E9: 46103 | F9: 46102
A10: Total Assets(in Cr) | B10: 13248 | C10: 11249 | D10: 9761.5 | E10: 8911.3 | F10: 8537
A11: YOY Growth | B11: =(B10-C10)/C10 -> 0.17770468 | C11: =(C10-D10)/D10 -> 0.15238437 | D11: =(D10-E10)/E10 -> 0.095406955 | E11: =(E10-F10)/F10 -> 0.043844442 | F11: -

Sheet Profit
A1: PROFIT OVER THE YEARS
A2: TOTAL PROFIT(in Millions)
B3: 2020-21 | C3: 2021-22 | D3: 2022-23 | E3: 2023-24 | F3: 2024-25 | G3: YOY
A4: Radico Khaitan | B4: 2705.64 | C4: 2485.43 | D4: 2043.72 | E4: 2621.75 | F4: 3456.11 | G4: =(F4-E4)/E4 -> 0.31824545
A5: YoY Sales Growth% (Radico) | B5: - | C5: =(C4-B4)/B4 -> -0.081389246 | D5: =(D4-C4)/C4 -> -0.17771975 | E5: =(E4-D4)/D4 -> 0.28283229 | F5: =(F4-E4)/E4 -> 0.31824545
A6: United Spirits Limited(USL) | B6: 3621 | C6: 8106 | D6: 11258 | E6: 14080 | F6: 15820 | G6: =(F6-E6)/E6 -> 0.12357955
A7: YoY Sales Growth% (USL) | B7: - | C7: =(C6-B6)/B6 -> 1.2386081 | D7: =(D6-C6)/C6 -> 0.38884777 | E7: =(E6-D6)/D6 -> 0.25066619 | F7: =(F6-E6)/E6 -> 0.12357955

Sheet Performance
A1: PERFORMANCE ANALYSIS
A3: TOTAL EMPLOYEES
B4: 2020-21 | C4: 2021-22 | D4: 2022-23 | E4: 2023-24 | F4: 2024-25 | G4: YOY
A5: Radico Khaitan | B5: 1179 | C5: 1196 | D5: 1329 | E5: 1469 | F5: 1494 | G5: =(F5-E5)/E5 -> 0.01701838
A6: YoY Growth% (Radico) | B6: - | C6: =(C5-B5)/B5 -> 0.014418999 | D6: =(D5-C5)/C5 -> 0.11120401 | E6: =(E5-D5)/D5 -> 0.10534236 | F6: =(F5-E5)/E5 -> 0.01701838
A7: United Spirits Limited(USL) | B7: 3261 | C7: 3145 | D7: 2957 | E7: 2598 | F7: 2420 | G7: =(F7-E7)/E7 -> -0.068514242 | M7: ←
A8: YoY Growth% (USL) | B8: - | C8: =(C7-B7)/B7 -> -0.03557191 | D8: =(D7-C7)/C7 -> -0.059777424 | E8: =(E7-D7)/D7 -> -0.12140683 | F8: =(F7-E7)/E7 -> -0.068514242
A10: TOTAL SALES(in crores)
B11: 2020-21 | C11: 2021-22 | D11: 2022-23 | E11: 2023-24 | F11: 2024-25 | G11: YOY
A12: Radico Khaitan | B12: 2398.8 | C12: 2868 | D12: 3142.8 | E12: 4118.5 | F12: 4851.2 | G12: =(F12-E12)/E12 -> 0.17790458
A13: YoY Sales Growth% (Radico) | B13: - | C13: =(C12-B12)/B12 -> 0.1955978 | D13: =(D12-C12)/C12 -> 0.0958159 | E13: =(E12-D12)/D12 -> 0.31045564 | F13: =(F12-E12)/E12 -> 0.17790458
A14: United Spirits Limited(USL) | B14: 9405.5 | C14: 9423.7 | D14: 10373.7 | E14: 10692 | F14: 11573 | G14: =(F14-E14)/E14 -> 0.082398055
A15: YoY Sales Growth% (USL) | B15: - | C15: =(C14-B14)/B14 -> 0.001935038 | D15: =(D14-C14)/C14 -> 0.10080966 | E15: =(E14-D14)/D14 -> 0.030683363 | F15: =(F14-E14)/E14 -> 0.082398055
A17: TOTAL PROFIT(in Millions)
B18: 2020-21 | C18: 2021-22 | D18: 2022-23 | E18: 2023-24 | F18: 2024-25 | G18: YOY
A19: Radico Khaitan | B19: 2705.64 | C19: 2485.43 | D19: 2043.72 | E19: 2621.75 | F19: 3456.11 | G19: =(F19-E19)/E19 -> 0.31824545
A20: YoY Sales Growth% (Radico) | B20: - | C20: =(C19-B19)/B19 -> -0.081389246 | D20: =(D19-C19)/C19 -> -0.17771975 | E20: =(E19-D19)/D19 -> 0.28283229 | F20: =(F19-E19)/E19 -> 0.31824545 | M20: ←
A21: United Spirits Limited(USL) | B21: 3621 | C21: 8106 | D21: 11258 | E21: 14080 | F21: 15820 | G21: =(F21-E21)/E21 -> 0.12357955
A22: YoY Sales Growth% (USL) | B22: - | C22: =(C21-B21)/B21 -> 1.2386081 | D22: =(D21-C21)/C21 -> 0.38884777 | E22: =(E21-D21)/D21 -> 0.25066619 | F22: =(F21-E21)/E21 -> 0.12357955
A24: TOTAL ASSET(in Millions)
B25: 2020-21 | C25: 2021-22 | D25: 2022-23 | E25: 2023-24 | F25: 2024-25 | G25: YOY
A26: Radico Khaitan | B26: 27143.62 | C26: 27811.92 | D26: 37190.88 | E26: 40949.83 | F26: 46389.56 | G26: =(F26-E26)/E26 -> 0.13283889
A27: YoY Sales Growth% (Radico) | B27: - | C27: =(C26-B26)/B26 -> 0.024620887 | D27: =(D26-C26)/C26 -> 0.33722807 | E27: =(E26-D26)/D26 -> 0.10107182 | F27: =(F26-E26)/E26 -> 0.13283889
A28: United Spirits Limited(USL) | B28: 85370 | C28: 89113 | D28: 97615 | E28: 112490 | F28: 132480 | G28: =(F28-E28)/E28 -> 0.17770468
A29: YoY Sales Growth% (USL) | B29: - | C29: =(C28-B28)/B28 -> 0.043844442 | D29: =(D28-C28)/C28 -> 0.095406955 | E29: =(E28-D28)/D28 -> 0.15238437 | F29: =(F28-E28)/E28 -> 0.17770468
M37: ←
M52: ←

Sheet Sales per rupee of asset deploy
A1: Sales per rupee of asset deployed in the company
A5: Asset Turnover Ratio = Net sales / Total Assets
A7: Radico Khaitan Ltd.
B8: 45741 | C8: 46105 | D8: 46104 | E8: 46103 | F8: 46102
A9: Net Sales (in Cr) | B9: 4851.2 | C9: 4118.5 | D9: 3142.8 | E9: 2868 | F9: 2398.8
A10: Total Assets (in CR) | B10: 4638.956 | C10: 4094.983 | D10: 3719.088 | E10: 2781.192 | F10: 2714.362
A11: Sales per rupee of asset deployed | B11: =B9/B10 -> 1.0457525 | C11: =C9/C10 -> 1.0057429 | D11: =D9/D10 -> 0.84504588 | E11: =E9/E10 -> 1.0312125 | F11: =F9/F10 -> 0.88374358
A13: United Spirits Ltd.
B14: 45741 | C14: 46105 | D14: 46104 | E14: 46103 | F14: 46102
A15: Net Sales (in Cr) | B15: 11573 | C15: 10692 | D15: 10373.7 | E15: 9423.7 | F15: 9405.5
A16: Total Assets (in CR) | B16: 13248 | C16: 11249 | D16: 9761.5 | E16: 8911.3 | F16: 8537
A17: Sales per rupee of asset deployed | B17: =B15/B16 -> 0.87356582 | C17: =C15/C16 -> 0.95048449 | D17: =D15/D16 -> 1.0627158 | E17: =E15/E16 -> 1.0575 | F17: =F15/F16 -> 1.1017336

Sheet Sales per employee
A1: Sales per employee
A5: Net sales / Total no. of employees
A7: Radico Khaitan Ltd.
B8: 45741 | C8: 46105 | D8: 46104 | E8: 46103 | F8: 46102
A9: Net Sales (in Cr) | B9: 4851.2 | C9: 4118.5 | D9: 3142.8 | E9: 2868 | F9: 2398.8
A10: Number of Employees | B10: 1494 | C10: 1469 | D10: 1329 | E10: 1196 | F10: 1179
A11: Sales(in Cr) per employee | B11: =B9/B10 -> 3.2471218 | C11: =C9/C10 -> 2.8036079 | D11: =D9/D10 -> 2.3647856 | E11: =E9/E10 -> 2.3979933 | F11: =F9/F10 -> 2.0346056
A13: United Spirits Ltd.
B14: 45741 | C14: 46105 | D14: 46104 | E14: 46103 | F14: 46102
A15: Net Sales (in Cr) | B15: 11573 | C15: 10692 | D15: 10373.7 | E15: 9423.7 | F15: 9405.5
A16: Number of Employees | B16: 2420 | C16: 2598 | D16: 2957 | E16: 3145 | F16: 3261
A17: Sales(in Cr) per employee | B17: =B15/B16 -> 4.7822314 | C17: =C15/C16 -> 4.1154734 | D17: =D15/D16 -> 3.508184 | E17: =E15/E16 -> 2.996407 | F17: =F15/F16 -> 2.884238

Sheet GPPM
A1: Liquor Industry Competitor Analysis (FY2021 - FY2025)
A3: 5-Year Growth Performance Profile Matrix
A4: Growth Dimension | B4: Radico Khaitan Ltd. | C4: United Spirits Ltd. (USL) | D4: Strategic Market Dynamics
A5: Sales Growth | B5: Robust volume expansion driven by high-velocity premium brands (Magic Moments, Morpheus). | C5: Flat headline growth due to divestment of low-margin popular brands; premium segments expanded heavily. | D5: USL prioritized premium value margins over volume; Radico pursued concurrent volume and brand premiumization.
A6: Assets Growth | B6: High asset expansion. Massive capital expenditure deployed on backward integration (e.g., Sitapur plant). | C6: Controlled and asset-light. Corporate restructuring optimized manufacturing footprint. | D6: Radico built physical capacity to secure raw spirit supplies; USL enhanced capital returns by reducing asset weight.
A7: Profit Growth | B7: Steady absolute growth, though short-term margins faced inflationary pressures from glass and grain inputs. | C7: Superior margin expansion. Divestment of regular portfolio significantly improved overall EBITDA profiles. | D7: USL underwent structural margin expansion; Radico focused on scaling long-term volume capabilities.
A8: Market Price Growth | B8: Massive multi-bagger returns, strongly re-rated for entering luxury single malts and craft segments. | C8: Exceptional market capitalization growth, matching valuation standards of a pure global Diageo clone. | D8: Both businesses rewarded intensely by public markets for transitioning into pure-play premium narratives.
A11: Visual Trend Reference Blocks
A13: Year | B13: Radico Asset Turnover | C13: USL Asset Turnover
A14: FY21 | B14: ='Financial Data'!E5 -> 0.88374358 | C14: ='Financial Data'!E14 -> 1.1017336
A15: FY22 | B15: ='Financial Data'!E6 -> 1.0312125 | C15: ='Financial Data'!E15 -> 1.0575
A16: FY23 | B16: ='Financial Data'!E7 -> 0.84504588 | C16: ='Financial Data'!E16 -> 1.0627158
A17: FY24 | B17: ='Financial Data'!E8 -> 1.0057429 | C17: ='Financial Data'!E17 -> 0.95048449
A18: FY25 | B18: ='Financial Data'!E9 -> 1.0457525 | C18: ='Financial Data'!E18 -> 0.87356582
A21: Year | B21: Radico Sales/Emp | C21: USL Sales/Emp
A22: FY21 | B22: ='Financial Data'!F5 -> 2.0346056 | C22: ='Financial Data'!F14 -> 2.884238
A23: FY22 | B23: ='Financial Data'!F6 -> 2.3979933 | C23: ='Financial Data'!F15 -> 2.996407
A24: FY23 | B24: ='Financial Data'!F7 -> 2.364936 | C24: ='Financial Data'!F16 -> 3.508184
A25: FY24 | B25: ='Financial Data'!F8 -> 2.8032675 | C25: ='Financial Data'!F17 -> 4.1154734
A26: FY25 | B26: ='Financial Data'!F9 -> 3.2471218 | C26: ='Financial Data'!F18 -> 4.7822314

Sheet Financial Data
A1: Detailed Financial Efficiency Analysis & Calculations
A3: Radico Khaitan Ltd. (Operational Metrics)
A4: Fiscal Year | B4: Net Sales (₹ Cr) | C4: Total Assets (₹ Cr) | D4: Estimated Employee Base | E4: Sales per Rupee of Asset | F4: Sales per Employee (₹ Cr)
A5: FY2021 | B5: 2418 | C5: 2500 | D5: 1179 | E5: 0.88374358 | F5: 2.0346056
A6: FY2022 | B6: 2868 | C6: 2810 | D6: 1196 | E6: 1.0312125 | F6: =B6/D6 -> 2.3979933
A7: FY2023 | B7: 3143 | C7: 3420 | D7: 1329 | E7: 0.84504588 | F7: =B7/D7 -> 2.364936
A8: FY2024 | B8: 4118 | C8: 4200 | D8: 1469 | E8: 1.0057429 | F8: =B8/D8 -> 2.8032675
A9: FY2025 | B9: 4600 | C9: 4700 | D9: 1494 | E9: 1.0457525 | F9: 3.2471218
A10: 5-Year Average | B10: =AVERAGE(B5:B9) -> 3429.4 | C10: =AVERAGE(C5:C9) -> 3526 | D10: =AVERAGE(D5:D9) -> 1333.4 | E10: =AVERAGE(E5:E9) -> 0.96229948 | F10: =AVERAGE(F5:F9) -> 2.5695849
B11: 4.7822314 | C11: 4.1154734 | D11: 3.508184 | E11: 2.996407 | F11: 2.884238
A12: United Spirits Ltd. (Diageo India - Operational Metrics)
A13: Fiscal Year | B13: Net Sales (₹ Cr) | C13: Total Assets (₹ Cr) | D13: Estimated Employee Base | E13: Sales per Rupee of Asset | F13: Sales per Employee (₹ Cr)
A14: FY2021 | B14: 8131 | C14: 7200 | D14: 3261 | E14: 1.1017336 | F14: 2.884238
A15: FY2022 | B15: 9382 | C15: 7500 | D15: 3145 | E15: 1.0575 | F15: 2.996407
A16: FY2023 | B16: 10374 | C16: 6820 | D16: 2957 | E16: 1.0627158 | F16: 3.508184
A17: FY2024 | B17: 10611 | C17: 7220 | D17: 2598 | E17: 0.95048449 | F17: 4.1154734
A18: FY2025 | B18: 11200 | C18: 7600 | D18: 2420 | E18: 0.87356582 | F18: 4.7822314
A19: 5-Year Average | B19: =AVERAGE(B14:B18) -> 9939.6 | C19: =AVERAGE(C14:C18) -> 7268 | D19: =AVERAGE(D14:D18) -> 2876.2 | E19: =AVERAGE(E14:E18) -> 1.0091999 | F19: =AVERAGE(F14:F18) -> 3.6573068

Sheet Major acquisitions and their im
A1: DETAILS | B1: SALES IMPACT | C1: PROFIT IMPACT | D1: CASH FROM OPERATIONS
A2: Radico Khaitan Limited:
A3: In a major move into luxury and lifestyle spirits, Radico approved a strategic investment of up to ₹40 crore to acquire a 47.5% equity stake in both D'YAVOL Spirits B.V. (Netherlands) and D'YAVOL Spirits Private Limited (India). This high-profile partnership alongside Shah Rukh Khan, Aryan Khan, and Nikhil Kamath positions Radico as the largest shareholder in the brand to roll out luxury tequila and luxury spirits globally. | B3: It being a new partial stakeholding acquistion by Radico Khaitan in a premium tequilla Brand rolled out by Aryan Khan, Shah Rukh Khan and Nikhil Kamath, the impact on sales has not been major being just a small part of Radico's portfolio. However the sales(consolidated) of Radico Khaitan in Financial Year 2026 has gone up from the previous financial year by almost 24% year over year. The deal has been more of a strategic move to expand globally in the premium spirts segment with the Godwill and brand image of the famous bollywood actor and one of the famous Business leader Nikhil. | C3: The major stakeholding takeover has not have had a major impact on the profit of Radico Khaitan yet. But the firm has seen a net profit rise by approximately~75% YoY that is from 304.5 crores to 604.4 crores in FY 26. Hence can per say that the strategic investments have helped firm expand their business, higher the sales and earn more profit out of premiumisation. | D3: Although Radico Khaitan's cash flow has improved significantly in Financial Year 26, the impact of this investment activity is very small on the books of accounts. Bringing in around 5.5 crores of net cash inflows from operations.
A4: Consolidation via Radico Spiritzs (2022)
A5: Radico acquired a 100% equity stake in Radico Spiritzs India Private Limited, turning it into a wholly-owned subsidiary. Through this vehicle, Radico layered in full ownership of several real estate and construction entities (including Accomreal Builders and Compaqt Era Builders) to streamline corporate assets. | B5: Radico Khaitan has reported in their reports that this acquisition was purely made to improve and assist the operations of their real estate entity. Hence the consolidated level impact of sales is not visible and impactful. | C5: As Radico Khaitan Spiritz business is anciliary to the real estate the profit impact of the real estate business is not direct to the spirits business. | D5: There was an investing cash outflow but no impact on cash flows from operations as they are filling to seperate entities.
A6: United Spirits Limited
A7: In 2025, United Spirits (part of Diageo) acquired NAO Spirits, a leading Indian craft gin company known for its premium and artisanal gin brands. This acquisition was aimed at strengthening USL’s presence in the fast-growing craft spirits segment, particularly gin, which is seeing strong demand among urban and younger consumers. The move aligns with Diageo’s global strategy of premiumisation, where the focus is on high-margin, experience-driven alcohol categories rather than mass-market volumes. By acquiring NAO Spirits, USL has expanded its premium portfolio and strengthened its position in niche but high-growth categories. | B7: NAO’s standalone net turnover was ₹34.83 crore in FY24; after acquisition NAO becomes a subsidiary so its full revenue will be consolidated into United Spirits,but the company did not claim an immediate material uplifting impact to USL’s overall sales given NAO’s small scale compared to USL overall business. | C7: As the stake increased to 97.07% of United Spirits in NAO spirits, now NAO being the subsidary, the profit and revenue would add up to the consolidated financial statements hence creating a positive impact on the profit of the business. But USL being a multi-diversified business the impact of NAO is not a large scale impact. | D7: The cash flows from operations do not have a major inflows as of now, but in further quarters there would be inflows and cash outflows from Operations of NAO Spirits.

Sheet Shareholding patterns
A1: Radico Khaitan Ltd.
A2: Category of Shareholder | B2: 45901 | C2: 46082 | D2: Change (Mar 26 vs Sep 25)
A3: Promoter & Promoter Group Shareholders | B3: 10 | C3: 8 | D3: -2
A4: Promoter Shares Held | B4: 53829818 | C4: 53829818 | D4: No Change
A5: Promoter Holding (%) | B5: 0.4021 | C5: 0.402 | D5: -0.01 pp
A6: Public Shareholders | B6: 149241 | C6: 152028 | D6: =2787 -> 2787
A7: Public Shares Held | B7: 80047728 | C7: 80068115 | D7: 20387
A8: Public Holding (%) | B8: 0.5979 | C8: 0.598 | D8: 76161
A28: United Spirits Limited
A29: Category of Shareholder | B29: 45901 | C29: 46082 | D29: Change (Mar 26 vs Sep 25)
A30: Promoter & Promoter Group Shareholders | B30: 4 | C30: 4 | D30: No Change
A31: Promoter & Promoter Group Shares Held | B31: 4,12,22,410 | C31: 4,12,22,410 | D31: No Change
A32: Promoter Holding (%) | B32: 0.5667 | C32: 0.5667 | D32: No Change
A33: Public Shareholders | B33: 2,92,657 | C33: 3,23,934 | D33: 31277
A34: Public Shares Held | B34: 3,15,29,443 | C34: 3,15,29,443 | D34: No Change
A35: Public Holding (%) | B35: 0.4333 | C35: 0.4333 | D35: No Change

Sheet Shareholders Report Radico
A1: Number | B1: Investor Name | C1: % Outstanding | AB1: Position (M) | BA1: Position Change (M) | BZ1: Value ($, M) | CY1: Filing Date | DX1: Filing Source | EW1: Investor Type | EX1: Investor Sub-Type | EY1: Equity Assets ($, M) | EZ1: Investment Style | FA1: Turnover | FZ1: City | GA1: Country/Region
C2: Most Recent | D2: 46142 | E2: 46112 | F2: 46081 | G2: 46053 | H2: 46022 | I2: 45991 | J2: 45961 | K2: 45930 | L2: 45900 | M2: 45869 | N2: 45838 | O2: 45808 | P2: 45777 | Q2: 45747 | R2: 45716 | S2: 45688 | T2: 45657 | U2: 45626 | V2: 45596 | W2: 45565 | X2: 45535 | Y2: 45504 | Z2: 45473 | AA2: 45443 | AB2: Most Recent | AC2: 46142 | AD2: 46112 | AE2: 46081 | AF2: 46053 | AG2: 46022 | AH2: 45991 | AI2: 45961 | AJ2: 45930 | AK2: 45900 | AL2: 45869 | AM2: 45838 | AN2: 45808 | AO2: 45777 | AP2: 45747 | AQ2: 45716 | AR2: 45688 | AS2: 45657 | AT2: 45626 | AU2: 45596 | AV2: 45565 | AW2: 45535 | AX2: 45504 | AY2: 45473 | AZ2: 45443 | BA2: Most Recent | BB2: 46142 | BC2: 46112 | BD2: 46081 | BE2: 46053 | BF2: 46022 | BG2: 45991 | BH2: 45961 | BI2: 45930 | BJ2: 45900 | BK2: 45869 | BL2: 45838 | BM2: 45808 | BN2: 45777 | BO2: 45747 | BP2: 45716 | BQ2: 45688 | BR2: 45657 | BS2: 45626 | BT2: 45596 | BU2: 45565 | BV2: 45535 | BW2: 45504 | BX2: 45473 | BY2: 45443 | BZ2: Most Recent | CA2: 46142 | CB2: 46112 | CC2: 46081 | CD2: 46053 | CE2: 46022 | CF2: 45991 | CG2: 45961 | CH2: 45930 | CI2: 45900 | CJ2: 45869 | CK2: 45838 | CL2: 45808 | CM2: 45777 | CN2: 45747 | CO2: 45716 | CP2: 45688 | CQ2: 45657 | CR2: 45626 | CS2: 45596 | CT2: 45565 | CU2: 45535 | CV2: 45504 | CW2: 45473 | CX2: 45443 | CY2: Most Recent | CZ2: 46142 | DA2: 46112 | DB2: 46081 | DC2: 46053 | DD2: 46022 | DE2: 45991 | DF2: 45961 | DG2: 45930 | DH2: 45900 | DI2: 45869 | DJ2: 45838 | DK2: 45808 | DL2: 45777 | DM2: 45747 | DN2: 45716 | DO2: 45688 | DP2: 45657 | DQ2: 45626 | DR2: 45596 | DS2: 45565 | DT2: 45535 | DU2: 45504 | DV2: 45473 | DW2: 45443 | DX2: Most Recent | DY2: 46142 | DZ2: 46112 | EA2: 46081 | EB2: 46053 | EC2: 46022 | ED2: 45991 | EE2: 45961 | EF2: 45930 | EG2: 45900 | EH2: 45869 | EI2: 45838 | EJ2: 45808 | EK2: 45777 | EL2: 45747 | EM2: 45716 | EN2: 45688 | EO2: 45657 | EP2: 45626 | EQ2: 45596 | ER2: 45565 | ES2: 45535 | ET2: 45504 | EU2: 45473 | EV2: 45443 | FA2: Most Recent | FB2: 46142 | FC2: 46112 | FD2: 46081 | FE2: 46053 | FF2: 46022 | FG2: 45991 | FH2: 45961 | FI2: 45930 | FJ2: 45900 | FK2: 45869 | FL2: 45838 | FM2: 45808 | FN2: 45777 | FO2: 45747 | FP2: 45716 | FQ2: 45688 | FR2: 45657 | FS2: 45626 | FT2: 45596 | FU2: 45565 | FV2: 45535 | FW2: 45504 | FX2: 45473 | FY2: 45443
A3: 1 | B3: Sapphire Intrex, Ltd. | C3: 0.338824 | D3: 0.338908 | E3: 0.338908 | F3: 0.338919 | G3: 0.338919 | H3: 0.338919 | I3: 0.338919 | J3: 0.33896 | K3: 0.33896 | L3: 0.338985 | M3: 0.338985 | N3: 0.339096 | O3: 0.339096 | P3: 0.339137 | Q3: 0.339137 | R3: 0.339149 | S3: 0.339149 | T3: 0.339187 | U3: 0.339187 | V3: 0.339214 | W3: 0.33925 | X3: 0.33925 | Y3: 0.33925 | Z3: 0.339371 | AA3: 0.339371 | AB3: 45.379098 | AC3: 45.379098 | AD3: 45.379098 | AE3: 45.379098 | AF3: 45.379098 | AG3: 45.379098 | AH3: 45.379098 | AI3: 45.379098 | AJ3: 45.379098 | AK3: 45.379098 | AL3: 45.379098 | AM3: 45.379098 | AN3: 45.379098 | AO3: 45.379098 | AP3: 45.379098 | AQ3: 45.379098 | AR3: 45.379098 | AS3: 45.379098 | AT3: 45.379098 | AU3: 45.379098 | AV3: 45.379098 | AW3: 45.379098 | AX3: 45.379098 | AY3: 45.379098 | AZ3: 45.379098 | BA3: 0 | BB3: 0 | BC3: 0 | BD3: 0 | BE3: 0 | BF3: 0 | BG3: 0 | BH3: 0 | BI3: 0 | BJ3: 0 | BK3: 0 | BL3: 0 | BM3: 0 | BN3: 0 | BO3: 0 | BP3: 0 | BQ3: 0 | BR3: 0 | BS3: 0 | BT3: 0 | BU3: 0 | BV3: 0 | BW3: 0 | BX3: 0 | BY3: 0 | BZ3: 1667.7447 | CA3: 1667.7447 | CB3: 1667.7447 | CC3: 1667.7447 | CD3: 1667.7447 | CE3: 1667.7447 | CF3: 1477.8886 | CG3: 1477.8886 | CH3: 1477.8886 | CI3: 1390.0535 | CJ3: 1390.0535 | CK3: 1390.0535 | CL3: 1287.057 | CM3: 1287.057 | CN3: 1287.057 | CO3: 1383.5013 | CP3: 1383.5013 | CQ3: 1383.5013 | CR3: 1108.2404 | CS3: 1108.2404 | CT3: 1108.2404 | CU3: 972.55701 | CV3: 972.55701 | CW3: 972.55701 | CX3: 940.63414 | CY3: 46022 | CZ3: 46022 | DA3: 46022 | DB3: 46022 | DC3: 46022 | DD3: 46022 | DE3: 45930 | DF3: 45930 | DG3: 45930 | DH3: 45838 | DI3: 45838 | DJ3: 45838 | DK3: 45747 | DL3: 45747 | DM3: 45747 | DN3: 45657 | DO3: 45657 | DP3: 45657 | DQ3: 45565 | DR3: 45565 | DS3: 45565 | DT3: 45473 | DU3: 45473 | DV3: 45473 | DW3: 45382 | DX3: Shareholder Report | DY3: Shareholder Report | DZ3: Shareholder Report | EA3: Shareholder Report | EB3: Shareholder Report | EC3: Shareholder Report | ED3: Shareholder Report | EE3: Shareholder Report | EF3: Shareholder Report | EG3: Shareholder Report | EH3: Shareholder Report | EI3: Shareholder Report | EJ3: Shareholder Report | EK3: Shareholder Report | EL3: Shareholder Report | EM3: Shareholder Report | EN3: Shareholder Report | EO3: Shareholder Report | EP3: Shareholder Report | EQ3: Shareholder Report | ER3: Shareholder Report | ES3: Shareholder Report | ET3: Shareholder Report | EU3: Shareholder Report | EV3: Shareholder Report | EW3: Strategic Entities | EX3: Corporation | EY3: 1684.126 | FA3: Low | FB3: Low | FC3: Low | FD3: Low | FE3: Low | FF3: Low | FG3: Low | FH3: Low | FI3: Low | FJ3: Low | FK3: Low | FL3: Low | FM3: Low | FN3: Low | FO3: Low | FP3: Low | FQ3: Low | FR3: Low | FS3: Low | FT3: Low | FU3: Low | FV3: Low | FW3: Low | FX3: Low | FZ3: Kolkata | GA3: India
A4: 2 | B4: Rampur International, Ltd. | C4: 0.03923 | D4: 0.039239 | E4: 0.039239 | F4: 0.039241 | G4: 0.039241 | H4: 0.039241 | I4: 0.039241 | J4: 0.039245 | K4: 0.039245 | L4: 0.039248 | M4: 0.039248 | N4: 0.039261 | O4: 0.039261 | P4: 0.039266 | Q4: 0.039266 | R4: 0.039267 | S4: 0.039267 | T4: 0.039272 | U4: 0.039272 | V4: 0.039275 | W4: 0.039279 | X4: 0.039279 | Y4: 0.039279 | Z4: 0.039293 | AA4: 0.039293 | AB4: 5.254085 | AC4: 5.254085 | AD4: 5.254085 | AE4: 5.254085 | AF4: 5.254085 | AG4: 5.254085 | AH4: 5.254085 | AI4: 5.254085 | AJ4: 5.254085 | AK4: 5.254085 | AL4: 5.254085 | AM4: 5.254085 | AN4: 5.254085 | AO4: 5.254085 | AP4: 5.254085 | AQ4: 5.254085 | AR4: 5.254085 | AS4: 5.254085 | AT4: 5.254085 | AU4: 5.254085 | AV4: 5.254085 | AW4: 5.254085 | AX4: 5.254085 | AY4: 5.254085 | AZ4: 5.254085 | BA4: 0 | BB4: 0 | BC4: 0 | BD4: 0 | BE4: 0 | BF4: 0 | BG4: 0 | BH4: 0 | BI4: 0 | BJ4: 0 | BK4: 0 | BL4: 0 | BM4: 0 | BN4: 0 | BO4: 0 | BP4: 0 | BQ4: 0 | BR4: 0 | BS4: 0 | BT4: 0 | BU4: 0 | BV4: 0 | BW4: 0 | BX4: 0 | BY4: 0 | BZ4: 193.0949 | CA4: 193.0949 | CB4: 193.0949 | CC4: 193.0949 | CD4: 193.0949 | CE4: 193.0949 | CF4: 171.11298 | CG4: 171.11298 | CH4: 171.11298 | CI4: 160.94325 | CJ4: 160.94325 | CK4: 160.94325 | CL4: 149.0181 | CM4: 149.0181 | CN4: 149.0181 | CO4: 160.18462 | CP4: 160.18462 | CQ4: 160.18462 | CR4: 128.31435 | CS4: 128.31435 | CT4: 128.31435 | CU4: 112.60464 | CV4: 112.60464 | CW4: 112.60464 | CX4: 108.90855 | CY4: 46022 | CZ4: 46022 | DA4: 46022 | DB4: 46022 | DC4: 46022 | DD4: 46022 | DE4: 45930 | DF4: 45930 | DG4: 45930 | DH4: 45838 | DI4: 45838 | DJ4: 45838 | DK4: 45747 | DL4: 45747 | DM4: 45747 | DN4: 45657 | DO4: 45657 | DP4: 45657 | DQ4: 45565 | DR4: 45565 | DS4: 45565 | DT4: 45473 | DU4: 45473 | DV4: 45473 | DW4: 45382 | DX4: Shareholder Report | DY4: Shareholder Report | DZ4: Shareholder Report | EA4: Shareholder Report | EB4: Shareholder Report | EC4: Shareholder Report | ED4: Shareholder Report | EE4: Shareholder Report | EF4: Shareholder Report | EG4: Shareholder Report | EH4: Shareholder Report | EI4: Shareholder Report | EJ4: Shareholder Report | EK4: Shareholder Report | EL4: Shareholder Report | EM4: Shareholder Report | EN4: Shareholder Report | EO4: Shareholder Report | EP4: Shareholder Report | EQ4: Shareholder Report | ER4: Shareholder Report | ES4: Shareholder Report | ET4: Shareholder Report | EU4: Shareholder Report | EV4: Shareholder Report | EW4: Strategic Entities | EX4: Corporation | EY4: 193.0949 | FA4: Low | FB4: Low | FC4: Low | FD4: Low | FE4: Low | FF4: Low | FG4: Low | FH4: Low | FI4: Low | FJ4: Low | FK4: Low | FL4: Low | FM4: Low | FN4: Low | FO4: Low | FP4: Low | FQ4: Low | FR4: Low | FS4: Low | FT4: Low | FU4: Low | FV4: Low | FW4: Low | FX4: Low | FY4: Low | FZ4: New Delhi | GA4: India
A5: 3 | B5: Nippon Life India Asset Management Limited | C5: 0.033643 | D5: 0.033652 | E5: 0.033652 | F5: 0.033653 | G5: 0.033653 | H5: 0.033653 | I5: 0.034118 | J5: 0.034122 | K5: 0.034122 | L5: 0.033954 | M5: 0.033954 | N5: 0.033965 | O5: 0.033952 | P5: 0.033956 | Q5: 0.033956 | R5: 0.033798 | S5: 0.033798 | T5: 0.033802 | U5: 0.033554 | V5: 0.033556 | W5: 0.03356 | X5: 0.033539 | Y5: 0.033522 | Z5: 0.033501 | AA5: 0.031236 | AB5: 4.505876 | AC5: 4.505876 | AD5: 4.505876 | AE5: 4.505876 | AF5: 4.505876 | AG5: 4.505876 | AH5: 4.568193 | AI5: 4.568193 | AJ5: 4.568193 | AK5: 4.545307 | AL5: 4.545307 | AM5: 4.545307 | AN5: 4.543547 | AO5: 4.543547 | AP5: 4.543547 | AQ5: 4.522315 | AR5: 4.522315 | AS5: 4.522315 | AT5: 4.489057 | AU5: 4.489057 | AV5: 4.489057 | AW5: 4.486325 | AX5: 4.484041 | AY5: 4.479541 | AZ5: 4.176719 | BA5: 0 | BB5: 0 | BC5: 0 | BD5: 0 | BE5: 0 | BF5: -0.062317 | BG5: 0 | BH5: 0 | BI5: 0.022886 | BJ5: 0 | BK5: 0 | BL5: 0.00176 | BM5: 0 | BN5: 0 | BO5: 0.021232 | BP5: 0 | BQ5: 0 | BR5: 0.033258 | BS5: 0 | BT5: 0 | BU5: 0.002732 | BV5: 0.002284 | BW5: 0.0045 | BX5: 0.302822 | BY5: 0.003332 | BZ5: 165.59718 | CA5: 165.59718 | CB5: 165.59718 | CC5: 165.59718 | CD5: 165.59718 | CE5: 165.59718 | CF5: 148.77512 | CG5: 148.77512 | CH5: 148.77512 | CI5: 139.23195 | CJ5: 139.23195 | CK5: 139.23195 | CL5: 128.86558 | CM5: 128.86558 | CN5: 128.86558 | CO5: 137.87468 | CP5: 137.87468 | CQ5: 137.87468 | CR5: 109.63097 | CS5: 109.63097 | CT5: 109.63097 | CU5: 103.88672 | CV5: 92.333555 | CW5: 96.004751 | CX5: 78.929295 | CY5: 46022 | CZ5: 46022 | DA5: 46022 | DB5: 46022 | DC5: 46022 | DD5: 46022 | DE5: 45930 | DF5: 45930 | DG5: 45930 | DH5: 45838 | DI5: 45838 | DJ5: 45838 | DK5: 45747 | DL5: 45747 | DM5: 45747 | DN5: 45657 | DO5: 45657 | DP5: 45657 | DQ5: 45565 | DR5: 45565 | DS5: 45565 | DT5: 45535 | DU5: 45504 | DV5: 45473 | DW5: 45443 | DX5: Shareholder Report | DY5: Shareholder Report | DZ5: Shareholder Report | EA5: Shareholder Report | EB5: Shareholder Report | EC5: Shareholder Report | ED5: Shareholder Report | EE5: Shareholder Report | EF5: Shareholder Report | EG5: Shareholder Report | EH5: Shareholder Report | EI5: Shareholder Report | EJ5: Shareholder Report | EK5: Shareholder Report | EL5: Shareholder Report | EM5: Shareholder Report | EN5: Shareholder Report | EO5: Shareholder Report | EP5: Shareholder Report | EQ5: Shareholder Report | ER5: Shareholder Report | ES5: Aggregate MFs | ET5: Aggregate MFs | EU5: Aggregate MFs | EV5: Aggregate MFs | EW5: Investment Managers | EX5: Investment Advisor | EY5: 54373.575 | EZ5: Core Growth | FA5: Low | FB5: Low | FC5: Low | FD5: Low | FE5: Low | FF5: Low | FG5: Low | FH5: Low | FI5: Low | FJ5: Low | FK5: Low | FL5: Low | FM5: Low | FN5: Low | FO5: Low | FP5: Low | FQ5: Low | FR5: Low | FS5: Low | FT5: Low | FU5: Low | FV5: Low | FW5: Low | FX5: Low | FY5: Low | FZ5: Mumbai | GA5: India
A6: 4 | B6: Tata Asset Management Ltd. | C6: 0.032837 | D6: 0.032845 | E6: 0.032845 | F6: 0.032846 | G6: 0.032846 | H6: 0.032846 | I6: 0.034141 | J6: 0.034145 | K6: 0.034145 | L6: 0.044901 | M6: 0.044901 | N6: 0.044916 | O6: 0.046101 | P6: 0.046107 | Q6: 0.046107 | R6: 0.046675 | S6: 0.046675 | T6: 0.046681 | U6: 0.052784 | V6: 0.052788 | W6: 0.052794 | X6: 0.055879 | Y6: 0.055879 | Z6: 0.055899 | AA6: 0.056017 | AB6: 4.39785 | AC6: 4.39785 | AD6: 4.39785 | AE6: 4.39785 | AF6: 4.39785 | AG6: 4.39785 | AH6: 4.571255 | AI6: 4.571255 | AJ6: 4.571255 | AK6: 6.010793 | AL6: 6.010793 | AM6: 6.010793 | AN6: 6.169453 | AO6: 6.169453 | AP6: 6.169453 | AQ6: 6.245312 | AR6: 6.245312 | AS6: 6.245312 | AT6: 7.061882 | AU6: 7.061882 | AV6: 7.061882 | AW6: 7.474539 | AX6: 7.474539 | AY6: 7.474539 | AZ6: 7.490339 | BA6: 0 | BB6: 0 | BC6: 0 | BD6: 0 | BE6: 0 | BF6: -0.173405 | BG6: 0 | BH6: 0 | BI6: -1.439538 | BJ6: 0 | BK6: 0 | BL6: -0.15866 | BM6: 0 | BN6: 0 | BO6: -0.075859 | BP6: 0 | BQ6: 0 | BR6: -0.81657 | BS6: 0 | BT6: 0 | BU6: -0.412657 | BV6: 0 | BW6: 0 | BX6: -0.0158 | BY6: 0 | BZ6: 161.62708 | CA6: 161.62708 | CB6: 161.62708 | CC6: 161.62708 | CD6: 161.62708 | CE6: 161.62708 | CF6: 148.87484 | CG6: 148.87484 | CH6: 148.87484 | CI6: 184.12275 | CJ6: 184.12275 | CK6: 184.12275 | CL6: 174.98007 | CM6: 174.98007 | CN6: 174.98007 | CO6: 190.40478 | CP6: 190.40478 | CQ6: 190.40478 | CR6: 172.46405 | CS6: 172.46405 | CT6: 172.46405 | CU6: 160.19303 | CV6: 160.19303 | CW6: 160.19303 | CX6: 155.26242 | CY6: 46022 | CZ6: 46022 | DA6: 46022 | DB6: 46022 | DC6: 46022 | DD6: 46022 | DE6: 45930 | DF6: 45930 | DG6: 45930 | DH6: 45838 | DI6: 45838 | DJ6: 45838 | DK6: 45747 | DL6: 45747 | DM6: 45747 | DN6: 45657 | DO6: 45657 | DP6: 45657 | DQ6: 45565 | DR6: 45565 | DS6: 45565 | DT6: 45473 | DU6: 45473 | DV6: 45473 | DW6: 45382 | DX6: Shareholder Report | DY6: Shareholder Report | DZ6: Shareholder Report | EA6: Shareholder Report | EB6: Shareholder Report | EC6: Shareholder Report | ED6: Shareholder Report | EE6: Shareholder Report | EF6: Shareholder Report | EG6: Shareholder Report | EH6: Shareholder Report | EI6: Shareholder Report | EJ6: Shareholder Report | EK6: Shareholder Report | EL6: Shareholder Report | EM6: Shareholder Report | EN6: Shareholder Report | EO6: Shareholder Report | EP6: Shareholder Report | EQ6: Shareholder Report | ER6: Shareholder Report | ES6: Shareholder Report | ET6: Shareholder Report | EU6: Shareholder Report | EV6: Shareholder Report | EW6: Investment Managers | EX6: Investment Advisor | EY6: 15766.072 | EZ6: Growth | FA6: Moderate | FB6: Moderate | FC6: Moderate | FD6: Moderate | FE6: Moderate | FF6: Moderate | FG6: Moderate | FH6: Moderate | FI6: Moderate | FJ6: Low | FK6: Low | FL6: Low | FM6: Low | FN6: Low | FO6: Low | FP6: Low | FQ6: Low | FR6: Low | FS6: Low | FT6: Low | FU6: Low | FV6: Low | FW6: Low | FX6: Moderate | FY6: Moderate | FZ6: Mumbai | GA6: India
A7: 5 | B7: Kotak Mahindra Asset Management Company Limited | C7: 0.029466 | D7: 0.029474 | E7: 0.029474 | F7: 0.029475 | G7: 0.029475 | H7: 0.029475 | I7: 0.029761 | J7: 0.029765 | K7: 0.029765 | L7: 0.028196 | M7: 0.028196 | N7: 0.028206 | O7: 0.028195 | P7: 0.028198 | Q7: 0.028198 | R7: 0.025427 | S7: 0.024284 | T7: 0.024208 | U7: 0.020284 | V7: 0.020282 | W7: 0.020195 | X7: 0.020272 | Y7: 0.020047 | Z7: 0.020047 | AA7: 0.019778 | AB7: 3.946477 | AC7: 3.946477 | AD7: 3.946477 | AE7: 3.946477 | AF7: 3.946477 | AG7: 3.946477 | AH7: 3.984849 | AI7: 3.984849 | AJ7: 3.984849 | AK7: 3.774575 | AL7: 3.774575 | AM7: 3.774575 | AN7: 3.773096 | AO7: 3.773096 | AP7: 3.773096 | AQ7: 3.402258 | AR7: 3.249263 | AS7: 3.238673 | AT7: 2.713714 | AU7: 2.713273 | AV7: 2.701342 | AW7: 2.711658 | AX7: 2.681489 | AY7: 2.680616 | AZ7: 2.644653 | BA7: 0 | BB7: 0 | BC7: 0 | BD7: 0 | BE7: 0 | BF7: -0.038372 | BG7: 0 | BH7: 0 | BI7: 0.210274 | BJ7: 0 | BK7: 0 | BL7: 0.001479 | BM7: 0 | BN7: 0 | BO7: 0.370838 | BP7: 0.152995 | BQ7: 0.01059 | BR7: 0.524959 | BS7: 0.000441 | BT7: 0.011931 | BU7: -0.010316 | BV7: 0.030169 | BW7: 0.000873 | BX7: 0.035963 | BY7: 0.012815 | BZ7: 145.03849 | CA7: 145.03849 | CB7: 145.03849 | CC7: 145.03849 | CD7: 145.03849 | CE7: 145.03849 | CF7: 129.777 | CG7: 129.777 | CH7: 129.777 | CI7: 115.62287 | CJ7: 115.62287 | CK7: 115.62287 | CL7: 107.0138 | CM7: 107.0138 | CN7: 107.0138 | CO7: 80.763208 | CP7: 81.786291 | CQ7: 98.739476 | CR7: 78.985161 | CS7: 72.365781 | CT7: 65.971703 | CU7: 62.791985 | CV7: 55.216135 | CW7: 57.4505 | CX7: 49.97717 | CY7: 46022 | CZ7: 46022 | DA7: 46022 | DB7: 46022 | DC7: 46022 | DD7: 46022 | DE7: 45930 | DF7: 45930 | DG7: 45930 | DH7: 45838 | DI7: 45838 | DJ7: 45838 | DK7: 45747 | DL7: 45747 | DM7: 45747 | DN7: 45716 | DO7: 45688 | DP7: 45657 | DQ7: 45626 | DR7: 45596 | DS7: 45565 | DT7: 45535 | DU7: 45504 | DV7: 45473 | DW7: 45443 | DX7: Shareholder Report | DY7: Shareholder Report | DZ7: Shareholder Report | EA7: Shareholder Report | EB7: Shareholder Report | EC7: Shareholder Report | ED7: Shareholder Report | EE7: Shareholder Report | EF7: Shareholder Report | EG7: Shareholder Report | EH7: Shareholder Report | EI7: Shareholder Report | EJ7: Shareholder Report | EK7: Shareholder Report | EL7: Shareholder Report | EM7: Aggregate MFs | EN7: Aggregate MFs | EO7: Aggregate MFs | EP7: Aggregate MFs | EQ7: Aggregate MFs | ER7: Aggregate MFs | ES7: Aggregate MFs | ET7: Aggregate MFs | EU7: Aggregate MFs | EV7: Aggregate MFs | EW7: Investment Managers | EX7: Investment Advisor | EY7: 43320.911 | EZ7: Growth | FA7: Low | FB7: Low | FC7: Low | FD7: Moderate | FE7: Moderate | FF7: Moderate | FG7: Moderate | FH7: Moderate | FI7: Moderate | FJ7: Moderate | FK7: Moderate | FL7: Moderate | FM7: Moderate | FN7: Moderate | FO7: Moderate | FP7: Moderate | FQ7: Moderate | FR7: Moderate | FS7: Moderate | FT7: Moderate | FU7: Moderate | FV7: Moderate | FW7: Moderate | FX7: Moderate | FY7: Moderate | FZ7: Mumbai | GA7: India
A8: 6 | B8: Classic Fintrex Pvt. Ltd. | C8: 0.019234 | D8: 0.019239 | E8: 0.019239 | F8: 0.01924 | G8: 0.01924 | H8: 0.01924 | I8: 0.01924 | J8: 0.019242 | K8: 0.019242 | L8: 0.019244 | M8: 0.019244 | N8: 0.01925 | O8: 0.01925 | P8: 0.019252 | Q8: 0.019252 | R8: 0.019253 | S8: 0.019253 | T8: 0.019255 | U8: 0.019255 | V8: 0.019257 | W8: 0.019259 | X8: 0.019259 | Y8: 0.019259 | Z8: 0.019266 | AA8: 0.019266 | AB8: 2.5761 | AC8: 2.5761 | AD8: 2.5761 | AE8: 2.5761 | AF8: 2.5761 | AG8: 2.5761 | AH8: 2.5761 | AI8: 2.5761 | AJ8: 2.5761 | AK8: 2.5761 | AL8: 2.5761 | AM8: 2.5761 | AN8: 2.5761 | AO8: 2.5761 | AP8: 2.5761 | AQ8: 2.5761 | AR8: 2.5761 | AS8: 2.5761 | AT8: 2.5761 | AU8: 2.5761 | AV8: 2.5761 | AW8: 2.5761 | AX8: 2.5761 | AY8: 2.5761 | AZ8: 2.5761 | BA8: 0 | BB8: 0 | BC8: 0 | BD8: 0 | BE8: 0 | BF8: 0 | BG8: 0 | BH8: 0 | BI8: 0 | BJ8: 0 | BK8: 0 | BL8: 0 | BM8: 0 | BN8: 0 | BO8: 0 | BP8: 0 | BQ8: 0 | BR8: 0 | BS8: 0 | BT8: 0 | BU8: 0 | BV8: 0 | BW8: 0 | BX8: 0 | BY8: 0 | BZ8: 94.675241 | CA8: 94.675241 | CB8: 94.675241 | CC8: 94.675241 | CD8: 94.675241 | CE8: 94.675241 | CF8: 83.897413 | CG8: 83.897413 | CH8: 83.897413 | CI8: 78.911153 | CJ8: 78.911153 | CK8: 78.911153 | CL8: 73.0642 | CM8: 73.0642 | CN8: 73.0642 | CO8: 78.539193 | CP8: 78.539193 | CQ8: 78.539193 | CR8: 62.913065 | CS8: 62.913065 | CT8: 62.913065 | CU8: 55.210531 | CV8: 55.210531 | CW8: 55.210531 | CX8: 53.39832 | CY8: 46022 | CZ8: 46022 | DA8: 46022 | DB8: 46022 | DC8: 46022 | DD8: 46022 | DE8: 45930 | DF8: 45930 | DG8: 45930 | DH8: 45838 | DI8: 45838 | DJ8: 45838 | DK8: 45747 | DL8: 45747 | DM8: 45747 | DN8: 45657 | DO8: 45657 | DP8: 45657 | DQ8: 45565 | DR8: 45565 | DS8: 45565 | DT8: 45473 | DU8: 45473 | DV8: 45473 | DW8: 45382 | DX8: Shareholder Report | DY8: Shareholder Report | DZ8: Shareholder Report | EA8: Shareholder Report | EB8: Shareholder Report | EC8: Shareholder Report | ED8: Shareholder Report | EE8: Shareholder Report | EF8: Shareholder Report | EG8: Shareholder Report | EH8: Shareholder Report | EI8: Shareholder Report | EJ8: Shareholder Report | EK8: Shareholder Report | EL8: Shareholder Report | EM8: Shareholder Report | EN8: Shareholder Report | EO8: Shareholder Report | EP8: Shareholder Report | EQ8: Shareholder Report | ER8: Shareholder Report | ES8: Shareholder Report | ET8: Shareholder Report | EU8: Shareholder Report | EV8: Shareholder Report | EW8: Strategic Entities | EX8: Corporation | EY8: 94.675241 | FA8: Low | FB8: Low | FC8: Low | FD8: Low | FE8: Low | FF8: Low | FG8: Low | FH8: Low | FI8: Low | FJ8: Low | FK8: Low | FL8: Low | FM8: Low | FN8: Low | FO8: Low | FP8: Low | FQ8: Low | FR8: Low | FS8: Low | FT8: Low | FU8: Low | FV8: Low | FW8: Low | FX8: Low | FY8: Low | FZ8: Kolkata | GA8: India
A9: 7 | B9: Vanguard Capital Management, LLC | C9: 0.018844 | D9: 0.018849 | E9: 0.018737 | F9: 0.017751 | G9: 0.01762 | H9: 0.017527 | I9: 0.017443 | J9: 0.01736 | K9: 0.01732 | L9: 0.017358 | M9: 0.017358 | N9: 0.017364 | O9: 0.018556 | P9: 0.018558 | Q9: 0.018593 | R9: 0.018515 | S9: 0.018459 | T9: 0.01843 | U9: 0.018668 | V9: 0.018599 | W9: 0.018558 | X9: 0.018558 | Y9: 0.018547 | Z9: 0.018534 | AA9: 0.018534 | AB9: 2.523786 | AC9: 2.523786 | AD9: 2.508878 | AE9: 2.376755 | AF9: 2.359179 | AG9: 2.346808 | AH9: 2.335562 | AI9: 2.32407 | AJ9: 2.318795 | AK9: 2.323738 | AL9: 2.323738 | AM9: 2.323738 | AN9: 2.483209 | AO9: 2.483209 | AP9: 2.487857 | AQ9: 2.477422 | AR9: 2.469842 | AS9: 2.465772 | AT9: 2.497572 | AU9: 2.488077 | AV9: 2.482427 | AW9: 2.482427 | AX9: 2.480884 | AY9: 2.478292 | AZ9: 2.478292 | BA9: 0 | BB9: 0.014908 | BC9: 0.132123 | BD9: 0.017576 | BE9: 0.012371 | BF9: 0.011246 | BG9: 0.011492 | BH9: 0.005275 | BI9: -0.004943 | BJ9: 0 | BK9: 0 | BL9: -0.159471 | BM9: 0 | BN9: -0.004648 | BO9: 0.010435 | BP9: 0.00758 | BQ9: 0.00407 | BR9: -0.0318 | BS9: 0.009495 | BT9: 0.00565 | BU9: 0 | BV9: 0.001543 | BW9: 0.002592 | BX9: 0 | BY9: 0 | BZ9: 91.082466 | CA9: 91.082466 | CB9: 69.6012 | CC9: 69.220674 | CD9: 72.697889 | CE9: 86.248443 | CF9: 83.862739 | CG9: 82.137861 | CH9: 75.517605 | CI9: 75.701084 | CJ9: 72.48593 | CK9: 71.180795 | CL9: 73.654972 | CM9: 71.634339 | CN9: 70.561423 | CO9: 58.80934 | CP9: 62.167702 | CQ9: 75.175553 | CR9: 72.694148 | CS9: 66.359572 | CT9: 60.625399 | CU9: 57.483842 | CV9: 51.085358 | CW9: 53.114327 | CX9: 46.833373 | CY9: 46142 | CZ9: 46142 | DA9: 46112 | DB9: 46081 | DC9: 46053 | DD9: 46022 | DE9: 45991 | DF9: 45961 | DG9: 45930 | DH9: 45900 | DI9: 45869 | DJ9: 45838 | DK9: 45808 | DL9: 45777 | DM9: 45747 | DN9: 45716 | DO9: 45688 | DP9: 45657 | DQ9: 45626 | DR9: 45596 | DS9: 45565 | DT9: 45535 | DU9: 45504 | DV9: 45473 | DW9: 45443 | DX9: Aggregate MFs | DY9: Aggregate MFs | DZ9: Aggregate MFs | EA9: Aggregate MFs | EB9: Aggregate MFs | EC9: Aggregate MFs | ED9: Aggregate MFs | EE9: Aggregate MFs | EF9: Aggregate MFs | EG9: Aggregate MFs | EH9: Aggregate MFs | EI9: Aggregate MFs | EJ9: Aggregate MFs | EK9: Aggregate MFs | EL9: Aggregate MFs | EM9: Aggregate MFs | EN9: Aggregate MFs | EO9: Aggregate MFs | EP9: Aggregate MFs | EQ9: Aggregate MFs | ER9: Aggregate MFs | ES9: Aggregate MFs | ET9: Aggregate MFs | EU9: Aggregate MFs | EV9: Aggregate MFs | EW9: Investment Managers | EX9: Investment Advisor | EY9: 6105646.3 | EZ9: Index | FZ9: Malvern | GA9: United States
A10: 8 | B10: HSBC Global Asset Management (India) Private Limited | C10: 0.018104 | D10: 0.018108 | E10: 0.018108 | F10: 0.018109 | G10: 0.018109 | H10: 0.018109 | I10: 0.020473 | J10: 0.020475 | K10: 0.020475 | L10: 0.018724 | M10: 0.018724 | N10: 0.01873 | O10: 0.018917 | P10: 0.018919 | Q10: 0.018919 | R10: 0.012093 | S10: 0.012093 | T10: 0.012094 | U10: 0.010153 | V10: 0.009773 | W10: 0.009774 | X10: 0.00913 | Y10: 0.009002 | Z10: 0.009463 | AA10: 0.008891 | AB10: 2.42467 | AC10: 2.42467 | AD10: 2.42467 | AE10: 2.42467 | AF10: 2.42467 | AG10: 2.42467 | AH10: 2.741203 | AI10: 2.741203 | AJ10: 2.741203 | AK10: 2.506502 | AL10: 2.506502 | AM10: 2.506502 | AN10: 2.531502 | AO10: 2.531502 | AP10: 2.531502 | AQ10: 1.618015 | AR10: 1.618015 | AS10: 1.618015 | AT10: 1.358303 | AU10: 1.307356 | AV10: 1.307356 | AW10: 1.221194 | AX10: 1.204076 | AY10: 1.265323 | AZ10: 1.188823 | BA10: 0 | BB10: 0 | BC10: 0 | BD10: 0 | BE10: 0 | BF10: -0.316533 | BG10: 0 | BH10: 0 | BI10: 0.234701 | BJ10: 0 | BK10: 0 | BL10: -0.025 | BM10: 0 | BN10: 0 | BO10: 0.913487 | BP10: 0 | BQ10: 0 | BR10: 0.259712 | BS10: 0.050947 | BT10: 0 | BU10: 0.086162 | BV10: 0.017118 | BW10: -0.061247 | BX10: 0.0765 | BY10: 0.155423 | BZ10: 89.109979 | CA10: 89.109979 | CB10: 89.109979 | CC10: 89.109979 | CD10: 89.109979 | CE10: 89.109979 | CF10: 89.274423 | CG10: 89.274423 | CH10: 89.274423 | CI10: 76.779226 | CJ10: 76.779226 | CK10: 76.779226 | CL10: 71.799297 | CM10: 71.799297 | CN10: 71.799297 | CO10: 49.329449 | CP10: 49.329449 | CQ10: 49.329449 | CR10: 39.534668 | CS10: 34.868529 | CT10: 31.92802 | CU10: 28.278343 | CV10: 24.793845 | CW10: 27.118185 | CX10: 22.465711 | CY10: 46022 | CZ10: 46022 | DA10: 46022 | DB10: 46022 | DC10: 46022 | DD10: 46022 | DE10: 45930 | DF10: 45930 | DG10: 45930 | DH10: 45838 | DI10: 45838 | DJ10: 45838 | DK10: 45747 | DL10: 45747 | DM10: 45747 | DN10: 45657 | DO10: 45657 | DP10: 45657 | DQ10: 45626 | DR10: 45596 | DS10: 45565 | DT10: 45535 | DU10: 45504 | DV10: 45473 | DW10: 45443 | DX10: Shareholder Report | DY10: Shareholder Report | DZ10: Shareholder Report | EA10: Shareholder Report | EB10: Shareholder Report | EC10: Shareholder Report | ED10: Shareholder Report | EE10: Shareholder Report | EF10: Shareholder Report | EG10: Shareholder Report | EH10: Shareholder Report | EI10: Shareholder Report | EJ10: Shareholder Report | EK10: Shareholder Report | EL10: Shareholder Report | EM10: Shareholder Report | EN10: Shareholder Report | EO10: Shareholder Report | EP10: Aggregate MFs | EQ10: Aggregate MFs | ER10: Aggregate MFs | ES10: Aggregate MFs | ET10: Aggregate MFs | EU10: Aggregate MFs | EV10: Aggregate MFs | EW10: Investment Managers | EX10: Investment Advisor | EY10: 9607.0922 | EZ10: GARP | FA10: Moderate | FB10: Moderate | FC10: Low | FD10: Low | FE10: Moderate | FF10: Moderate | FG10: Moderate | FH10: Low | FI10: Low | FJ10: Low | FK10: Moderate | FL10: Low | FM10: Moderate | FN10: Moderate | FO10: Moderate | FP10: Moderate | FQ10: Moderate | FR10: Moderate | FS10: Moderate | FT10: Moderate | FU10: Moderate | FV10: Moderate | FW10: Moderate | FX10: Moderate | FY10: Moderate | FZ10: Mumbai | GA10: India
A11: 9 | B11: Aditya Birla Sun Life AMC Limited | C11: 0.017646 | D11: 0.01765 | E11: 0.01765 | F11: 0.017651 | G11: 0.017651 | H11: 0.017651 | I11: 0.019944 | J11: 0.019946 | K11: 0.019946 | L11: 0.023361 | M11: 0.023361 | N11: 0.023369 | O11: 0.026111 | P11: 0.026114 | Q11: 0.026114 | R11: 0.026105 | S11: 0.026019 | T11: 0.026948 | U11: 0.029787 | V11: 0.032503 | W11: 0.033865 | X11: 0.035225 | Y11: 0.035018 | Z11: 0.035037 | AA11: 0.035002 | AB11: 2.363299 | AC11: 2.363299 | AD11: 2.363299 | AE11: 2.363299 | AF11: 2.363299 | AG11: 2.363299 | AH11: 2.670306 | AI11: 2.670306 | AJ11: 2.670306 | AK11: 3.127343 | AL11: 3.127343 | AM11: 3.127343 | AN11: 3.494217 | AO11: 3.494217 | AP11: 3.494217 | AQ11: 3.49296 | AR11: 3.481408 | AS11: 3.605296 | AT11: 3.985128 | AU11: 4.348214 | AV11: 4.529856 | AW11: 4.711748 | AX11: 4.684117 | AY11: 4.68501 | AZ11: 4.680251 | BA11: 0 | BB11: 0 | BC11: 0 | BD11: 0 | BE11: 0 | BF11: -0.307007 | BG11: 0 | BH11: 0 | BI11: -0.457037 | BJ11: 0 | BK11: 0 | BL11: -0.366874 | BM11: 0 | BN11: 0 | BO11: 0.001257 | BP11: 0.011552 | BQ11: -0.123888 | BR11: -0.379832 | BS11: -0.363086 | BT11: -0.181642 | BU11: -0.181892 | BV11: 0.027631 | BW11: -0.000893 | BX11: 0.004759 | BY11: 0.00078 | BZ11: 86.85451 | CA11: 86.85451 | CB11: 86.85451 | CC11: 86.85451 | CD11: 86.85451 | CE11: 86.85451 | CF11: 86.965477 | CG11: 86.965477 | CH11: 86.965477 | CI11: 95.796841 | CJ11: 95.796841 | CK11: 95.796841 | CL11: 99.104138 | CM11: 99.104138 | CN11: 99.104138 | CO11: 82.916303 | CP11: 87.629547 | CQ11: 109.91694 | CR11: 115.99084 | CS11: 115.97134 | CT11: 110.62735 | CU11: 109.10668 | CV11: 96.453439 | CW11: 100.40833 | CX11: 88.444761 | CY11: 46022 | CZ11: 46022 | DA11: 46022 | DB11: 46022 | DC11: 46022 | DD11: 46022 | DE11: 45930 | DF11: 45930 | DG11: 45930 | DH11: 45838 | DI11: 45838 | DJ11: 45838 | DK11: 45747 | DL11: 45747 | DM11: 45747 | DN11: 45716 | DO11: 45688 | DP11: 45657 | DQ11: 45626 | DR11: 45596 | DS11: 45565 | DT11: 45535 | DU11: 45504 | DV11: 45473 | DW11: 45443 | DX11: Shareholder Report | DY11: Shareholder Report | DZ11: Shareholder Report | EA11: Shareholder Report | EB11: Shareholder Report | EC11: Shareholder Report | ED11: Shareholder Report | EE11: Shareholder Report | EF11: Shareholder Report | EG11: Shareholder Report | EH11: Shareholder Report | EI11: Shareholder Report | EJ11: Shareholder Report | EK11: Shareholder Report | EL11: Shareholder Report | EM11: Aggregate MFs | EN11: Aggregate MFs | EO11: Aggregate MFs | EP11: Aggregate MFs | EQ11: Aggregate MFs | ER11: Aggregate MFs | ES11: Aggregate MFs | ET11: Aggregate MFs | EU11: Aggregate MFs | EV11: Aggregate MFs | EW11: Investment Managers | EX11: Investment Advisor | EY11: 34858.816 | EZ11: Core Growth | FA11: Moderate | FB11: Moderate | FC11: Moderate | FD11: Moderate | FE11: Moderate | FF11: Moderate | FG11: Low | FH11: Low | FI11: Low | FJ11: Low | FK11: Low | FL11: Low | FM11: Low | FN11: Low | FO11: Low | FP11: Low | FQ11: Low | FR11: Low | FS11: Low | FT11: Low | FU11: Low | FV11: Low | FW11: Low | FX11: Low | FY11: Low | FZ11: Mumbai | GA11: India
A12: 10 | B12: TIMF Holdings | C12: 0.016473 | D12: 0.016477 | E12: 0.016477 | F12: 0.016477 | G12: 0.016477 | H12: 0.016477 | I12: 0.019175 | J12: 0.019177 | K12: 0.019177 | L12: 0.023422 | M12: 0.023422 | N12: 0.02343 | O12: 0.023972 | P12: 0.023975 | Q12: 0.023975 | R12: 0.023976 | S12: 0.023976 | T12: 0.023979 | U12: 0.023979 | V12: 0.023981 | W12: 0.023983 | X12: 0.024221 | Y12: 0.024221 | Z12: 0.024229 | AA12: 0.026099 | AB12: 2.206226 | AC12: 2.206226 | AD12: 2.206226 | AE12: 2.206226 | AF12: 2.206226 | AG12: 2.206226 | AH12: 2.567347 | AI12: 2.567347 | AJ12: 2.567347 | AK12: 3.135466 | AL12: 3.135466 | AM12: 3.135466 | AN12: 3.208082 | AO12: 3.208082 | AP12: 3.208082 | AQ12: 3.208082 | AR12: 3.208082 | AS12: 3.208082 | AT12: 3.208082 | AU12: 3.208082 | AV12: 3.208082 | AW12: 3.239819 | AX12: 3.239819 | AY12: 3.239819 | AZ12: 3.489819 | BA12: 0 | BB12: 0 | BC12: 0 | BD12: 0 | BE12: 0 | BF12: -0.361121 | BG12: 0 | BH12: 0 | BI12: -0.568119 | BJ12: 0 | BK12: 0 | BL12: -0.072616 | BM12: 0 | BN12: 0 | BO12: 0 | BP12: 0 | BQ12: 0 | BR12: 0 | BS12: 0 | BT12: 0 | BU12: -0.031737 | BV12: 0 | BW12: 0 | BX12: -0.25 | BY12: 0 | BZ12: 81.08186 | CA12: 81.08186 | CB12: 81.08186 | CC12: 81.08186 | CD12: 81.08186 | CE12: 81.08186 | CF12: 83.612349 | CG12: 83.612349 | CH12: 83.612349 | CI12: 96.045665 | CJ12: 96.045665 | CK12: 96.045665 | CL12: 90.988683 | CM12: 90.988683 | CN12: 90.988683 | CO12: 97.806829 | CP12: 97.806829 | CQ12: 97.806829 | CR12: 78.347219 | CS12: 78.347219 | CT12: 78.347219 | CU12: 69.435243 | CV12: 69.435243 | CW12: 69.435243 | CX12: 72.338214 | CY12: 46022 | CZ12: 46022 | DA12: 46022 | DB12: 46022 | DC12: 46022 | DD12: 46022 | DE12: 45930 | DF12: 45930 | DG12: 45930 | DH12: 45838 | DI12: 45838 | DJ12: 45838 | DK12: 45747 | DL12: 45747 | DM12: 45747 | DN12: 45657 | DO12: 45657 | DP12: 45657 | DQ12: 45565 | DR12: 45565 | DS12: 45565 | DT12: 45473 | DU12: 45473 | DV12: 45473 | DW12: 45382 | DX12: Shareholder Report | DY12: Shareholder Report | DZ12: Shareholder Report | EA12: Shareholder Report | EB12: Shareholder Report | EC12: Shareholder Report | ED12: Shareholder Report | EE12: Shareholder Report | EF12: Shareholder Report | EG12: Shareholder Report | EH12: Shareholder Report | EI12: Shareholder Report | EJ12: Shareholder Report | EK12: Shareholder Report | EL12: Shareholder Report | EM12: Shareholder Report | EN12: Shareholder Report | EO12: Shareholder Report | EP12: Shareholder Report | EQ12: Shareholder Report | ER12: Shareholder Report | ES12: Shareholder Report | ET12: Shareholder Report | EU12: Shareholder Report | EV12: Shareholder Report | EW12: Strategic Entities | EX12: Corporation | EY12: 248.02853 | FA12: Low | FB12: Low | FC12: Low | FD12: Low | FE12: Low | FF12: Low | FG12: Low | FH12: Low | FI12: Low | FJ12: Low | FK12: Low | FL12: Low | FM12: Low | FN12: Low | FO12: Low | FP12: Low | FQ12: Low | FR12: Low | FS12: Low | FT12: Low | FU12: Low | FV12: Low | FW12: Low | FX12: Low | FY12: Low | GA12: Mauritius
A13: 11 | B13: Canara Robeco Asset Management Company Ltd. | C13: 0.013626 | D13: 0.01363 | E13: 0.013784 | F13: 0.010243 | G13: 0.009111 | H13: 0.008899 | I13: 0.0087 | J13: 0.008701 | K13: 0.008062 | L13: 0.008012 | M13: 0.007242 | N13: 0.006407 | O13: 0.004855 | P13: 0.004613 | Q13: 0.004613 | R13: 0.004613 | S13: 0.003369 | T13: 0.002292 | AB13: 1.824974 | AC13: 1.824974 | AD13: 1.845657 | AE13: 1.371438 | AF13: 1.21992 | AG13: 1.191536 | AH13: 1.16491 | AI13: 1.16491 | AJ13: 1.07936 | AK13: 1.07256 | AL13: 0.969446 | AM13: 0.857446 | AN13: 0.649734 | AO13: 0.617287 | AP13: 0.617287 | AQ13: 0.617287 | AR13: 0.450835 | AS13: 0.306669 | BA13: 0 | BB13: -0.020683 | BC13: 0.474219 | BD13: 0.151518 | BE13: 0.028384 | BF13: 0.026626 | BG13: 0 | BH13: 0.08555 | BI13: 0.0068 | BJ13: 0.103114 | BK13: 0.112 | BL13: 0.207712 | BM13: 0.032447 | BN13: 0 | BO13: 0 | BP13: 0.166452 | BQ13: 0.144166 | BR13: 0.306669 | BZ13: 65.862609 | CA13: 65.862609 | CB13: 51.202148 | CC13: 39.941796 | CD13: 37.591725 | CE13: 43.790598 | CF13: 41.828281 | CG13: 41.17054 | CH13: 35.152172 | CI13: 34.941097 | CJ13: 30.240584 | CK13: 26.265305 | CL13: 19.271894 | CM13: 17.807179 | CN13: 17.507698 | CO13: 14.653233 | CP13: 11.347842 | CQ13: 9.3496121 | CY13: 46142 | CZ13: 46142 | DA13: 46112 | DB13: 46081 | DC13: 46053 | DD13: 46022 | DE13: 45991 | DF13: 45961 | DG13: 45930 | DH13: 45900 | DI13: 45869 | DJ13: 45838 | DK13: 45808 | DL13: 45777 | DM13: 45747 | DN13: 45716 | DO13: 45688 | DP13: 45657 | DX13: Aggregate MFs | DY13: Aggregate MFs | DZ13: Aggregate MFs | EA13: Aggregate MFs | EB13: Aggregate MFs | EC13: Aggregate MFs | ED13: Aggregate MFs | EE13: Aggregate MFs | EF13: Aggregate MFs | EG13: Aggregate MFs | EH13: Aggregate MFs | EI13: Aggregate MFs | EJ13: Aggregate MFs | EK13: Aggregate MFs | EL13: Aggregate MFs | EM13: Aggregate MFs | EN13: Aggregate MFs | EO13: Aggregate MFs | EW13: Investment Managers | EX13: Investment Advisor | EY13: 11263.419 | EZ13: Growth | FA13: Low | FB13: Low | FC13: Low | FD13: Low | FE13: Low | FF13: Low | FG13: Low | FH13: Low | FI13: Low | FJ13: Low | FK13: Low | FL13: Low | FM13: Low | FN13: Low | FO13: Low | FP13: Low | FQ13: Low | FR13: Low | FZ13: Mumbai | GA13: India
A14: 12 | B14: Investor Education Protection Fund | C14: 0.013063 | D14: 0.013066 | E14: 0.013066 | F14: 0.013066 | G14: 0.013066 | H14: 0.013066 | I14: 0.012929 | J14: 0.012931 | K14: 0.012931 | L14: 0.013109 | M14: 0.013109 | N14: 0.013113 | O14: 0.013159 | P14: 0.01316 | Q14: 0.01316 | R14: 0.013204 | S14: 0.013204 | T14: 0.013206 | U14: 0.012857 | V14: 0.012858 | W14: 0.012859 | X14: 0.012889 | Y14: 0.012889 | Z14: 0.012893 | AA14: 0.012917 | AB14: 1.749508 | AC14: 1.749508 | AD14: 1.749508 | AE14: 1.749508 | AF14: 1.749508 | AG14: 1.749508 | AH14: 1.731143 | AI14: 1.731143 | AJ14: 1.731143 | AK14: 1.754863 | AL14: 1.754863 | AM14: 1.754863 | AN14: 1.760953 | AO14: 1.760953 | AP14: 1.760953 | AQ14: 1.766748 | AR14: 1.766748 | AS14: 1.766748 | AT14: 1.720108 | AU14: 1.720108 | AV14: 1.720108 | AW14: 1.724033 | AX14: 1.724033 | AY14: 1.724033 | AZ14: 1.727183 | BA14: 0 | BB14: 0 | BC14: 0 | BD14: 0 | BE14: 0 | BF14: 0.018365 | BG14: 0 | BH14: 0 | BI14: -0.02372 | BJ14: 0 | BK14: 0 | BL14: -0.00609 | BM14: 0 | BN14: 0 | BO14: -0.005795 | BP14: 0 | BQ14: 0 | BR14: 0.04664 | BS14: 0 | BT14: 0 | BU14: -0.003925 | BV14: 0 | BW14: 0 | BX14: -0.00315 | BY14: 0 | BZ14: 64.296841 | CA14: 64.296841 | CB14: 64.296841 | CC14: 64.296841 | CD14: 64.296841 | CE14: 64.296841 | CF14: 56.379185 | CG14: 56.379185 | CH14: 56.379185 | CI14: 53.755003 | CJ14: 53.755003 | CK14: 53.755003 | CL14: 49.944731 | CM14: 49.944731 | CN14: 49.944731 | CO14: 53.863966 | CP14: 53.863966 | CQ14: 53.863966 | CR14: 42.008178 | CS14: 42.008178 | CT14: 42.008178 | CU14: 36.949178 | CV14: 36.949178 | CW14: 36.949178 | CX14: 35.801666 | CY14: 46022 | CZ14: 46022 | DA14: 46022 | DB14: 46022 | DC14: 46022 | DD14: 46022 | DE14: 45930 | DF14: 45930 | DG14: 45930 | DH14: 45838 | DI14: 45838 | DJ14: 45838 | DK14: 45747 | DL14: 45747 | DM14: 45747 | DN14: 45657 | DO14: 45657 | DP14: 45657 | DQ14: 45565 | DR14: 45565 | DS14: 45565 | DT14: 45473 | DU14: 45473 | DV14: 45473 | DW14: 45382 | DX14: Shareholder Report | DY14: Shareholder Report | DZ14: Shareholder Report | EA14: Shareholder Report | EB14: Shareholder Report | EC14: Shareholder Report | ED14: Shareholder Report | EE14: Shareholder Report | EF14: Shareholder Report | EG14: Shareholder Report | EH14: Shareholder Report | EI14: Shareholder Report | EJ14: Shareholder Report | EK14: Shareholder Report | EL14: Shareholder Report | EM14: Shareholder Report | EN14: Shareholder Report | EO14: Shareholder Report | EP14: Shareholder Report | EQ14: Shareholder Report | ER14: Shareholder Report | ES14: Shareholder Report | ET14: Shareholder Report | EU14: Shareholder Report | EV14: Shareholder Report | EW14: Strategic Entities | EX14: Corporation | EY14: 9985.9213 | FA14: Low | FB14: Low | FC14: Low | FD14: Low | FE14: Low | FF14: Low | FG14: Low | FH14: Low | FI14: Low | FJ14: Low | FK14: Low | FL14: Low | FM14: Low | FN14: Low | FO14: Low | FP14: Low | FQ14: Low | FR14: Low | FS14: Low | FT14: Low | FU14: Low | FV14: Low | FW14: Low | FX14: Low | FY14: Low | FZ14: New Delhi | GA14: India
A15: 13 | B15: Motilal Oswal Asset Management Company Ltd. | C15: 0.011861 | D15: 0.011863 | E15: 0.003905 | F15: 0.002766 | G15: 0.002621 | H15: 0.002979 | I15: 0.002956 | J15: 0.002949 | K15: 0.002815 | L15: 0.003616 | M15: 0.002222 | N15: 0.002437 | O15: 0.002476 | P15: 0.002468 | Q15: 0.002424 | R15: 0.002198 | S15: 0.002434 | T15: 0.002395 | U15: 0.000352 | V15: 0.000341 | W15: 0.000337 | X15: 0.000345 | Y15: 0.000322 | Z15: 0.0003 | AA15: 0.000293 | AB15: 1.588498 | AC15: 1.588498 | AD15: 0.522862 | AE15: 0.370371 | AF15: 0.350987 | AG15: 0.398803 | AH15: 0.395825 | AI15: 0.394794 | AJ15: 0.376855 | AK15: 0.484078 | AL15: 0.297473 | AM15: 0.326133 | AN15: 0.33136 | AO15: 0.330254 | AP15: 0.324316 | AQ15: 0.294064 | AR15: 0.325706 | AS15: 0.320414 | AT15: 0.047097 | AU15: 0.045611 | AV15: 0.045014 | AW15: 0.046186 | AX15: 0.043079 | AY15: 0.040108 | AZ15: 0.039199 | BA15: 0 | BB15: 1.065636 | BC15: 0.152491 | BD15: 0.019384 | BE15: -0.047816 | BF15: 0.002978 | BG15: 0.001031 | BH15: 0.017939 | BI15: -0.107223 | BJ15: 0.186605 | BK15: -0.02866 | BL15: -0.005227 | BM15: 0.001106 | BN15: 0.005938 | BO15: 0.030252 | BP15: -0.031642 | BQ15: 0.005292 | BR15: 0.273317 | BS15: 0.001486 | BT15: 0.000597 | BU15: -0.001172 | BV15: 0.003107 | BW15: 0.002971 | BX15: 0.000909 | BY15: 0.00017 | BZ15: 57.328282 | CA15: 57.328282 | CB15: 14.505218 | CC15: 10.786695 | CD15: 10.815633 | CE15: 14.656562 | CF15: 14.21284 | CG15: 13.952908 | CH15: 12.273266 | CI15: 15.769949 | CJ15: 9.2792763 | CK15: 9.9901134 | CL15: 9.8285371 | CM15: 9.5269979 | CN15: 9.1983576 | CO15: 6.9805265 | CP15: 8.1982547 | CQ15: 9.7686646 | CR15: 1.3708018 | CS15: 1.2164923 | CT15: 1.0993241 | CU15: 1.0694972 | CV15: 0.88706531 | CW15: 0.85958775 | CX15: 0.74076073 | CY15: 46142 | CZ15: 46142 | DA15: 46112 | DB15: 46081 | DC15: 46053 | DD15: 46022 | DE15: 45991 | DF15: 45961 | DG15: 45930 | DH15: 45900 | DI15: 45869 | DJ15: 45838 | DK15: 45808 | DL15: 45777 | DM15: 45747 | DN15: 45716 | DO15: 45688 | DP15: 45657 | DQ15: 45626 | DR15: 45596 | DS15: 45565 | DT15: 45535 | DU15: 45504 | DV15: 45473 | DW15: 45443 | DX15: Aggregate MFs | DY15: Aggregate MFs | DZ15: Aggregate MFs | EA15: Aggregate MFs | EB15: Aggregate MFs | EC15: Aggregate MFs | ED15: Aggregate MFs | EE15: Aggregate MFs | EF15: Aggregate MFs | EG15: Aggregate MFs | EH15: Aggregate MFs | EI15: Aggregate MFs | EJ15: Aggregate MFs | EK15: Aggregate MFs | EL15: Aggregate MFs | EM15: Aggregate MFs | EN15: Aggregate MFs | EO15: Aggregate MFs | EP15: Aggregate MFs | EQ15: Aggregate MFs | ER15: Aggregate MFs | ES15: Aggregate MFs | ET15: Aggregate MFs | EU15: Aggregate MFs | EV15: Aggregate MFs | EW15: Investment Managers | EX15: Investment Advisor | EY15: 14769.322 | EZ15: GARP | FA15: Moderate | FB15: Low | FC15: Low | FD15: Moderate | FE15: Moderate | FF15: Moderate | FG15: Moderate | FH15: Moderate | FI15: Moderate | FJ15: Moderate | FK15: Moderate | FL15: Moderate | FM15: Moderate | FN15: Moderate | FO15: Moderate | FP15: Moderate | FQ15: Moderate | FR15: Moderate | FS15: Moderate | FT15: Moderate | FU15: Moderate | FV15: Moderate | FW15: Moderate | FX15: Moderate | FY15: Moderate | FZ15: Mumbai | GA15: India
A16: 14 | B16: Edelweiss Asset Management Ltd. | C16: 0.011722 | D16: 0.011725 | E16: 0.011725 | F16: 0.011725 | G16: 0.011725 | H16: 0.011725 | I16: 0.011724 | J16: 0.011725 | K16: 0.011725 | L16: 0.012253 | M16: 0.012253 | N16: 0.012257 | O16: 0.01213 | P16: 0.012132 | Q16: 0.012132 | R16: 0.011945 | S16: 0.011945 | T16: 0.011946 | U16: 0.011402 | V16: 0.011141 | W16: 0.010883 | X16: 0.010106 | Y16: 0.009419 | Z16: 0.00942 | AA16: 0.007955 | AB16: 1.569959 | AC16: 1.569959 | AD16: 1.569959 | AE16: 1.569959 | AF16: 1.569959 | AG16: 1.569959 | AH16: 1.569765 | AI16: 1.569765 | AJ16: 1.569765 | AK16: 1.640274 | AL16: 1.640274 | AM16: 1.640274 | AN16: 1.623338 | AO16: 1.623338 | AP16: 1.623338 | AQ16: 1.598275 | AR16: 1.598275 | AS16: 1.598275 | AT16: 1.525514 | AU16: 1.490352 | AV16: 1.455686 | AW16: 1.351748 | AX16: 1.259909 | AY16: 1.259661 | AZ16: 1.063689 | BA16: 0 | BB16: 0 | BC16: 0 | BD16: 0 | BE16: 0 | BF16: 0.000194 | BG16: 0 | BH16: 0 | BI16: -0.070509 | BJ16: 0 | BK16: 0 | BL16: 0.016936 | BM16: 0 | BN16: 0 | BO16: 0.025063 | BP16: 0 | BQ16: 0 | BR16: 0.072761 | BS16: 0.035162 | BT16: 0.034666 | BU16: 0.103938 | BV16: 0.091839 | BW16: 0.000248 | BX16: 0.195972 | BY16: 0.092882 | BZ16: 57.698167 | CA16: 57.698167 | CB16: 57.698167 | CC16: 57.698167 | CD16: 57.698167 | CE16: 57.698167 | CF16: 51.12349 | CG16: 51.12349 | CH16: 51.12349 | CI16: 50.24491 | CJ16: 50.24491 | CK16: 50.24491 | CL16: 46.041649 | CM16: 46.041649 | CN16: 46.041649 | CO16: 48.727623 | CP16: 48.727623 | CQ16: 48.727623 | CR16: 44.401499 | CS16: 39.74922 | CT16: 35.55051 | CU16: 31.301492 | CV16: 25.943535 | CW16: 26.996838 | CX16: 20.100999 | CY16: 46022 | CZ16: 46022 | DA16: 46022 | DB16: 46022 | DC16: 46022 | DD16: 46022 | DE16: 45930 | DF16: 45930 | DG16: 45930 | DH16: 45838 | DI16: 45838 | DJ16: 45838 | DK16: 45747 | DL16: 45747 | DM16: 45747 | DN16: 45657 | DO16: 45657 | DP16: 45657 | DQ16: 45626 | DR16: 45596 | DS16: 45565 | DT16: 45535 | DU16: 45504 | DV16: 45473 | DW16: 45443 | DX16: Shareholder Report | DY16: Shareholder Report | DZ16: Shareholder Report | EA16: Shareholder Report | EB16: Shareholder Report | EC16: Shareholder Report | ED16: Shareholder Report | EE16: Shareholder Report | EF16: Shareholder Report | EG16: Shareholder Report | EH16: Shareholder Report | EI16: Shareholder Report | EJ16: Shareholder Report | EK16: Shareholder Report | EL16: Shareholder Report | EM16: Shareholder Report | EN16: Shareholder Report | EO16: Shareholder Report | EP16: Aggregate MFs | EQ16: Aggregate MFs | ER16: Aggregate MFs | ES16: Aggregate MFs | ET16: Aggregate MFs | EU16: Aggregate MFs | EV16: Aggregate MFs | EW16: Investment Managers | EX16: Investment Advisor/Hedge Fund | EY16: 10889.685 | FA16: Low | FB16: Low | FC16: Low | FD16: Low | FE16: Low | FF16: Moderate | FG16: Moderate | FH16: Moderate | FI16: Moderate | FJ16: Moderate | FK16: Moderate | FL16: Moderate | FM16: Moderate | FN16: Moderate | FO16: Moderate | FP16: Moderate | FQ16: Moderate | FR16: Moderate | FS16: Moderate | FT16: Moderate | FU16: Moderate | FV16: Moderate | FW16: Moderate | FX16: Moderate | FY16: Moderate | FZ16: Mumbai | GA16: India
A17: 15 | B17: Think Investments LP | C17: 0.010729 | D17: 0.010731 | E17: 0.010731 | F17: 0.010732 | G17: 0.010732 | H17: 0.010732 | I17: 0.010732 | J17: 0.010733 | K17: 0.010733 | L17: 0.010734 | M17: 0.010734 | N17: 0.010737 | O17: 0.010737 | P17: 0.010738 | Q17: 0.010738 | R17: 0.010739 | S17: 0.010739 | T17: 0.01074 | U17: 0.01074 | V17: 0.010741 | W17: 0.010742 | X17: 0.010742 | Y17: 0.010742 | Z17: 0.010746 | AA17: 0.010746 | AB17: 1.436888 | AC17: 1.436888 | AD17: 1.436888 | AE17: 1.436888 | AF17: 1.436888 | AG17: 1.436888 | AH17: 1.436888 | AI17: 1.436888 | AJ17: 1.436888 | AK17: 1.436888 | AL17: 1.436888 | AM17: 1.436888 | AN17: 1.436888 | AO17: 1.436888 | AP17: 1.436888 | AQ17: 1.436888 | AR17: 1.436888 | AS17: 1.436888 | AT17: 1.436888 | AU17: 1.436888 | AV17: 1.436888 | AW17: 1.436888 | AX17: 1.436888 | AY17: 1.436888 | AZ17: 1.436888 | BA17: 0 | BB17: 0 | BC17: 0 | BD17: 0 | BE17: 0 | BF17: 0 | BG17: 0 | BH17: 0 | BI17: 0 | BJ17: 0 | BK17: 0 | BL17: 0 | BM17: 0 | BN17: 0 | BO17: 0 | BP17: 0 | BQ17: 0 | BR17: 0 | BS17: 0 | BT17: 0 | BU17: 0 | BV17: 0 | BW17: 0 | BX17: 0 | BY17: 0 | BZ17: 52.807623 | CA17: 52.807623 | CB17: 52.807623 | CC17: 52.807623 | CD17: 52.807623 | CE17: 52.807623 | CF17: 46.796004 | CG17: 46.796004 | CH17: 46.796004 | CI17: 44.014786 | CJ17: 44.014786 | CK17: 44.014786 | CL17: 40.753493 | CM17: 40.753493 | CN17: 40.753493 | CO17: 43.807315 | CP17: 43.807315 | CQ17: 43.807315 | CR17: 35.091428 | CS17: 35.091428 | CT17: 35.091428 | CU17: 30.795136 | CV17: 30.795136 | CW17: 30.795136 | CX17: 29.784327 | CY17: 46022 | CZ17: 46022 | DA17: 46022 | DB17: 46022 | DC17: 46022 | DD17: 46022 | DE17: 45930 | DF17: 45930 | DG17: 45930 | DH17: 45838 | DI17: 45838 | DJ17: 45838 | DK17: 45747 | DL17: 45747 | DM17: 45747 | DN17: 45657 | DO17: 45657 | DP17: 45657 | DQ17: 45565 | DR17: 45565 | DS17: 45565 | DT17: 45473 | DU17: 45473 | DV17: 45473 | DW17: 45382 | DX17: Shareholder Report | DY17: Shareholder Report | DZ17: Shareholder Report | EA17: Shareholder Report | EB17: Shareholder Report | EC17: Shareholder Report | ED17: Shareholder Report | EE17: Shareholder Report | EF17: Shareholder Report | EG17: Shareholder Report | EH17: Shareholder Report | EI17: Shareholder Report | EJ17: Shareholder Report | EK17: Shareholder Report | EL17: Shareholder Report | EM17: Shareholder Report | EN17: Shareholder Report | EO17: Shareholder Report | EP17: Shareholder Report | EQ17: Shareholder Report | ER17: Shareholder Report | ES17: Shareholder Report | ET17: Shareholder Report | EU17: Shareholder Report | EV17: Shareholder Report | EW17: Investment Managers | EX17: Hedge Fund | EY17: 1000.276 | EZ17: Hedge Fund | FA17: Moderate | FB17: Low | FC17: Low | FD17: Moderate | FE17: Moderate | FF17: Moderate | FH17: Low | FI17: Moderate | FJ17: Moderate | FK17: Moderate | FL17: Moderate | FM17: Low | FN17: Moderate | FO17: Moderate | FQ17: Low | FR17: Moderate | FS17: Moderate | FT17: Moderate | FU17: Moderate | FV17: Moderate | FW17: Moderate | FX17: Moderate | FY17: Moderate | FZ17: San Francisco | GA17: United States
A18: 16 | B18: DSP Investment Managers Pvt. Ltd. | C18: 0.010721 | D18: 0.010724 | E18: 0.010724 | F18: 0.010724 | G18: 0.010724 | H18: 0.010724 | I18: 0.011612 | J18: 0.011614 | K18: 0.011614 | L18: 0.011615 | M18: 0.011615 | N18: 0.011618 | O18: 0.012853 | P18: 0.012854 | Q18: 0.012854 | R18: 0.013703 | S18: 0.013703 | T18: 0.013704 | U18: 0.013966 | V18: 0.013967 | W18: 0.013968 | X18: 0.014477 | Y18: 0.014477 | Z18: 0.014482 | AA18: 0.014097 | AB18: 1.435911 | AC18: 1.435911 | AD18: 1.435911 | AE18: 1.435911 | AF18: 1.435911 | AG18: 1.435911 | AH18: 1.554815 | AI18: 1.554815 | AJ18: 1.554815 | AK18: 1.554815 | AL18: 1.554815 | AM18: 1.554815 | AN18: 1.720026 | AO18: 1.720026 | AP18: 1.720026 | AQ18: 1.833493 | AR18: 1.833493 | AS18: 1.833493 | AT18: 1.868413 | AU18: 1.868413 | AV18: 1.868413 | AW18: 1.936493 | AX18: 1.936493 | AY18: 1.936493 | AZ18: 1.884988 | BA18: 0 | BB18: 0 | BC18: 0 | BD18: 0 | BE18: 0 | BF18: -0.118904 | BG18: 0 | BH18: 0 | BI18: 0 | BJ18: 0 | BK18: 0 | BL18: -0.165211 | BM18: 0 | BN18: 0 | BO18: -0.113467 | BP18: 0 | BQ18: 0 | BR18: -0.03492 | BS18: 0 | BT18: 0 | BU18: -0.06808 | BV18: 0 | BW18: 0 | BX18: 0.051505 | BY18: 0 | BZ18: 52.771717 | CA18: 52.771717 | CB18: 52.771717 | CC18: 52.771717 | CD18: 52.771717 | CE18: 52.771717 | CF18: 50.636604 | CG18: 50.636604 | CH18: 50.636604 | CI18: 47.627128 | CJ18: 47.627128 | CK18: 47.627128 | CL18: 48.783946 | CM18: 48.783946 | CN18: 48.783946 | CO18: 55.898863 | CP18: 55.898863 | CQ18: 55.898863 | CR18: 45.630056 | CS18: 45.630056 | CT18: 45.630056 | CU18: 41.502584 | CV18: 41.502584 | CW18: 41.502584 | CX18: 39.072704 | CY18: 46022 | CZ18: 46022 | DA18: 46022 | DB18: 46022 | DC18: 46022 | DD18: 46022 | DE18: 45930 | DF18: 45930 | DG18: 45930 | DH18: 45838 | DI18: 45838 | DJ18: 45838 | DK18: 45747 | DL18: 45747 | DM18: 45747 | DN18: 45657 | DO18: 45657 | DP18: 45657 | DQ18: 45565 | DR18: 45565 | DS18: 45565 | DT18: 45473 | DU18: 45473 | DV18: 45473 | DW18: 45382 | DX18: Shareholder Report | DY18: Shareholder Report | DZ18: Shareholder Report | EA18: Shareholder Report | EB18: Shareholder Report | EC18: Shareholder Report | ED18: Shareholder Report | EE18: Shareholder Report | EF18: Shareholder Report | EG18: Shareholder Report | EH18: Shareholder Report | EI18: Shareholder Report | EJ18: Shareholder Report | EK18: Shareholder Report | EL18: Shareholder Report | EM18: Shareholder Report | EN18: Shareholder Report | EO18: Shareholder Report | EP18: Shareholder Report | EQ18: Shareholder Report | ER18: Shareholder Report | ES18: Shareholder Report | ET18: Shareholder Report | EU18: Shareholder Report | EV18: Shareholder Report | EW18: Investment Managers | EX18: Investment Advisor | EY18: 16047.989 | EZ18: Core Value | FA18: Low | FB18: Low | FC18: Low | FD18: Low | FE18: Low | FF18: Low | FG18: Low | FH18: Low | FI18: Low | FJ18: Low | FK18: Low | FL18: Low | FM18: Low | FN18: Low | FO18: Low | FP18: Low | FQ18: Low | FR18: Low | FS18: Low | FT18: Low | FU18: Low | FV18: Low | FW18: Low | FX18: Low | FY18: Low | FZ18: Mumbai | GA18: India
A19: 17 | B19: Agrawal (Mukul Mahavir) | C19: 0.010454 | D19: 0.010456 | E19: 0.010456 | F19: 0.010457 | G19: 0.010457 | H19: 0.010457 | I19: 0.010457 | J19: 0.010458 | K19: 0.010458 | L19: 0.010459 | M19: 0.010459 | N19: 0.010462 | O19: 0.010462 | P19: 0.010463 | Q19: 0.010463 | R19: 0.010464 | S19: 0.010464 | T19: 0.010465 | U19: 0.010465 | V19: 0.010466 | W19: 0.010467 | X19: 0.010467 | Y19: 0.010467 | Z19: 0.010471 | AA19: 0.010471 | AB19: 1.400083 | AC19: 1.400083 | AD19: 1.400083 | AE19: 1.400083 | AF19: 1.400083 | AG19: 1.400083 | AH19: 1.400083 | AI19: 1.400083 | AJ19: 1.400083 | AK19: 1.400083 | AL19: 1.400083 | AM19: 1.400083 | AN19: 1.400083 | AO19: 1.400083 | AP19: 1.400083 | AQ19: 1.400083 | AR19: 1.400083 | AS19: 1.400083 | AT19: 1.400083 | AU19: 1.400083 | AV19: 1.400083 | AW19: 1.400083 | AX19: 1.400083 | AY19: 1.400083 | AZ19: 1.400083 | BA19: 0 | BB19: 0 | BC19: 0 | BD19: 0 | BE19: 0 | BF19: 0 | BG19: 0 | BH19: 0 | BI19: 0 | BJ19: 0 | BK19: 0 | BL19: 0 | BM19: 0 | BN19: 0 | BO19: 0 | BP19: 0 | BQ19: 0 | BR19: 0 | BS19: 0 | BT19: 0 | BU19: 0 | BV19: 0 | BW19: 0 | BX19: 0 | BY19: 0 | BZ19: 51.454989 | CA19: 51.454989 | CB19: 51.454989 | CC19: 51.454989 | CD19: 51.454989 | CE19: 51.454989 | CF19: 45.597353 | CG19: 45.597353 | CH19: 45.597353 | CI19: 42.887374 | CJ19: 42.887374 | CK19: 42.887374 | CL19: 39.709617 | CM19: 39.709617 | CN19: 39.709617 | CO19: 42.685218 | CP19: 42.685218 | CQ19: 42.685218 | CR19: 34.192583 | CS19: 34.192583 | CT19: 34.192583 | CU19: 30.006338 | CV19: 30.006338 | CW19: 30.006338 | CX19: 29.02142 | CY19: 46022 | CZ19: 46022 | DA19: 46022 | DB19: 46022 | DC19: 46022 | DD19: 46022 | DE19: 45930 | DF19: 45930 | DG19: 45930 | DH19: 45838 | DI19: 45838 | DJ19: 45838 | DK19: 45747 | DL19: 45747 | DM19: 45747 | DN19: 45657 | DO19: 45657 | DP19: 45657 | DQ19: 45565 | DR19: 45565 | DS19: 45565 | DT19: 45473 | DU19: 45473 | DV19: 45473 | DW19: 45382 | DX19: Shareholder Report | DY19: Shareholder Report | DZ19: Shareholder Report | EA19: Shareholder Report | EB19: Shareholder Report | EC19: Shareholder Report | ED19: Shareholder Report | EE19: Shareholder Report | EF19: Shareholder Report | EG19: Shareholder Report | EH19: Shareholder Report | EI19: Shareholder Report | EJ19: Shareholder Report | EK19: Shareholder Report | EL19: Shareholder Report | EM19: Shareholder Report | EN19: Shareholder Report | EO19: Shareholder Report | EP19: Shareholder Report | EQ19: Shareholder Report | ER19: Shareholder Report | ES19: Shareholder Report | ET19: Shareholder Report | EU19: Shareholder Report | EV19: Shareholder Report | EW19: Strategic Entities | EX19: Individual Investor | EY19: 145.92011 | FA19: Low | FB19: Low | FC19: Low | FD19: Low | FE19: Low | FF19: Low | FH19: Low | FI19: Low | FK19: Low | FL19: Low | FM19: Low | FN19: Low | FO19: Low | FP19: Low | FQ19: Low | FR19: Low | FS19: Low | FT19: Low | FU19: Low | FV19: Low | FW19: Low | FX19: Low | FY19: Low | GA19: India
A20: 18 | B20: Capital World Investors | C20: 0.010004 | D20: 0.010006 | E20: 0.010006 | F20: 0.010007 | G20: 0.010007 | H20: 0.010007 | I20: 0.013069 | J20: 0.013071 | K20: 0.013071 | L20: 0.013072 | M20: 0.013072 | N20: 0.013076 | O20: 0.013076 | P20: 0.013077 | Q20: 0.013077 | R20: 0.013078 | S20: 0.013078 | T20: 0.013079 | U20: 0.013079 | V20: 0.01308 | W20: 0.013082 | X20: 0.011207 | Y20: 0.011207 | Z20: 0.011211 | AA20: 0.011211 | AB20: 1.339842 | AC20: 1.339842 | AD20: 1.339842 | AE20: 1.339842 | AF20: 1.339842 | AG20: 1.339842 | AH20: 1.749854 | AI20: 1.749854 | AJ20: 1.749854 | AK20: 1.749854 | AL20: 1.749854 | AM20: 1.749854 | AN20: 1.749854 | AO20: 1.749854 | AP20: 1.749854 | AQ20: 1.749854 | AR20: 1.749854 | AS20: 1.749854 | AT20: 1.749854 | AU20: 1.749854 | AV20: 1.749854 | AW20: 1.499109 | AX20: 1.499109 | AY20: 1.499109 | AZ20: 1.499109 | BA20: 0 | BB20: 0 | BC20: 0 | BD20: 0 | BE20: 0 | BF20: -0.410012 | BG20: 0 | BH20: 0 | BI20: 0 | BJ20: 0 | BK20: 0 | BL20: 0 | BM20: 0 | BN20: 0 | BO20: 0 | BP20: 0 | BQ20: 0 | BR20: 0 | BS20: 0 | BT20: 0 | BU20: 0.250745 | BV20: 0 | BW20: 0 | BX20: 0 | BY20: 0 | BZ20: 49.241048 | CA20: 49.241048 | CB20: 49.241048 | CC20: 49.241048 | CD20: 49.241048 | CE20: 49.241048 | CF20: 56.988558 | CG20: 56.988558 | CH20: 56.988558 | CI20: 53.601567 | CJ20: 53.601567 | CK20: 53.601567 | CL20: 49.629938 | CM20: 49.629938 | CN20: 49.629938 | CO20: 53.348908 | CP20: 53.348908 | CQ20: 53.348908 | CR20: 42.734629 | CS20: 42.734629 | CT20: 42.734629 | CU20: 32.128646 | CV20: 32.128646 | CW20: 32.128646 | CX20: 31.074066 | CY20: 46022 | CZ20: 46022 | DA20: 46022 | DB20: 46022 | DC20: 46022 | DD20: 46022 | DE20: 45930 | DF20: 45930 | DG20: 45930 | DH20: 45838 | DI20: 45838 | DJ20: 45838 | DK20: 45747 | DL20: 45747 | DM20: 45747 | DN20: 45657 | DO20: 45657 | DP20: 45657 | DQ20: 45565 | DR20: 45565 | DS20: 45565 | DT20: 45473 | DU20: 45473 | DV20: 45473 | DW20: 45382 | DX20: Shareholder Report | DY20: Shareholder Report | DZ20: Shareholder Report | EA20: Shareholder Report | EB20: Shareholder Report | EC20: Shareholder Report | ED20: Shareholder Report | EE20: Shareholder Report | EF20: Shareholder Report | EG20: Shareholder Report | EH20: Shareholder Report | EI20: Shareholder Report | EJ20: Shareholder Report | EK20: Shareholder Report | EL20: Shareholder Report | EM20: Shareholder Report | EN20: Shareholder Report | EO20: Shareholder Report | EP20: Shareholder Report | EQ20: Shareholder Report | ER20: Shareholder Report | ES20: Shareholder Report | ET20: Shareholder Report | EU20: Shareholder Report | EV20: Shareholder Report | EW20: Investment Managers | EX20: Investment Advisor | EY20: 1198994.2 | EZ20: Growth | FA20: Low | FB20: Low | FC20: Low | FD20: Low | FE20: Low | FF20: Low | FG20: Low | FH20: Low | FI20: Low | FJ20: Low | FK20: Low | FL20: Low | FM20: Low | FN20: Low | FO20: Low | FP20: Low | FQ20: Low | FR20: Low | FS20: Low | FT20: Low | FU20: Low | FV20: Low | FW20: Low | FX20: Low | FY20: Low | FZ20: Los Angeles | GA20: United States
A21: 19 | B21: Axis Asset Management Company Limited | C21: 0.009644 | D21: 0.009646 | E21: 0.00414 | F21: 0.004576 | G21: 0.00457 | H21: 0.00457 | I21: 0.004567 | J21: 0.004566 | K21: 0.004571 | L21: 0.004606 | M21: 0.004595 | N21: 0.004587 | O21: 0.004575 | P21: 0.004571 | Q21: 0.001577 | R21: 0.000412 | S21: 0.000406 | T21: 0.000377 | U21: 0.000374 | V21: 0.000368 | W21: 0 | X21: 0.000355 | Y21: 0.000342 | Z21: 0.00032 | AA21: 0.000311 | AB21: 1.291626 | AC21: 1.291626 | AD21: 0.554354 | AE21: 0.612722 | AF21: 0.611876 | AG21: 0.611918 | AH21: 0.611511 | AI21: 0.611255 | AJ21: 0.611891 | AK21: 0.616537 | AL21: 0.615188 | AM21: 0.613894 | AN21: 0.612253 | AO21: 0.611678 | AP21: 0.211062 | AQ21: 0.055089 | AR21: 0.054359 | AS21: 0.050425 | AT21: 0.050042 | AU21: 0.049217 | AV21: 0 | AW21: 0.047437 | AX21: 0.045791 | AY21: 0.042785 | AZ21: 0.041639 | BA21: 0 | BB21: 0.737272 | BC21: -0.058368 | BD21: 0.000846 | BE21: -4.2e-05 | BF21: 0.000407 | BG21: 0.000256 | BH21: -0.000636 | BI21: -0.004646 | BJ21: 0.001349 | BK21: 0.001294 | BL21: 0.001641 | BM21: 0.000575 | BN21: 0.400616 | BO21: 0.155973 | BP21: 0.00073 | BQ21: 0.003934 | BR21: 0.000383 | BS21: 0.000825 | BT21: 0.049217 | BU21: -0.047437 | BV21: 0.001646 | BW21: 0.003006 | BX21: 0.001146 | BY21: 0.002965 | BZ21: 46.614285 | CA21: 46.614285 | CB21: 15.378868 | CC21: 17.844931 | CD21: 18.854904 | CE21: 22.488834 | CF21: 21.957451 | CG21: 21.603127 | CH21: 19.927826 | CI21: 20.085104 | CJ21: 19.189975 | CK21: 18.804815 | CL21: 18.160162 | CM21: 17.645373 | CN21: 5.9862102 | CO21: 1.3077093 | CP21: 1.3682552 | CQ21: 1.5373389 | CR21: 1.4565188 | CS21: 1.312668 | CT21: 0 | CU21: 1.0984657 | CV21: 0.94290971 | CW21: 0.91696075 | CX21: 0.78687049 | CY21: 46142 | CZ21: 46142 | DA21: 46112 | DB21: 46081 | DC21: 46053 | DD21: 46022 | DE21: 45991 | DF21: 45961 | DG21: 45930 | DH21: 45900 | DI21: 45869 | DJ21: 45838 | DK21: 45808 | DL21: 45777 | DM21: 45747 | DN21: 45716 | DO21: 45688 | DP21: 45657 | DQ21: 45626 | DR21: 45596 | DS21: 45565 | DT21: 45535 | DU21: 45504 | DV21: 45473 | DW21: 45443 | DX21: Aggregate MFs | DY21: Aggregate MFs | DZ21: Aggregate MFs | EA21: Aggregate MFs | EB21: Aggregate MFs | EC21: Aggregate MFs | ED21: Aggregate MFs | EE21: Aggregate MFs | EF21: Aggregate MFs | EG21: Aggregate MFs | EH21: Aggregate MFs | EI21: Aggregate MFs | EJ21: Aggregate MFs | EK21: Aggregate MFs | EL21: Aggregate MFs | EM21: Aggregate MFs | EN21: Aggregate MFs | EO21: Aggregate MFs | EP21: Aggregate MFs | EQ21: Aggregate MFs | ER21: Aggregate MFs | ES21: Aggregate MFs | ET21: Aggregate MFs | EU21: Aggregate MFs | EV21: Aggregate MFs | EW21: Investment Managers | EX21: Investment Advisor | EY21: 24152.846 | EZ21: Growth | FA21: Low | FB21: Low | FC21: Low | FD21: Low | FE21: Low | FF21: Low | FG21: Low | FH21: Low | FI21: Low | FJ21: Low | FK21: Low | FL21: Low | FM21: Low | FN21: Low | FO21: Low | FP21: Low | FQ21: Low | FR21: Low | FS21: Low | FT21: Low | FU21: Low | FV21: Low | FW21: Low | FX21: Low | FY21: Low | FZ21: Mumbai | GA21: India
A22: 20 | B22: BlackRock Institutional Trust Company, N.A. | C22: 0.009535 | D22: 0.009538 | E22: 0.00957 | F22: 0.009781 | G22: 0.009633 | H22: 0.009195 | I22: 0.009302 | J22: 0.009069 | K22: 0.009071 | L22: 0.008932 | M22: 0.008911 | N22: 0.008765 | O22: 0.0086 | P22: 0.008846 | Q22: 0.008814 | R22: 0.008456 | S22: 0.008563 | T22: 0.008567 | U22: 0.008663 | V22: 0.008958 | W22: 0.008965 | X22: 0.008909 | Y22: 0.008889 | Z22: 0.008981 | AA22: 0.009066 | AB22: 1.277052 | AC22: 1.277052 | AD22: 1.281376 | AE22: 1.309594 | AF22: 1.289787 | AG22: 1.231104 | AH22: 1.245464 | AI22: 1.214091 | AJ22: 1.214339 | AK22: 1.195725 | AL22: 1.192951 | AM22: 1.172964 | AN22: 1.150944 | AO22: 1.183713 | AP22: 1.179402 | AQ22: 1.131404 | AR22: 1.1457 | AS22: 1.146224 | AT22: 1.158985 | AU22: 1.198336 | AV22: 1.199126 | AW22: 1.191699 | AX22: 1.189006 | AY22: 1.200844 | AZ22: 1.212278 | BA22: 0 | BB22: -0.004324 | BC22: -0.028218 | BD22: 0.019807 | BE22: 0.058683 | BF22: -0.01436 | BG22: 0.031373 | BH22: -0.000248 | BI22: 0.018614 | BJ22: 0.002774 | BK22: 0.019987 | BL22: 0.02202 | BM22: -0.032769 | BN22: 0.004311 | BO22: 0.047998 | BP22: -0.014296 | BQ22: -0.000524 | BR22: -0.012761 | BS22: -0.039351 | BT22: -0.00079 | BU22: 0.007427 | BV22: 0.002693 | BW22: -0.011838 | BX22: -0.011434 | BY22: -0.004263 | BZ22: 46.088315 | CA22: 46.088315 | CB22: 35.547885 | CC22: 38.140649 | CD22: 39.74467 | CE22: 45.244776 | CF22: 44.720724 | CG22: 42.908707 | CH22: 39.548116 | CI22: 38.953479 | CJ22: 37.212527 | CK22: 35.93026 | CL22: 34.138387 | CM22: 34.147145 | CN22: 33.45059 | CO22: 26.857404 | CP22: 28.838094 | CQ22: 34.945657 | CR22: 33.733333 | CS22: 31.960853 | CT22: 29.284846 | CU22: 27.595348 | CV22: 24.48353 | CW22: 25.736282 | CX22: 22.90895 | CY22: 46142 | CZ22: 46142 | DA22: 46112 | DB22: 46081 | DC22: 46053 | DD22: 46022 | DE22: 45991 | DF22: 45961 | DG22: 45930 | DH22: 45900 | DI22: 45869 | DJ22: 45838 | DK22: 45808 | DL22: 45777 | DM22: 45747 | DN22: 45716 | DO22: 45688 | DP22: 45657 | DQ22: 45626 | DR22: 45596 | DS22: 45565 | DT22: 45535 | DU22: 45504 | DV22: 45473 | DW22: 45443 | DX22: Aggregate MFs | DY22: Aggregate MFs | DZ22: Aggregate MFs | EA22: Aggregate MFs | EB22: Aggregate MFs | EC22: Aggregate MFs | ED22: Aggregate MFs | EE22: Aggregate MFs | EF22: Aggregate MFs | EG22: Aggregate MFs | EH22: Aggregate MFs | EI22: Aggregate MFs | EJ22: Aggregate MFs | EK22: Aggregate MFs | EL22: Aggregate MFs | EM22: Aggregate MFs | EN22: Aggregate MFs | EO22: Aggregate MFs | EP22: Aggregate MFs | EQ22: Aggregate MFs | ER22: Aggregate MFs | ES22: Aggregate MFs | ET22: Aggregate MFs | EU22: Aggregate MFs | EV22: Aggregate MFs | EW22: Investment Managers | EX22: Investment Advisor | EY22: 5207142.2 | EZ22: Index | FA22: Low | FB22: Low | FC22: Low | FD22: Low | FE22: Low | FF22: Low | FG22: Low | FH22: Low | FI22: Low | FJ22: Low | FK22: Low | FL22: Low | FM22: Low | FN22: Low | FO22: Low | FP22: Low | FQ22: Low | FR22: Low | FS22: Low | FT22: Low | FU22: Low | FV22: Low | FW22: Low | FX22: Low | FY22: Low | FZ22: San Francisco | GA22: United States
A23: 21 | B23: Baroda BNP Paribas Asset Management India Pvt. Ltd. | C23: 0.00746 | D23: 0.007462 | E23: 0.007008 | F23: 0.008188 | G23: 0.007519 | H23: 0.006884 | I23: 0.00595 | J23: 0.005734 | K23: 0.005734 | L23: 0.00566 | M23: 0.00566 | N23: 0.005572 | O23: 0.005572 | P23: 0.005573 | Q23: 0.005453 | R23: 0.004807 | S23: 0.004695 | T23: 0.003822 | U23: 0.00369 | V23: 0.003525 | W23: 0.002956 | X23: 0.002956 | Y23: 0.002956 | Z23: 0.003133 | AA23: 0.003768 | AB23: 0.9991 | AC23: 0.9991 | AD23: 0.938306 | AE23: 1.096384 | AF23: 1.0067 | AG23: 0.9217 | AH23: 0.7967 | AI23: 0.767703 | AJ23: 0.767703 | AK23: 0.757703 | AL23: 0.757703 | AM23: 0.745703 | AN23: 0.745703 | AO23: 0.745703 | AP23: 0.729703 | AQ23: 0.643203 | AR23: 0.628203 | AS23: 0.511305 | AT23: 0.493702 | AU23: 0.471558 | AV23: 0.3954 | AW23: 0.3954 | AX23: 0.3954 | AY23: 0.4189 | AZ23: 0.5039 | BA23: 0 | BB23: 0.060794 | BC23: -0.158078 | BD23: 0.089684 | BE23: 0.085 | BF23: 0.125 | BG23: 0.028997 | BH23: 0 | BI23: 0.01 | BJ23: 0 | BK23: 0.012 | BL23: 0 | BM23: 0 | BN23: 0.016 | BO23: 0.0865 | BP23: 0.015 | BQ23: 0.116898 | BR23: 0.017603 | BS23: 0.022144 | BT23: 0.076158 | BU23: 0 | BV23: 0 | BW23: -0.0235 | BX23: -0.085 | BY23: 0 | BZ23: 36.057135 | CA23: 36.057135 | CB23: 26.03045 | CC23: 31.931116 | CD23: 31.02137 | CE23: 33.873751 | CF23: 28.60701 | CG23: 27.132351 | CH23: 25.00225 | CI23: 24.68391 | CJ23: 23.635542 | CK23: 22.842391 | CL23: 22.11845 | CM23: 21.511657 | CN23: 20.696078 | CO23: 15.26843 | CP23: 15.812322 | CQ23: 15.58848 | CR23: 14.369654 | CS23: 12.576937 | CT23: 9.6563898 | CU23: 9.1560038 | CV23: 8.1419165 | CW23: 8.9777926 | CX23: 9.5224198 | CY23: 46142 | CZ23: 46142 | DA23: 46112 | DB23: 46081 | DC23: 46053 | DD23: 46022 | DE23: 45991 | DF23: 45961 | DG23: 45930 | DH23: 45900 | DI23: 45869 | DJ23: 45838 | DK23: 45808 | DL23: 45777 | DM23: 45747 | DN23: 45716 | DO23: 45688 | DP23: 45657 | DQ23: 45626 | DR23: 45596 | DS23: 45565 | DT23: 45535 | DU23: 45504 | DV23: 45473 | DW23: 45443 | DX23: Aggregate MFs | DY23: Aggregate MFs | DZ23: Aggregate MFs | EA23: Aggregate MFs | EB23: Aggregate MFs | EC23: Aggregate MFs | ED23: Aggregate MFs | EE23: Aggregate MFs | EF23: Aggregate MFs | EG23: Aggregate MFs | EH23: Aggregate MFs | EI23: Aggregate MFs | EJ23: Aggregate MFs | EK23: Aggregate MFs | EL23: Aggregate MFs | EM23: Aggregate MFs | EN23: Aggregate MFs | EO23: Aggregate MFs | EP23: Aggregate MFs | EQ23: Aggregate MFs | ER23: Aggregate MFs | ES23: Aggregate MFs | ET23: Aggregate MFs | EU23: Aggregate MFs | EV23: Aggregate MFs | EW23: Investment Managers | EX23: Investment Advisor | EY23: 2900.3093 | EZ23: GARP | FA23: Moderate | FB23: Moderate | FC23: Moderate | FD23: Moderate | FE23: Moderate | FF23: Moderate | FG23: Moderate | FH23: Moderate | FI23: Moderate | FJ23: Moderate | FK23: Moderate | FL23: Moderate | FM23: Moderate | FN23: Moderate | FO23: Moderate | FP23: Moderate | FQ23: Moderate | FR23: Moderate | FS23: Moderate | FT23: Moderate | FU23: Moderate | FV23: Moderate | FW23: Moderate | FX23: Moderate | FY23: Moderate | FZ23: Mumbai | GA23: India
A24: 22 | B24: Sundaram Asset Management Company Limited | C24: 0.006903 | D24: 0.006905 | E24: 0.003624 | F24: 0 | G24: 0.000203 | H24: 0.000203 | I24: 0.000199 | J24: 0.00022 | K24: 0.000216 | L24: 0.000212 | M24: 0 | N24: 0 | O24: 0 | P24: 0 | Q24: 0.000452 | R24: 0.000564 | S24: 0.000697 | T24: 0.000697 | U24: 0.001349 | V24: 0.001956 | W24: 0.001991 | X24: 0.003069 | Y24: 0.003069 | Z24: 0.003071 | AA24: 0.003071 | AB24: 0.92451 | AC24: 0.92451 | AD24: 0.485226 | AE24: 0 | AF24: 0.027178 | AG24: 0.027178 | AH24: 0.026625 | AI24: 0.029458 | AJ24: 0.028962 | AK24: 0.028391 | AL24: 0 | AM24: 0 | AN24: 0 | AO24: 0 | AP24: 0.060504 | AQ24: 0.075504 | AR24: 0.093259 | AS24: 0.093259 | AT24: 0.180464 | AU24: 0.261711 | AV24: 0.266293 | AW24: 0.41058 | AX24: 0.41058 | AY24: 0.41058 | AZ24: 0.41058 | BA24: 0 | BB24: 0.439284 | BC24: 0.485226 | BD24: -0.027178 | BE24: 0 | BF24: 0.000553 | BG24: -0.002833 | BH24: 0.000496 | BI24: 0.000571 | BJ24: 0.028391 | BK24: 0 | BL24: 0 | BM24: 0 | BN24: -0.060504 | BO24: -0.015 | BP24: -0.017755 | BQ24: 0 | BR24: -0.087205 | BS24: -0.081247 | BT24: -0.004582 | BU24: -0.144287 | BV24: 0 | BW24: 0 | BX24: 0 | BY24: 0 | BZ24: 33.36521 | CA24: 33.36521 | CB24: 13.461122 | CC24: 0 | CD24: 0.83748763 | CE24: 0.99882913 | CF24: 0.95602062 | CG24: 1.041112 | CH24: 0.94322304 | CI24: 0.92490181 | CJ24: 0 | CK24: 0 | CL24: 0 | CM24: 0 | CN24: 1.7160345 | CO24: 1.792323 | CP24: 2.3473962 | CQ24: 2.8432462 | CR24: 5.252572 | CS24: 6.9801015 | CT24: 6.5033612 | CU24: 9.5075165 | CV24: 8.4544969 | CW24: 8.7994798 | CX24: 7.7589108 | CY24: 46142 | CZ24: 46142 | DA24: 46112 | DB24: 46081 | DC24: 46053 | DD24: 46022 | DE24: 45991 | DF24: 45961 | DG24: 45930 | DH24: 45900 | DI24: 45777 | DJ24: 45777 | DK24: 45777 | DL24: 45777 | DM24: 45747 | DN24: 45716 | DO24: 45688 | DP24: 45657 | DQ24: 45626 | DR24: 45596 | DS24: 45565 | DT24: 45535 | DU24: 45504 | DV24: 45473 | DW24: 45443 | DX24: Aggregate MFs | DY24: Aggregate MFs | DZ24: Aggregate MFs | EA24: Aggregate MFs | EB24: Aggregate MFs | EC24: Aggregate MFs | ED24: Aggregate MFs | EE24: Aggregate MFs | EF24: Aggregate MFs | EG24: Aggregate MFs | EH24: Aggregate MFs | EI24: Aggregate MFs | EJ24: Aggregate MFs | EK24: Aggregate MFs | EL24: Aggregate MFs | EM24: Aggregate MFs | EN24: Aggregate MFs | EO24: Aggregate MFs | EP24: Aggregate MFs | EQ24: Aggregate MFs | ER24: Aggregate MFs | ES24: Aggregate MFs | ET24: Aggregate MFs | EU24: Aggregate MFs | EV24: Aggregate MFs | EW24: Investment Managers | EX24: Investment Advisor/Hedge Fund | EY24: 6072.0114 | EZ24: Growth | FA24: Low | FB24: Low | FC24: Low | FD24: Low | FE24: Low | FF24: Low | FG24: Low | FH24: Low | FI24: Low | FJ24: Low | FK24: Low | FL24: Low | FM24: Low | FN24: Low | FO24: Low | FP24: Low | FQ24: Low | FR24: Low | FS24: Low | FT24: Low | FU24: Low | FV24: Low | FW24: Low | FX24: Low | FY24: Low | FZ24: Chennai | GA24: India
A25: 23 | B25: Norges Bank Investment Management (NBIM) | C25: 0.006398 | D25: 0.0064 | E25: 0.0064 | F25: 0.0064 | G25: 0.0064 | H25: 0.0064 | I25: 0.006413 | J25: 0.006413 | K25: 0.006413 | L25: 0.006414 | M25: 0.006414 | N25: 0.006416 | O25: 0.006453 | P25: 0.006454 | Q25: 0.006454 | R25: 0.006454 | S25: 0.006454 | T25: 0.006455 | U25: 0.006472 | V25: 0.006472 | W25: 0.006473 | X25: 0.006473 | Y25: 0.006473 | Z25: 0.006475 | AA25: 0.00546 | AB25: 0.856908 | AC25: 0.856908 | AD25: 0.856908 | AE25: 0.856908 | AF25: 0.856908 | AG25: 0.856908 | AH25: 0.858595 | AI25: 0.858595 | AJ25: 0.858595 | AK25: 0.858595 | AL25: 0.858595 | AM25: 0.858595 | AN25: 0.863573 | AO25: 0.863573 | AP25: 0.863573 | AQ25: 0.863573 | AR25: 0.863573 | AS25: 0.863573 | AT25: 0.86587 | AU25: 0.86587 | AV25: 0.86587 | AW25: 0.86587 | AX25: 0.86587 | AY25: 0.86587 | AZ25: 0.730131 | BA25: 0 | BB25: 0 | BC25: 0 | BD25: 0 | BE25: 0 | BF25: -0.001687 | BG25: 0 | BH25: 0 | BI25: 0 | BJ25: 0 | BK25: 0 | BL25: -0.004978 | BM25: 0 | BN25: 0 | BO25: 0 | BP25: 0 | BQ25: 0 | BR25: -0.002297 | BS25: 0 | BT25: 0 | BU25: 0 | BV25: 0 | BW25: 0 | BX25: 0.135739 | BY25: 0 | BZ25: 31.492555 | CA25: 31.492555 | CB25: 31.492555 | CC25: 31.492555 | CD25: 31.492555 | CE25: 31.492555 | CF25: 26.300501 | CG25: 26.300501 | CH25: 26.300501 | CI25: 26.300501 | CJ25: 26.300501 | CK25: 26.300501 | CL25: 26.328297 | CM25: 26.328297 | CN25: 26.328297 | CO25: 26.328297 | CP25: 26.328297 | CQ25: 26.328297 | CR25: 18.557177 | CS25: 18.557177 | CT25: 18.557177 | CU25: 18.557177 | CV25: 18.557177 | CW25: 18.557177 | CX25: 14.553909 | CY25: 46022 | CZ25: 46022 | DA25: 46022 | DB25: 46022 | DC25: 46022 | DD25: 46022 | DE25: 45838 | DF25: 45838 | DG25: 45838 | DH25: 45838 | DI25: 45838 | DJ25: 45838 | DK25: 45657 | DL25: 45657 | DM25: 45657 | DN25: 45657 | DO25: 45657 | DP25: 45657 | DQ25: 45473 | DR25: 45473 | DS25: 45473 | DT25: 45473 | DU25: 45473 | DV25: 45473 | DW25: 45291 | DX25: Aggregate MFs | DY25: Aggregate MFs | DZ25: Aggregate MFs | EA25: Aggregate MFs | EB25: Aggregate MFs | EC25: Aggregate MFs | ED25: Aggregate MFs | EE25: Aggregate MFs | EF25: Aggregate MFs | EG25: Aggregate MFs | EH25: Aggregate MFs | EI25: Aggregate MFs | EJ25: Aggregate MFs | EK25: Aggregate MFs | EL25: Aggregate MFs | EM25: Aggregate MFs | EN25: Aggregate MFs | EO25: Aggregate MFs | EP25: Aggregate MFs | EQ25: Aggregate MFs | ER25: Aggregate MFs | ES25: Aggregate MFs | ET25: Aggregate MFs | EU25: Aggregate MFs | EV25: Aggregate MFs | EW25: Investment Managers | EX25: Sovereign Wealth Fund | EY25: 1576244.2 | EZ25: Core Value | FA25: Low | FB25: Low | FC25: Low | FD25: Low | FE25: Low | FF25: Low | FG25: Low | FH25: Low | FI25: Low | FJ25: Low | FK25: Low | FL25: Low | FM25: Low | FN25: Low | FO25: Low | FP25: Low | FQ25: Low | FR25: Low | FS25: Low | FT25: Low | FU25: Low | FV25: Low | FW25: Low | FX25: Low | FY25: Low | FZ25: Oslo | GA25: Norway
A26: 24 | B26: ICICI Prudential Asset Management Co. Ltd. | C26: 0.005915 | D26: 0.005916 | E26: 0.005876 | F26: 0.004125 | G26: 0.002799 | H26: 0.000524 | I26: 0.00052 | J26: 0.001007 | K26: 0.000998 | L26: 0.000764 | M26: 0.000498 | N26: 0.000484 | O26: 0.000452 | P26: 0.000444 | Q26: 0.000453 | R26: 0.000481 | S26: 0.000444 | T26: 0.00043 | U26: 0.000367 | V26: 0.000344 | W26: 0.000736 | X26: 0.000722 | Y26: 0.000708 | Z26: 0.000632 | AA26: 0.000657 | AB26: 0.792145 | AC26: 0.792145 | AD26: 0.786765 | AE26: 0.552246 | AF26: 0.374797 | AG26: 0.070226 | AH26: 0.06966 | AI26: 0.134791 | AJ26: 0.133674 | AK26: 0.1023 | AL26: 0.066644 | AM26: 0.064741 | AN26: 0.060485 | AO26: 0.059375 | AP26: 0.060575 | AQ26: 0.06431 | AR26: 0.059453 | AS26: 0.057534 | AT26: 0.049086 | AU26: 0.046022 | AV26: 0.098453 | AW26: 0.096513 | AX26: 0.09477 | AY26: 0.084536 | AZ26: 0.087888 | BA26: 0 | BB26: 0.00538 | BC26: 0.234519 | BD26: 0.177449 | BE26: 0.304571 | BF26: 0.000566 | BG26: -0.065131 | BH26: 0.001117 | BI26: 0.031374 | BJ26: 0.035656 | BK26: 0.001903 | BL26: 0.004256 | BM26: 0.00111 | BN26: -0.0012 | BO26: -0.003735 | BP26: 0.004857 | BQ26: 0.001919 | BR26: 0.008448 | BS26: 0.003064 | BT26: -0.052431 | BU26: 0.00194 | BV26: 0.001743 | BW26: 0.010234 | BX26: -0.003352 | BY26: 0.062479 | BZ26: 28.588208 | CA26: 28.588208 | CB26: 21.826405 | CC26: 16.083627 | CD26: 11.549336 | CE26: 2.5809027 | CF26: 2.5012731 | CG26: 4.7638171 | CH26: 4.3534423 | CI26: 3.3326567 | CJ26: 2.0788713 | CK26: 1.9831478 | CL26: 1.794058 | CM26: 1.7128195 | CN26: 1.7180482 | CO26: 1.5265985 | CP26: 1.4964748 | CQ26: 1.7540755 | CR26: 1.4286935 | CS26: 1.2274541 | CT26: 2.404402 | CU26: 2.2348847 | CV26: 1.9514654 | CW26: 1.811761 | CX26: 1.6608582 | CY26: 46142 | CZ26: 46142 | DA26: 46112 | DB26: 46081 | DC26: 46053 | DD26: 46022 | DE26: 45991 | DF26: 45961 | DG26: 45930 | DH26: 45900 | DI26: 45869 | DJ26: 45838 | DK26: 45808 | DL26: 45777 | DM26: 45747 | DN26: 45716 | DO26: 45688 | DP26: 45657 | DQ26: 45626 | DR26: 45596 | DS26: 45565 | DT26: 45535 | DU26: 45504 | DV26: 45473 | DW26: 45443 | DX26: Aggregate MFs | DY26: Aggregate MFs | DZ26: Aggregate MFs | EA26: Aggregate MFs | EB26: Aggregate MFs | EC26: Aggregate MFs | ED26: Aggregate MFs | EE26: Aggregate MFs | EF26: Aggregate MFs | EG26: Aggregate MFs | EH26: Aggregate MFs | EI26: Aggregate MFs | EJ26: Aggregate MFs | EK26: Aggregate MFs | EL26: Aggregate MFs | EM26: Aggregate MFs | EN26: Aggregate MFs | EO26: Aggregate MFs | EP26: Aggregate MFs | EQ26: Aggregate MFs | ER26: Aggregate MFs | ES26: Aggregate MFs | ET26: Aggregate MFs | EU26: Aggregate MFs | EV26: Aggregate MFs | EW26: Investment Managers | EX26: Investment Advisor | EY26: 83569.132 | EZ26: Core Growth | FA26: Low | FB26: Low | FC26: Low | FD26: Low | FE26: Low | FF26: Low | FG26: Low | FH26: Low | FI26: Low | FJ26: Low | FK26: Low | FL26: Low | FM26: Low | FN26: Low | FO26: Low | FP26: Low | FQ26: Low | FR26: Low | FS26: Low | FT26: Low | FU26: Low | FV26: Low | FW26: Low | FX26: Low | FY26: Low | FZ26: New Delhi | GA26: India
A27: 25 | B27: American Century Investment Management, Inc. | C27: 0.004368 | D27: 0.004369 | E27: 0.004369 | F27: 0.004996 | G27: 0.00449 | H27: 0.004996 | I27: 0.001434 | J27: 0.001434 | K27: 0.001224 | L27: 0.000786 | M27: 0.000786 | N27: 0.000786 | O27: 6e-06 | P27: 6e-06 | Q27: 6e-06 | R27: 6e-06 | S27: 6e-06 | T27: 6e-06 | U27: 6e-06 | V27: 6e-06 | W27: 6e-06 | X27: 6e-06 | Y27: 6e-06 | Z27: 6e-06 | AA27: 0.000224 | AB27: 0.585022 | AC27: 0.585022 | AD27: 0.585022 | AE27: 0.668968 | AF27: 0.601205 | AG27: 0.668968 | AH27: 0.191988 | AI27: 0.191988 | AJ27: 0.163874 | AK27: 0.105181 | AL27: 0.105181 | AM27: 0.105181 | AN27: 0.000866 | AO27: 0.000866 | AP27: 0.000866 | AQ27: 0.000822 | AR27: 0.000822 | AS27: 0.000822 | AT27: 0.000822 | AU27: 0.000822 | AV27: 0.000822 | AW27: 0.000822 | AX27: 0.000822 | AY27: 0.000822 | AZ27: 0.029983 | BA27: 0 | BB27: 0 | BC27: -0.083946 | BD27: 0.067763 | BE27: -0.067763 | BF27: 0.47698 | BG27: 0 | BH27: 0.028114 | BI27: 0.058693 | BJ27: 0 | BK27: 0 | BL27: 0.104315 | BM27: 0 | BN27: 0 | BO27: 4.4e-05 | BP27: 0 | BQ27: 0 | BR27: 0 | BS27: 0 | BT27: 0 | BU27: 0 | BV27: 0 | BW27: 0 | BX27: -0.029161 | BY27: 0 | BZ27: 21.113219 | CA27: 21.113219 | CB27: 16.229659 | CC27: 19.483041 | CD27: 18.526078 | CE27: 24.5855 | CF27: 6.8936897 | CG27: 6.7852878 | CH27: 5.3369841 | CI27: 3.4265118 | CJ27: 3.280982 | CK27: 3.2219068 | CL27: 0.02456178 | CM27: 0.02456178 | CN27: 0.02456178 | CO27: 0.02506083 | CP27: 0.02506083 | CQ27: 0.02506083 | CR27: 0.01761696 | CS27: 0.01761696 | CT27: 0.01761696 | CU27: 0.01761696 | CV27: 0.01761696 | CW27: 0.01761696 | CX27: 0.62149832 | CY27: 46142 | CZ27: 46142 | DA27: 46112 | DB27: 46081 | DC27: 46053 | DD27: 46022 | DE27: 45991 | DF27: 45961 | DG27: 45930 | DH27: 45900 | DI27: 45869 | DJ27: 45838 | DK27: 45747 | DL27: 45747 | DM27: 45747 | DN27: 45657 | DO27: 45657 | DP27: 45657 | DQ27: 45473 | DR27: 45473 | DS27: 45473 | DT27: 45473 | DU27: 45473 | DV27: 45473 | DW27: 45382 | DX27: Aggregate MFs | DY27: Aggregate MFs | DZ27: Aggregate MFs | EA27: Aggregate MFs | EB27: Aggregate MFs | EC27: Aggregate MFs | ED27: Aggregate MFs | EE27: Aggregate MFs | EF27: Aggregate MFs | EG27: Aggregate MFs | EH27: Aggregate MFs | EI27: Aggregate MFs | EJ27: Aggregate MFs | EK27: Aggregate MFs | EL27: Aggregate MFs | EM27: Aggregate MFs | EN27: Aggregate MFs | EO27: Aggregate MFs | EP27: Aggregate MFs | EQ27: Aggregate MFs | ER27: Aggregate MFs | ES27: Aggregate MFs | ET27: Aggregate MFs | EU27: Aggregate MFs | EV27: Aggregate MFs | EW27: Investment Managers | EX27: Investment Advisor | EY27: 278218.49 | EZ27: Core Growth | FA27: Low | FB27: Low | FC27: Low | FD27: Low | FE27: Low | FF27: Low | FG27: Low | FH27: Low | FI27: Low | FJ27: Low | FK27: Low | FL27: Low | FM27: Low | FN27: Low | FO27: Low | FP27: Low | FQ27: Low | FR27: Low | FS27: Low | FT27: Low | FU27: Low | FV27: Low | FW27: Low | FX27: Low | FY27: Low | FZ27: Kansas City | GA27: United States
A28: 26 | B28: Mahindra Manulife Investment Management Private Limited | C28: 0.003811 | D28: 0.003812 | E28: 0.00453 | F28: 0.003904 | G28: 0.003813 | H28: 0.003461 | I28: 0.003415 | J28: 0.002377 | K28: 0.002377 | L28: 0.002377 | M28: 0.001854 | N28: 0.001481 | O28: 0.001481 | P28: 0.001481 | Q28: 0.001481 | R28: 0.000381 | S28: 0.000149 | T28: 0 | U28: 0 | V28: 0 | W28: 0 | X28: 0 | Y28: 0 | Z28: 0 | AA28: 0 | AB28: 0.510427 | AC28: 0.510427 | AD28: 0.606585 | AE28: 0.522661 | AF28: 0.510561 | AG28: 0.463378 | AH28: 0.457276 | AI28: 0.3182 | AJ28: 0.3182 | AK28: 0.3182 | AL28: 0.2482 | AM28: 0.1982 | AN28: 0.1982 | AO28: 0.1982 | AP28: 0.1982 | AQ28: 0.051 | AR28: 0.02 | AS28: 0 | AT28: 0 | AU28: 0 | AV28: 0 | AW28: 0 | AX28: 0 | AY28: 0 | AZ28: 0 | BA28: 0 | BB28: -0.096158 | BC28: 0.083924 | BD28: 0.0121 | BE28: 0.047183 | BF28: 0.006102 | BG28: 0.139076 | BH28: 0 | BI28: 0 | BJ28: 0.07 | BK28: 0.05 | BL28: 0 | BM28: 0 | BN28: 0 | BO28: 0.1472 | BP28: 0.031 | BQ28: 0.02 | BR28: 0 | BS28: 0 | BT28: 0 | BU28: 0 | BV28: 0 | BW28: 0 | BX28: 0 | BY28: 0 | BZ28: 18.421114 | CA28: 18.421114 | CB28: 16.827858 | CC28: 15.221992 | CD28: 15.732891 | CE28: 17.029783 | CF28: 16.419353 | CG28: 11.245904 | CH28: 10.363013 | CI28: 10.366093 | CJ28: 7.7422703 | CK28: 6.0712668 | CL28: 5.8788509 | CM28: 5.7175719 | CN28: 5.6214139 | CO28: 1.2106441 | CP28: 0.50341441 | CQ28: 0 | CR28: 0 | CS28: 0 | CT28: 0 | CU28: 0 | CV28: 0 | CW28: 0 | CX28: 0 | CY28: 46142 | CZ28: 46142 | DA28: 46112 | DB28: 46081 | DC28: 46053 | DD28: 46022 | DE28: 45991 | DF28: 45961 | DG28: 45930 | DH28: 45900 | DI28: 45869 | DJ28: 45838 | DK28: 45808 | DL28: 45777 | DM28: 45747 | DN28: 45716 | DO28: 45688 | DP28: 45291 | DQ28: 45291 | DR28: 45291 | DS28: 45291 | DT28: 45291 | DU28: 45291 | DV28: 45291 | DW28: 45291 | DX28: Aggregate MFs | DY28: Aggregate MFs | DZ28: Aggregate MFs | EA28: Aggregate MFs | EB28: Aggregate MFs | EC28: Aggregate MFs | ED28: Aggregate MFs | EE28: Aggregate MFs | EF28: Aggregate MFs | EG28: Aggregate MFs | EH28: Aggregate MFs | EI28: Aggregate MFs | EJ28: Aggregate MFs | EK28: Aggregate MFs | EL28: Aggregate MFs | EM28: Aggregate MFs | EN28: Aggregate MFs | EO28: Aggregate MFs | EP28: Aggregate MFs | EQ28: Aggregate MFs | ER28: Aggregate MFs | ES28: Aggregate MFs | ET28: Aggregate MFs | EU28: Aggregate MFs | EV28: Aggregate MFs | EW28: Investment Managers | EX28: Investment Advisor | EY28: 3077.9463 | FA28: Moderate | FB28: Moderate | FC28: Moderate | FD28: Moderate | FE28: Moderate | FF28: Moderate | FG28: Moderate | FH28: Moderate | FI28: Moderate | FJ28: Moderate | FK28: Moderate | FL28: Moderate | FM28: Moderate | FN28: Moderate | FO28: Moderate | FP28: Moderate | FQ28: Moderate | FR28: High | FS28: High | FT28: High | FU28: High | FV28: High | FW28: High | FX28: High | FY28: High | FZ28: Mumbai | GA28: India
A29: 27 | B29: Matthews International Capital Management, L.L.C. | C29: 0.003556 | D29: 0.003557 | E29: 0.003557 | F29: 0.003557 | G29: 0.003557 | H29: 0.003628 | I29: 0.003628 | J29: 0.003689 | K29: 0.003719 | L29: 0.00372 | M29: 0.003741 | N29: 0.003742 | O29: 0.003742 | P29: 0.003742 | Q29: 0.003742 | R29: 0.003736 | S29: 0.003848 | T29: 0.004156 | U29: 0.004144 | V29: 0.00429 | W29: 0.004571 | X29: 0.005056 | Y29: 0.005056 | Z29: 0.005046 | AA29: 0.005035 | AB29: 0.476264 | AC29: 0.476264 | AD29: 0.476264 | AE29: 0.476264 | AF29: 0.476264 | AG29: 0.485766 | AH29: 0.485766 | AI29: 0.493939 | AJ29: 0.49793 | AK29: 0.49793 | AL29: 0.50077 | AM29: 0.50077 | AN29: 0.50077 | AO29: 0.50077 | AP29: 0.50077 | AQ29: 0.499822 | AR29: 0.514822 | AS29: 0.556025 | AT29: 0.554432 | AU29: 0.573955 | AV29: 0.611466 | AW29: 0.676283 | AX29: 0.676283 | AY29: 0.67469 | AZ29: 0.673287 | BA29: 0 | BB29: 0 | BC29: 0 | BD29: 0 | BE29: -0.009502 | BF29: 0 | BG29: -0.008173 | BH29: -0.003991 | BI29: 0 | BJ29: -0.00284 | BK29: 0 | BL29: 0 | BM29: 0 | BN29: 0 | BO29: 0.000948 | BP29: -0.015 | BQ29: -0.041203 | BR29: 0.001593 | BS29: -0.019523 | BT29: -0.037511 | BU29: -0.064817 | BV29: 0 | BW29: 0.001593 | BX29: 0.001403 | BY29: 0.001593 | BZ29: 17.188184 | CA29: 17.188184 | CB29: 13.212498 | CC29: 13.870725 | CD29: 14.676032 | CE29: 17.852573 | CF29: 17.44234 | CG29: 17.456915 | CH29: 16.216389 | CI29: 16.22121 | CJ29: 15.620857 | CK29: 15.339598 | CL29: 14.853442 | CM29: 14.445956 | CN29: 14.203004 | CO29: 11.864835 | CP29: 12.958441 | CQ29: 16.951887 | CR29: 16.137257 | CS29: 15.30797 | CT29: 14.933116 | CU29: 15.660217 | CV29: 13.925745 | CW29: 14.45984 | CX29: 12.7234 | CY29: 46142 | CZ29: 46142 | DA29: 46112 | DB29: 46081 | DC29: 46053 | DD29: 46022 | DE29: 45991 | DF29: 45961 | DG29: 45930 | DH29: 45900 | DI29: 45869 | DJ29: 45838 | DK29: 45808 | DL29: 45777 | DM29: 45747 | DN29: 45716 | DO29: 45688 | DP29: 45657 | DQ29: 45626 | DR29: 45596 | DS29: 45565 | DT29: 45535 | DU29: 45504 | DV29: 45473 | DW29: 45443 | DX29: Aggregate MFs | DY29: Aggregate MFs | DZ29: Aggregate MFs | EA29: Aggregate MFs | EB29: Aggregate MFs | EC29: Aggregate MFs | ED29: Aggregate MFs | EE29: Aggregate MFs | EF29: Aggregate MFs | EG29: Aggregate MFs | EH29: Aggregate MFs | EI29: Aggregate MFs | EJ29: Aggregate MFs | EK29: Aggregate MFs | EL29: Aggregate MFs | EM29: Aggregate MFs | EN29: Aggregate MFs | EO29: Aggregate MFs | EP29: Aggregate MFs | EQ29: Aggregate MFs | ER29: Aggregate MFs | ES29: Aggregate MFs | ET29: Aggregate MFs | EU29: Aggregate MFs | EV29: Aggregate MFs | EW29: Investment Managers | EX29: Investment Advisor | EY29: 6915.9122 | EZ29: GARP | FA29: Moderate | FB29: Moderate | FC29: Moderate | FD29: Moderate | FE29: Moderate | FF29: Moderate | FG29: Moderate | FH29: Moderate | FI29: Moderate | FJ29: Moderate | FK29: Moderate | FL29: Moderate | FM29: Moderate | FN29: Moderate | FO29: Moderate | FP29: Moderate | FQ29: Moderate | FR29: Moderate | FS29: High | FT29: Moderate | FU29: Moderate | FV29: Moderate | FW29: Moderate | FX29: Moderate | FY29: Moderate | FZ29: San Francisco | GA29: United States
A30: 28 | B30: Caisse de Depot et Placement du Quebec | C30: 0.00352 | D30: 0.00352 | E30: 0.00352 | F30: 0.003521 | G30: 0.003521 | H30: 0.003521 | I30: 0.003521 | J30: 0.003521 | K30: 0.003521 | L30: 0.003521 | M30: 0.003521 | N30: 0.003522 | O30: 0.003522 | P30: 0.003523 | Q30: 0.003523 | R30: 0.003523 | S30: 0.003523 | T30: 0.003523 | U30: 0.004806 | V30: 0.004807 | W30: 0.004807 | X30: 0.004807 | Y30: 0.004807 | Z30: 0.004809 | AA30: 0.004809 | AB30: 0.471374 | AC30: 0.471374 | AD30: 0.471374 | AE30: 0.471374 | AF30: 0.471374 | AG30: 0.471374 | AH30: 0.471374 | AI30: 0.471374 | AJ30: 0.471374 | AK30: 0.471374 | AL30: 0.471374 | AM30: 0.471374 | AN30: 0.471374 | AO30: 0.471374 | AP30: 0.471374 | AQ30: 0.471374 | AR30: 0.471374 | AS30: 0.471374 | AT30: 0.643021 | AU30: 0.643021 | AV30: 0.643021 | AW30: 0.643021 | AX30: 0.643021 | AY30: 0.643021 | AZ30: 0.643021 | BA30: 0 | BB30: 0 | BC30: 0 | BD30: 0 | BE30: 0 | BF30: 0 | BG30: 0 | BH30: 0 | BI30: 0 | BJ30: 0 | BK30: 0 | BL30: 0 | BM30: 0 | BN30: 0 | BO30: 0 | BP30: 0 | BQ30: 0 | BR30: -0.171647 | BS30: 0 | BT30: 0 | BU30: 0 | BV30: 0 | BW30: 0 | BX30: 0 | BY30: 0 | BZ30: 14.371078 | CA30: 14.371078 | CB30: 14.371078 | CC30: 14.371078 | CD30: 14.371078 | CE30: 14.371078 | CF30: 14.371078 | CG30: 14.371078 | CH30: 14.371078 | CI30: 14.371078 | CJ30: 14.371078 | CK30: 14.371078 | CL30: 14.371078 | CM30: 14.371078 | CN30: 14.371078 | CO30: 14.371078 | CP30: 14.371078 | CQ30: 14.371078 | CR30: 12.817521 | CS30: 12.817521 | CT30: 12.817521 | CU30: 12.817521 | CV30: 12.817521 | CW30: 12.817521 | CX30: 12.817521 | CY30: 45657 | CZ30: 45657 | DA30: 45657 | DB30: 45657 | DC30: 45657 | DD30: 45657 | DE30: 45657 | DF30: 45657 | DG30: 45657 | DH30: 45657 | DI30: 45657 | DJ30: 45657 | DK30: 45657 | DL30: 45657 | DM30: 45657 | DN30: 45657 | DO30: 45657 | DP30: 45657 | DQ30: 45291 | DR30: 45291 | DS30: 45291 | DT30: 45291 | DU30: 45291 | DV30: 45291 | DW30: 45291 | DX30: Aggregate MFs | DY30: Aggregate MFs | DZ30: Aggregate MFs | EA30: Aggregate MFs | EB30: Aggregate MFs | EC30: Aggregate MFs | ED30: Aggregate MFs | EE30: Aggregate MFs | EF30: Aggregate MFs | EG30: Aggregate MFs | EH30: Aggregate MFs | EI30: Aggregate MFs | EJ30: Aggregate MFs | EK30: Aggregate MFs | EL30: Aggregate MFs | EM30: Aggregate MFs | EN30: Aggregate MFs | EO30: Aggregate MFs | EP30: Aggregate MFs | EQ30: Aggregate MFs | ER30: Aggregate MFs | ES30: Aggregate MFs | ET30: Aggregate MFs | EU30: Aggregate MFs | EV30: Aggregate MFs | EW30: Investment Managers | EX30: Pension Fund | EY30: 101974.41 | EZ30: GARP | FA30: Low | FB30: Low | FC30: Low | FD30: Low | FE30: Low | FF30: Low | FG30: Moderate | FH30: Moderate | FI30: Moderate | FJ30: Moderate | FK30: Moderate | FL30: Moderate | FM30: Low | FN30: Low | FO30: Low | FP30: Low | FQ30: Low | FR30: Low | FS30: Low | FT30: Low | FU30: Low | FV30: Low | FW30: Low | FX30: Low | FY30: Low | FZ30: Montreal | GA30: Canada
A31: 29 | B31: Manulife Investment Management (North America) Limited | C31: 0.002785 | D31: 0.002786 | E31: 0.002786 | F31: 0.002268 | G31: 0.002177 | H31: 0.002458 | I31: 2.8e-05 | J31: 2.8e-05 | K31: 2.8e-05 | L31: 2.8e-05 | M31: 2.8e-05 | N31: 2.8e-05 | AB31: 0.37304 | AC31: 0.37304 | AD31: 0.37304 | AE31: 0.303619 | AF31: 0.291535 | AG31: 0.329061 | AH31: 0.0037 | AI31: 0.0037 | AJ31: 0.0037 | AK31: 0.0037 | AL31: 0.0037 | AM31: 0.0037 | BA31: 0 | BB31: 0 | BC31: 0.069421 | BD31: 0.012084 | BE31: -0.037526 | BF31: 0.325361 | BG31: 0 | BH31: 0 | BI31: 0 | BJ31: 0 | BK31: 0 | BL31: 0.0037 | BZ31: 10.348862 | CA31: 10.348862 | CB31: 10.348862 | CC31: 8.8426076 | CD31: 8.9836248 | CE31: 12.093447 | CF31: 0.12050015 | CG31: 0.12050015 | CH31: 0.12050015 | CI31: 0.11333848 | CJ31: 0.11333848 | CK31: 0.11333848 | CY31: 46112 | CZ31: 46112 | DA31: 46112 | DB31: 46081 | DC31: 46053 | DD31: 46022 | DE31: 45930 | DF31: 45930 | DG31: 45930 | DH31: 45838 | DI31: 45838 | DJ31: 45838 | DX31: Aggregate MFs | DY31: Aggregate MFs | DZ31: Aggregate MFs | EA31: Aggregate MFs | EB31: Aggregate MFs | EC31: Aggregate MFs | ED31: Aggregate MFs | EE31: Aggregate MFs | EF31: Aggregate MFs | EG31: Aggregate MFs | EH31: Aggregate MFs | EI31: Aggregate MFs | EW31: Investment Managers | EX31: Investment Advisor | EY31: 195610.89 | EZ31: Core Value | FA31: Low | FB31: Low | FC31: Low | FD31: Low | FE31: Low | FF31: Low | FG31: Low | FH31: Low | FI31: Low | FJ31: Low | FK31: Low | FL31: Low | FZ31: Toronto | GA31: Canada
A32: 30 | B32: Khaitan (Abhishek) | C32: 0.002704 | D32: 0.002705 | E32: 0.002705 | F32: 0.002705 | G32: 0.002705 | H32: 0.002705 | I32: 0.000643 | J32: 0.000643 | K32: 0.000643 | L32: 0.000643 | M32: 0.000643 | N32: 0.000643 | O32: 0.000643 | P32: 0.000643 | Q32: 0.000643 | R32: 0.000643 | S32: 0.000643 | T32: 0.000643 | U32: 0.000643 | V32: 0.000643 | W32: 0.000643 | X32: 0.000643 | Y32: 0.000643 | Z32: 0.000644 | AA32: 0.000644 | AB32: 0.36221 | AC32: 0.36221 | AD32: 0.36221 | AE32: 0.36221 | AF32: 0.36221 | AG32: 0.36221 | AH32: 0.086065 | AI32: 0.086065 | AJ32: 0.086065 | AK32: 0.086065 | AL32: 0.086065 | AM32: 0.086065 | AN32: 0.086065 | AO32: 0.086065 | AP32: 0.086065 | AQ32: 0.086065 | AR32: 0.086065 | AS32: 0.086065 | AT32: 0.086065 | AU32: 0.086065 | AV32: 0.086065 | AW32: 0.086065 | AX32: 0.086065 | AY32: 0.086065 | AZ32: 0.086065 | BA32: 0 | BB32: 0 | BC32: 0 | BD32: 0 | BE32: 0 | BF32: 0.276145 | BG32: 0 | BH32: 0 | BI32: 0 | BJ32: 0 | BK32: 0 | BL32: 0 | BM32: 0 | BN32: 0 | BO32: 0 | BP32: 0 | BQ32: 0 | BR32: 0 | BS32: 0 | BT32: 0 | BU32: 0 | BV32: 0 | BW32: 0 | BX32: 0 | BY32: 0 | BZ32: 13.311719 | CA32: 13.311719 | CB32: 13.311719 | CC32: 13.311719 | CD32: 13.311719 | CE32: 13.311719 | CF32: 2.8029311 | CG32: 2.8029311 | CH32: 2.8029311 | CI32: 2.636345 | CJ32: 2.636345 | CK32: 2.636345 | CL32: 2.441004 | CM32: 2.441004 | CN32: 2.441004 | CO32: 2.6239182 | CP32: 2.6239182 | CQ32: 2.6239182 | CR32: 2.1018644 | CS32: 2.1018644 | CT32: 2.1018644 | CU32: 1.8445303 | CV32: 1.8445303 | CW32: 1.8445303 | CX32: 1.783986 | CY32: 46022 | CZ32: 46022 | DA32: 46022 | DB32: 46022 | DC32: 46022 | DD32: 46022 | DE32: 45930 | DF32: 45930 | DG32: 45930 | DH32: 45838 | DI32: 45838 | DJ32: 45838 | DK32: 45747 | DL32: 45747 | DM32: 45747 | DN32: 45657 | DO32: 45657 | DP32: 45657 | DQ32: 45565 | DR32: 45565 | DS32: 45565 | DT32: 45473 | DU32: 45473 | DV32: 45473 | DW32: 45382 | DX32: Shareholder Report | DY32: Shareholder Report | DZ32: Shareholder Report | EA32: Shareholder Report | EB32: Shareholder Report | EC32: Shareholder Report | ED32: Shareholder Report | EE32: Shareholder Report | EF32: Shareholder Report | EG32: Shareholder Report | EH32: Shareholder Report | EI32: Shareholder Report | EJ32: Shareholder Report | EK32: Shareholder Report | EL32: Shareholder Report | EM32: Shareholder Report | EN32: Shareholder Report | EO32: Shareholder Report | EP32: Shareholder Report | EQ32: Shareholder Report | ER32: Shareholder Report | ES32: Shareholder Report | ET32: Shareholder Report | EU32: Shareholder Report | EV32: Shareholder Report | EW32: Strategic Entities | EX32: Individual Investor | EY32: 13.311719 | FA32: Moderate | FB32: Moderate | FC32: Moderate | FD32: Moderate | FE32: Moderate | FF32: Moderate | FG32: Low | FH32: Low | FI32: Low | FJ32: Low | FK32: Low | FL32: Low | FM32: Low | FN32: Low | FO32: Low | FP32: Low | FQ32: Low | FR32: Low | FS32: Low | FT32: Low | FU32: Low | FV32: Low | FW32: Low | FX32: Low | FY32: Low | GA32: India
A33: 31 | B33: PGIM India Asset Management Private Limited | C33: 0.002639 | D33: 0.00264 | E33: 0.002571 | F33: 0.002571 | G33: 0.002571 | H33: 0.002719 | I33: 0.002356 | J33: 0.002356 | K33: 0.002561 | L33: 0.002561 | M33: 0.002561 | N33: 0.001049 | O33: 0.001049 | P33: 0.001049 | Q33: 0.001049 | R33: 0.001049 | S33: 0.001049 | T33: 0.001049 | U33: 0.001049 | V33: 0.001049 | W33: 0.000436 | X33: 0.011165 | Y33: 0.011165 | Z33: 0.011169 | AA33: 0.011169 | AB33: 0.353456 | AC33: 0.353456 | AD33: 0.344255 | AE33: 0.344255 | AF33: 0.344255 | AG33: 0.36399 | AH33: 0.31539 | AI33: 0.31539 | AJ33: 0.34289 | AK33: 0.34289 | AL33: 0.34289 | AM33: 0.140377 | AN33: 0.140377 | AO33: 0.140377 | AP33: 0.140377 | AQ33: 0.140377 | AR33: 0.140377 | AS33: 0.140377 | AT33: 0.140377 | AU33: 0.140377 | AV33: 0.058318 | AW33: 1.493473 | AX33: 1.493473 | AY33: 1.493473 | AZ33: 1.493473 | BA33: 0 | BB33: 0.009201 | BC33: 0 | BD33: 0 | BE33: -0.019735 | BF33: 0.0486 | BG33: 0 | BH33: -0.0275 | BI33: 0 | BJ33: 0 | BK33: 0.202513 | BL33: 0 | BM33: 0 | BN33: 0 | BO33: 0 | BP33: 0 | BQ33: 0 | BR33: 0 | BS33: 0 | BT33: 0.082059 | BU33: -1.435155 | BV33: 0 | BW33: 0 | BX33: 0 | BY33: 0 | BZ33: 12.756091 | CA33: 12.756091 | CB33: 9.5503094 | CC33: 10.026092 | CD33: 10.608187 | CE33: 13.377136 | CF33: 11.32467 | CG33: 11.146592 | CH33: 11.167107 | CI33: 11.170427 | CJ33: 10.695999 | CK33: 4.3000314 | CL33: 4.1637511 | CM33: 4.0495236 | CN33: 3.9814189 | CO33: 3.332286 | CP33: 3.5333902 | CQ33: 4.2797626 | CR33: 4.0858027 | CS33: 3.7439989 | CT33: 1.424232 | CU33: 21.987934 | CV33: 21.987934 | CW33: 21.987934 | CX33: 21.987934 | CY33: 46142 | CZ33: 46142 | DA33: 46112 | DB33: 46081 | DC33: 46053 | DD33: 46022 | DE33: 45991 | DF33: 45961 | DG33: 45930 | DH33: 45900 | DI33: 45869 | DJ33: 45838 | DK33: 45808 | DL33: 45777 | DM33: 45747 | DN33: 45716 | DO33: 45688 | DP33: 45657 | DQ33: 45626 | DR33: 45596 | DS33: 45565 | DT33: 45107 | DU33: 45107 | DV33: 45107 | DW33: 45107 | DX33: Aggregate MFs | DY33: Aggregate MFs | DZ33: Aggregate MFs | EA33: Aggregate MFs | EB33: Aggregate MFs | EC33: Aggregate MFs | ED33: Aggregate MFs | EE33: Aggregate MFs | EF33: Aggregate MFs | EG33: Aggregate MFs | EH33: Aggregate MFs | EI33: Aggregate MFs | EJ33: Aggregate MFs | EK33: Aggregate MFs | EL33: Aggregate MFs | EM33: Aggregate MFs | EN33: Aggregate MFs | EO33: Aggregate MFs | EP33: Aggregate MFs | EQ33: Aggregate MFs | ER33: Aggregate MFs | ES33: Shareholder Report | ET33: Shareholder Report | EU33: Shareholder Report | EV33: Shareholder Report | EW33: Investment Managers | EX33: Investment Advisor | EY33: 2345.4074 | FA33: Low | FB33: Low | FC33: Low | FD33: Low | FE33: Low | FF33: Low | FG33: Low | FH33: Low | FI33: Low | FJ33: Low | FK33: Low | FL33: Low | FM33: Low | FN33: Low | FO33: Moderate | FP33: Moderate | FQ33: Moderate | FR33: Moderate | FS33: Moderate | FT33: Moderate | FU33: Moderate | FV33: Moderate | FW33: Moderate | FX33: Moderate | FY33: Moderate | FZ33: Mumbai | GA33: India
A34: 32 | B34: Dimensional Fund Advisors, L.P. | C34: 0.002638 | D34: 0.002639 | E34: 0.002613 | F34: 0.002613 | G34: 0.002554 | H34: 0.002343 | I34: 0.002304 | J34: 0.002304 | K34: 0.002252 | L34: 0.002233 | M34: 0.002226 | N34: 0.00219 | O34: 0.00219 | P34: 0.00219 | Q34: 0.00212 | R34: 0.002136 | S34: 0.002078 | T34: 0.00195 | U34: 0.001893 | V34: 0.00185 | W34: 0.001899 | X34: 0.001899 | Y34: 0.001899 | Z34: 0.002777 | AA34: 0.002827 | AB34: 0.353322 | AC34: 0.353322 | AD34: 0.349899 | AE34: 0.349899 | AF34: 0.342025 | AG34: 0.313735 | AH34: 0.30851 | AI34: 0.30851 | AJ34: 0.301509 | AK34: 0.298959 | AL34: 0.297987 | AM34: 0.293096 | AN34: 0.293096 | AO34: 0.293096 | AP34: 0.283676 | AQ34: 0.285752 | AR34: 0.278109 | AS34: 0.260945 | AT34: 0.253313 | AU34: 0.247465 | AV34: 0.254082 | AW34: 0.254082 | AX34: 0.254082 | AY34: 0.371351 | AZ34: 0.378056 | BA34: 0 | BB34: 0.003423 | BC34: 0 | BD34: 0.007874 | BE34: 0.02829 | BF34: 0.005225 | BG34: 0 | BH34: 0.007001 | BI34: 0.00255 | BJ34: 0.000972 | BK34: 0.004891 | BL34: 0 | BM34: 0 | BN34: 0.00942 | BO34: -0.002076 | BP34: 0.007643 | BQ34: 0.017164 | BR34: 0.007632 | BS34: 0.005848 | BT34: -0.006617 | BU34: 0 | BV34: 0 | BW34: -0.117269 | BX34: -0.006705 | BY34: 0 | BZ34: 12.751255 | CA34: 12.751255 | CB34: 9.706885 | CC34: 10.190468 | CD34: 10.53947 | CE34: 11.530196 | CF34: 11.077631 | CG34: 10.903437 | CH34: 9.8194267 | CI34: 9.7392737 | CJ34: 9.2953098 | CK34: 8.9781233 | CL34: 8.6935807 | CM34: 8.455083 | CN34: 8.0457125 | CO34: 6.7832152 | CP34: 7.0002039 | CQ34: 7.9555956 | CR34: 7.3729097 | CS34: 6.600146 | CT34: 6.2051463 | CU34: 5.8836008 | CV34: 5.2319536 | CW34: 7.9587307 | CX34: 7.1442904 | CY34: 46142 | CZ34: 46142 | DA34: 46112 | DB34: 46081 | DC34: 46053 | DD34: 46022 | DE34: 45991 | DF34: 45961 | DG34: 45930 | DH34: 45900 | DI34: 45869 | DJ34: 45838 | DK34: 45808 | DL34: 45777 | DM34: 45747 | DN34: 45716 | DO34: 45688 | DP34: 45657 | DQ34: 45626 | DR34: 45596 | DS34: 45565 | DT34: 45535 | DU34: 45504 | DV34: 45473 | DW34: 45443 | DX34: Aggregate MFs | DY34: Aggregate MFs | DZ34: Aggregate MFs | EA34: Aggregate MFs | EB34: Aggregate MFs | EC34: Aggregate MFs | ED34: Aggregate MFs | EE34: Aggregate MFs | EF34: Aggregate MFs | EG34: Aggregate MFs | EH34: Aggregate MFs | EI34: Aggregate MFs | EJ34: Aggregate MFs | EK34: Aggregate MFs | EL34: Aggregate MFs | EM34: Aggregate MFs | EN34: Aggregate MFs | EO34: Aggregate MFs | EP34: Aggregate MFs | EQ34: Aggregate MFs | ER34: Aggregate MFs | ES34: Aggregate MFs | ET34: Aggregate MFs | EU34: Aggregate MFs | EV34: Aggregate MFs | EW34: Investment Managers | EX34: Investment Advisor/Hedge Fund | EY34: 739135.54 | EZ34: Deep Value | FA34: Low | FB34: Low | FC34: Low | FD34: Low | FE34: Low | FF34: Low | FG34: Low | FH34: Low | FI34: Low | FJ34: Low | FK34: Low | FL34: Low | FM34: Low | FN34: Low | FO34: Low | FP34: Low | FQ34: Low | FR34: Low | FS34: Low | FT34: Low | FU34: Low | FV34: Low | FW34: Low | FX34: Low | FY34: Low | FZ34: Austin | GA34: United States
A35: 33 | B35: Old Bridge Capital Management Pvt. Ltd. | C35: 0.002524 | D35: 0.002524 | E35: 0.002226 | F35: 0.00189 | G35: 0.00189 | H35: 0.00189 | I35: 0.00189 | J35: 0.001703 | K35: 0.001703 | L35: 0.001703 | M35: 0.001599 | N35: 0.001599 | O35: 0.001599 | P35: 0.001428 | Q35: 0.001129 | R35: 0.001129 | S35: 0.001129 | T35: 0.001129 | U35: 0.001129 | V35: 0.001129 | W35: 0.001129 | X35: 0.001129 | Y35: 0.00071 | Z35: 0.000621 | AA35: 0.000535 | AB35: 0.338 | AC35: 0.338 | AD35: 0.298 | AE35: 0.253 | AF35: 0.253 | AG35: 0.253 | AH35: 0.253 | AI35: 0.228 | AJ35: 0.228 | AK35: 0.228 | AL35: 0.214033 | AM35: 0.214033 | AN35: 0.214033 | AO35: 0.191033 | AP35: 0.151033 | AQ35: 0.151033 | AR35: 0.151033 | AS35: 0.151033 | AT35: 0.151033 | AU35: 0.151033 | AV35: 0.151033 | AW35: 0.151033 | AX35: 0.095033 | AY35: 0.083062 | AZ35: 0.07155 | BA35: 0 | BB35: 0.04 | BC35: 0.045 | BD35: 0 | BE35: 0 | BF35: 0 | BG35: 0.025 | BH35: 0 | BI35: 0 | BJ35: 0.013967 | BK35: 0 | BL35: 0 | BM35: 0.023 | BN35: 0.04 | BO35: 0 | BP35: 0 | BQ35: 0 | BR35: 0 | BS35: 0 | BT35: 0 | BU35: 0 | BV35: 0.056 | BW35: 0.011971 | BX35: 0.011512 | BY35: 0 | BZ35: 12.19829 | CA35: 12.19829 | CB35: 8.2671049 | CC35: 7.3683785 | CD35: 7.7961722 | CE35: 9.2981003 | CF35: 9.0844401 | CG35: 8.0580328 | CH35: 7.4254144 | CI35: 7.4276219 | CJ35: 6.676476 | CK35: 6.5562637 | CL35: 6.3484768 | CM35: 5.5108219 | CN35: 4.2836479 | CO35: 3.5852394 | CP35: 3.8016094 | CQ35: 4.6046388 | CR35: 4.3959555 | CS35: 4.0282054 | CT35: 3.6885016 | CU35: 3.4973665 | CV35: 1.956881 | CW35: 1.7801705 | CX35: 1.3521118 | CY35: 46142 | CZ35: 46142 | DA35: 46112 | DB35: 46081 | DC35: 46053 | DD35: 46022 | DE35: 45991 | DF35: 45961 | DG35: 45930 | DH35: 45900 | DI35: 45869 | DJ35: 45838 | DK35: 45808 | DL35: 45777 | DM35: 45747 | DN35: 45716 | DO35: 45688 | DP35: 45657 | DQ35: 45626 | DR35: 45596 | DS35: 45565 | DT35: 45535 | DU35: 45504 | DV35: 45473 | DW35: 45443 | DX35: Aggregate MFs | DY35: Aggregate MFs | DZ35: Aggregate MFs | EA35: Aggregate MFs | EB35: Aggregate MFs | EC35: Aggregate MFs | ED35: Aggregate MFs | EE35: Aggregate MFs | EF35: Aggregate MFs | EG35: Aggregate MFs | EH35: Aggregate MFs | EI35: Aggregate MFs | EJ35: Aggregate MFs | EK35: Aggregate MFs | EL35: Aggregate MFs | EM35: Aggregate MFs | EN35: Aggregate MFs | EO35: Aggregate MFs | EP35: Aggregate MFs | EQ35: Aggregate MFs | ER35: Aggregate MFs | ES35: Aggregate MFs | ET35: Aggregate MFs | EU35: Aggregate MFs | EV35: Aggregate MFs | EW35: Investment Managers | EX35: Investment Advisor | EY35: 244.69327 | FA35: Low | FB35: Low | FC35: Low | FD35: Low | FE35: Low | FF35: Low | FG35: Low | FH35: Low | FI35: Low | FJ35: Moderate | FK35: Moderate | FL35: Moderate | FM35: Moderate | FN35: Moderate | FO35: Moderate | FP35: High | FQ35: Low | FR35: High | FS35: High | FT35: Low | FU35: High | FV35: High | FW35: Low | FX35: High | FY35: High | FZ35: Mumbai | GA35: India
A36: 34 | B36: BlackRock Advisors (UK) Limited | C36: 0.002474 | D36: 0.002474 | E36: 0.002479 | F36: 0.00257 | G36: 0.002412 | H36: 0.00236 | I36: 0.002351 | J36: 0.002186 | K36: 0.002183 | L36: 0.002148 | M36: 0.002118 | N36: 0.0021 | O36: 0.002089 | P36: 0.001983 | Q36: 0.001969 | R36: 0.001955 | S36: 0.001944 | T36: 0.001942 | U36: 0.001927 | V36: 0.001917 | W36: 0.001881 | X36: 0.001831 | Y36: 0.001794 | Z36: 0.001869 | AA36: 0.001854 | AB36: 0.331326 | AC36: 0.331326 | AD36: 0.331887 | AE36: 0.344094 | AF36: 0.322918 | AG36: 0.315949 | AH36: 0.314791 | AI36: 0.292657 | AJ36: 0.292277 | AK36: 0.287547 | AL36: 0.283581 | AM36: 0.281016 | AN36: 0.279614 | AO36: 0.265296 | AP36: 0.263508 | AQ36: 0.261561 | AR36: 0.260145 | AS36: 0.259869 | AT36: 0.257792 | AU36: 0.256393 | AV36: 0.251593 | AW36: 0.244871 | AX36: 0.239961 | AY36: 0.249973 | AZ36: 0.247903 | BA36: 0 | BB36: -0.000561 | BC36: -0.012207 | BD36: 0.021176 | BE36: 0.006969 | BF36: 0.001158 | BG36: 0.022134 | BH36: 0.00038 | BI36: 0.00473 | BJ36: 0.003966 | BK36: 0.002565 | BL36: 0.001402 | BM36: 0.014318 | BN36: 0.001788 | BO36: 0.001947 | BP36: 0.001416 | BQ36: 0.000276 | BR36: 0.002077 | BS36: 0.001399 | BT36: 0.0048 | BU36: 0.006722 | BV36: 0.00491 | BW36: -0.010012 | BX36: 0.00207 | BY36: 0.005896 | BZ36: 11.957428 | CA36: 11.957428 | CB36: 9.2071968 | CC36: 10.021403 | CD36: 9.9506891 | CE36: 11.611563 | CF36: 11.303162 | CG36: 10.343157 | CH36: 9.5187625 | CI36: 9.3675017 | CJ36: 8.8459338 | CK36: 8.6080884 | CL36: 8.2936883 | CM36: 7.6531228 | CN36: 7.473701 | CO36: 6.2089663 | CP36: 6.5480371 | CQ36: 7.9227909 | CR36: 7.5032751 | CS36: 6.838265 | CT36: 6.1443604 | CU36: 5.6703081 | CV36: 4.9411796 | CW36: 5.3573783 | CX36: 4.684732 | CY36: 46142 | CZ36: 46142 | DA36: 46112 | DB36: 46081 | DC36: 46053 | DD36: 46022 | DE36: 45991 | DF36: 45961 | DG36: 45930 | DH36: 45900 | DI36: 45869 | DJ36: 45838 | DK36: 45808 | DL36: 45777 | DM36: 45747 | DN36: 45716 | DO36: 45688 | DP36: 45657 | DQ36: 45626 | DR36: 45596 | DS36: 45565 | DT36: 45535 | DU36: 45504 | DV36: 45473 | DW36: 45443 | DX36: Aggregate MFs | DY36: Aggregate MFs | DZ36: Aggregate MFs | EA36: Aggregate MFs | EB36: Aggregate MFs | EC36: Aggregate MFs | ED36: Aggregate MFs | EE36: Aggregate MFs | EF36: Aggregate MFs | EG36: Aggregate MFs | EH36: Aggregate MFs | EI36: Aggregate MFs | EJ36: Aggregate MFs | EK36: Aggregate MFs | EL36: Aggregate MFs | EM36: Aggregate MFs | EN36: Aggregate MFs | EO36: Aggregate MFs | EP36: Aggregate MFs | EQ36: Aggregate MFs | ER36: Aggregate MFs | ES36: Aggregate MFs | ET36: Aggregate MFs | EU36: Aggregate MFs | EV36: Aggregate MFs | EW36: Investment Managers | EX36: Investment Advisor/Hedge Fund | EY36: 476353.18 | EZ36: Index | FA36: Low | FB36: Low | FC36: Low | FD36: Low | FE36: Low | FF36: Low | FG36: Low | FH36: Low | FI36: Low | FJ36: Low | FK36: Low | FL36: Low | FM36: Low | FN36: Low | FO36: Low | FP36: Low | FQ36: Low | FR36: Low | FS36: Low | FT36: Low | FU36: Low | FV36: Low | FW36: Low | FX36: Low | FY36: Low | FZ36: London | GA36: United Kingdom
A37: 35 | B37: State Street Investment Management (US) | C37: 0.002175 | D37: 0.002176 | E37: 0.002176 | F37: 0.00218 | G37: 0.002121 | H37: 0.002093 | I37: 0.00207 | J37: 0.001973 | K37: 0.001962 | L37: 0.001897 | M37: 0.001868 | N37: 0.001844 | O37: 0.00181 | P37: 0.001736 | Q37: 0.001706 | R37: 0.001706 | S37: 0.001648 | T37: 0.001648 | U37: 0.001648 | V37: 0.001649 | W37: 0.001579 | X37: 0.001579 | Y37: 0.001564 | Z37: 0.001547 | AA37: 0.001547 | AB37: 0.291339 | AC37: 0.291339 | AD37: 0.291339 | AE37: 0.291821 | AF37: 0.283936 | AG37: 0.280205 | AH37: 0.277165 | AI37: 0.264205 | AJ37: 0.262685 | AK37: 0.253896 | AL37: 0.250032 | AM37: 0.246752 | AN37: 0.24227 | AO37: 0.23231 | AP37: 0.228227 | AQ37: 0.228227 | AR37: 0.220541 | AS37: 0.220541 | AT37: 0.220541 | AU37: 0.220577 | AV37: 0.211194 | AW37: 0.211194 | AX37: 0.20925 | AY37: 0.20681 | AZ37: 0.20681 | BA37: 0 | BB37: 0 | BC37: -0.000482 | BD37: 0.007885 | BE37: 0.003731 | BF37: 0.00304 | BG37: 0.01296 | BH37: 0.00152 | BI37: 0.008789 | BJ37: 0.003864 | BK37: 0.00328 | BL37: 0.004482 | BM37: 0.00996 | BN37: 0.004083 | BO37: 0 | BP37: 0.007686 | BQ37: 0 | BR37: 0 | BS37: -3.6e-05 | BT37: 0.009383 | BU37: 0 | BV37: 0.001944 | BW37: 0.00244 | BX37: 0 | BY37: 0.000324 | BZ37: 10.514312 | CA37: 10.514312 | CB37: 8.0823157 | CC37: 8.4990023 | CD37: 8.7494623 | CE37: 10.297922 | CF37: 9.9521298 | CG37: 9.337599 | CH37: 8.5550219 | CI37: 8.2712434 | CJ37: 7.7994171 | CK37: 7.5585128 | CL37: 7.1860203 | CM37: 6.7015596 | CN37: 6.4730497 | CO37: 5.4176799 | CP37: 5.5511759 | CQ37: 6.7237732 | CR37: 6.4190502 | CS37: 5.8830154 | CT37: 5.157743 | CU37: 4.8904731 | CV37: 4.3087912 | CW37: 4.4323163 | CX37: 3.9081795 | CY37: 46142 | CZ37: 46142 | DA37: 46112 | DB37: 46081 | DC37: 46053 | DD37: 46022 | DE37: 45991 | DF37: 45961 | DG37: 45930 | DH37: 45900 | DI37: 45869 | DJ37: 45838 | DK37: 45808 | DL37: 45777 | DM37: 45747 | DN37: 45716 | DO37: 45688 | DP37: 45657 | DQ37: 45626 | DR37: 45596 | DS37: 45565 | DT37: 45535 | DU37: 45504 | DV37: 45473 | DW37: 45443 | DX37: Aggregate MFs | DY37: Aggregate MFs | DZ37: Aggregate MFs | EA37: Aggregate MFs | EB37: Aggregate MFs | EC37: Aggregate MFs | ED37: Aggregate MFs | EE37: Aggregate MFs | EF37: Aggregate MFs | EG37: Aggregate MFs | EH37: Aggregate MFs | EI37: Aggregate MFs | EJ37: Aggregate MFs | EK37: Aggregate MFs | EL37: Aggregate MFs | EM37: Aggregate MFs | EN37: Aggregate MFs | EO37: Aggregate MFs | EP37: Aggregate MFs | EQ37: Aggregate MFs | ER37: Aggregate MFs | ES37: Aggregate MFs | ET37: Aggregate MFs | EU37: Aggregate MFs | EV37: Aggregate MFs | EW37: Investment Managers | EX37: Investment Advisor/Hedge Fund | EY37: 3155327.4 | EZ37: Index | FA37: Low | FB37: Low | FC37: Low | FD37: Low | FE37: Low | FF37: Low | FG37: Low | FH37: Low | FI37: Low | FJ37: Low | FK37: Low | FL37: Low | FM37: Low | FN37: Low | FO37: Low | FP37: Low | FQ37: Low | FR37: Low | FS37: Low | FT37: Low | FU37: Low | FV37: Low | FW37: Low | FX37: Low | FY37: Low | FZ37: Boston | GA37: United States
A38: 36 | B38: ITI Asset Management Limited | C38: 0.001771 | D38: 0.001772 | E38: 0.001588 | F38: 0.001534 | G38: 0.001534 | H38: 0.001507 | I38: 0.001516 | J38: 0.001601 | K38: 0.001697 | L38: 0.001604 | M38: 0.00166 | N38: 0.001355 | O38: 0.001341 | P38: 0.001341 | Q38: 0.001341 | R38: 0.001271 | S38: 0.001271 | T38: 0.001271 | U38: 0.001271 | V38: 0.001271 | W38: 0.001271 | X38: 0.001271 | Y38: 0.001271 | Z38: 0.001201 | AA38: 0.001147 | AB38: 0.237234 | AC38: 0.237234 | AD38: 0.212575 | AE38: 0.205435 | AF38: 0.205435 | AG38: 0.20183 | AH38: 0.203037 | AI38: 0.214302 | AJ38: 0.227251 | AK38: 0.214658 | AL38: 0.22217 | AM38: 0.181366 | AN38: 0.179498 | AO38: 0.179498 | AP38: 0.179498 | AQ38: 0.170041 | AR38: 0.170041 | AS38: 0.170041 | AT38: 0.170041 | AU38: 0.170041 | AV38: 0.170041 | AW38: 0.170041 | AX38: 0.170041 | AY38: 0.160582 | AZ38: 0.153426 | BA38: 0 | BB38: 0.024659 | BC38: 0.00714 | BD38: 0 | BE38: 0.003605 | BF38: -0.001207 | BG38: -0.011265 | BH38: -0.012949 | BI38: 0.012593 | BJ38: -0.007512 | BK38: 0.040804 | BL38: 0.001868 | BM38: 0 | BN38: 0 | BO38: 0.009457 | BP38: 0 | BQ38: 0 | BR38: 0 | BS38: 0 | BT38: 0 | BU38: 0 | BV38: 0 | BW38: 0.009459 | BX38: 0.007156 | BY38: 0 | BZ38: 8.5616838 | CA38: 8.5616838 | CB38: 5.8972477 | CC38: 5.9830942 | CD38: 6.3304611 | CE38: 7.4175319 | CF38: 7.2904247 | CG38: 7.5739147 | CH38: 7.4010213 | CI38: 6.9929757 | CJ38: 6.9302989 | CK38: 5.5556074 | CL38: 5.3241271 | CM38: 5.1780662 | CN38: 5.0909816 | CO38: 4.0364536 | CP38: 4.2800545 | CQ38: 5.1841477 | CR38: 4.9492009 | CS38: 4.5351683 | CT38: 4.1527116 | CU38: 3.9375216 | CV38: 3.5014153 | CW38: 3.4415658 | CX38: 2.8993586 | CY38: 46142 | CZ38: 46142 | DA38: 46112 | DB38: 46081 | DC38: 46053 | DD38: 46022 | DE38: 45991 | DF38: 45961 | DG38: 45930 | DH38: 45900 | DI38: 45869 | DJ38: 45838 | DK38: 45808 | DL38: 45777 | DM38: 45747 | DN38: 45716 | DO38: 45688 | DP38: 45657 | DQ38: 45626 | DR38: 45596 | DS38: 45565 | DT38: 45535 | DU38: 45504 | DV38: 45473 | DW38: 45443 | DX38: Aggregate MFs | DY38: Aggregate MFs | DZ38: Aggregate MFs | EA38: Aggregate MFs | EB38: Aggregate MFs | EC38: Aggregate MFs | ED38: Aggregate MFs | EE38: Aggregate MFs | EF38: Aggregate MFs | EG38: Aggregate MFs | EH38: Aggregate MFs | EI38: Aggregate MFs | EJ38: Aggregate MFs | EK38: Aggregate MFs | EL38: Aggregate MFs | EM38: Aggregate MFs | EN38: Aggregate MFs | EO38: Aggregate MFs | EP38: Aggregate MFs | EQ38: Aggregate MFs | ER38: Aggregate MFs | ES38: Aggregate MFs | ET38: Aggregate MFs | EU38: Aggregate MFs | EV38: Aggregate MFs | EW38: Investment Managers | EX38: Investment Advisor | EY38: 999.14523 | FA38: Moderate | FB38: Moderate | FC38: Moderate | FD38: Moderate | FE38: Moderate | FF38: Moderate | FG38: Moderate | FH38: Moderate | FI38: Moderate | FJ38: Moderate | FK38: Moderate | FL38: Moderate | FM38: Moderate | FN38: Moderate | FO38: Moderate | FP38: Moderate | FQ38: Moderate | FR38: Moderate | FS38: Moderate | FT38: Moderate | FU38: Moderate | FV38: Moderate | FW38: Moderate | FX38: Moderate | FY38: Moderate | FZ38: Mumbai | GA38: India
A39: 37 | B39: Union Asset Management Company Private Limited | C39: 0.001605 | D39: 0.001606 | E39: 0.001501 | F39: 0.001319 | G39: 0.001319 | H39: 0.000896 | I39: 0.000896 | J39: 0.000896 | K39: 0.000896 | L39: 0.000896 | M39: 0.001173 | N39: 0.001173 | O39: 0.001173 | P39: 0.000747 | Q39: 0.000581 | R39: 0.000581 | S39: 0 | T39: 0 | U39: 0 | V39: 0 | W39: 0 | X39: 0 | Y39: 0 | Z39: 0 | AA39: 0 | AB39: 0.214975 | AC39: 0.214975 | AD39: 0.200993 | AE39: 0.176601 | AF39: 0.176601 | AG39: 0.12 | AH39: 0.12 | AI39: 0.12 | AJ39: 0.12 | AK39: 0.12 | AL39: 0.157 | AM39: 0.157 | AN39: 0.157 | AO39: 0.1 | AP39: 0.077777 | AQ39: 0.077777 | AR39: 0 | AS39: 0 | AT39: 0 | AU39: 0 | AV39: 0 | AW39: 0 | AX39: 0 | AY39: 0 | AZ39: 0 | BA39: 0 | BB39: 0.013982 | BC39: 0.024392 | BD39: 0 | BE39: 0.056601 | BF39: 0 | BG39: 0 | BH39: 0 | BI39: 0 | BJ39: -0.037 | BK39: 0 | BL39: 0 | BM39: 0.057 | BN39: 0.022223 | BO39: 0 | BP39: 0.077777 | BQ39: 0 | BR39: 0 | BS39: 0 | BT39: 0 | BU39: 0 | BV39: 0 | BW39: 0 | BX39: 0 | BY39: 0 | BZ39: 7.758365 | CA39: 7.758365 | CB39: 5.5759403 | CC39: 5.1433321 | CD39: 5.4419439 | CE39: 4.4101661 | CF39: 4.3088253 | CG39: 4.2410699 | CH39: 3.9081129 | CI39: 3.9092747 | CJ39: 4.8974071 | CK39: 4.8092275 | CL39: 4.6568093 | CM39: 2.8847487 | CN39: 2.205937 | CO39: 1.8462797 | CP39: 0 | CQ39: 0 | CR39: 0 | CS39: 0 | CT39: 0 | CU39: 0 | CV39: 0 | CW39: 0 | CX39: 0 | CY39: 46142 | CZ39: 46142 | DA39: 46112 | DB39: 46081 | DC39: 46053 | DD39: 46022 | DE39: 45991 | DF39: 45961 | DG39: 45930 | DH39: 45900 | DI39: 45869 | DJ39: 45838 | DK39: 45808 | DL39: 45777 | DM39: 45747 | DN39: 45716 | DO39: 45382 | DP39: 45382 | DQ39: 45382 | DR39: 45382 | DS39: 45382 | DT39: 45382 | DU39: 45382 | DV39: 45382 | DW39: 45382 | DX39: Aggregate MFs | DY39: Aggregate MFs | DZ39: Aggregate MFs | EA39: Aggregate MFs | EB39: Aggregate MFs | EC39: Aggregate MFs | ED39: Aggregate MFs | EE39: Aggregate MFs | EF39: Aggregate MFs | EG39: Aggregate MFs | EH39: Aggregate MFs | EI39: Aggregate MFs | EJ39: Aggregate MFs | EK39: Aggregate MFs | EL39: Aggregate MFs | EM39: Aggregate MFs | EN39: Aggregate MFs | EO39: Aggregate MFs | EP39: Aggregate MFs | EQ39: Aggregate MFs | ER39: Aggregate MFs | ES39: Aggregate MFs | ET39: Aggregate MFs | EU39: Aggregate MFs | EV39: Aggregate MFs | EW39: Investment Managers | EX39: Investment Advisor | EY39: 1533.2535 | FA39: Moderate | FB39: Moderate | FC39: Moderate | FD39: Moderate | FE39: Moderate | FF39: Moderate | FG39: Moderate | FH39: Moderate | FI39: Moderate | FJ39: Moderate | FK39: Moderate | FL39: Moderate | FM39: High | FN39: High | FO39: High | FP39: High | FQ39: High | FR39: High | FS39: High | FT39: High | FU39: High | FV39: High | FW39: High | FX39: High | FY39: High | FZ39: Mumbai | GA39: India
A40: 38 | B40: First Sentier Investors | C40: 0.001359 | D40: 0.00136 | E40: 0.00136 | F40: 0.00136 | G40: 0.00136 | H40: 0.001854 | I40: 0.00214 | J40: 0.00214 | K40: 0.002028 | L40: 0.001915 | M40: 0.001915 | N40: 0.001915 | O40: 0.001915 | P40: 0.002451 | Q40: 0.002451 | R40: 0.002451 | S40: 0.002451 | T40: 0.002896 | U40: 0.002896 | V40: 0.003595 | W40: 0.003892 | X40: 0.004469 | Y40: 0.004469 | Z40: 0.004471 | AA40: 0.004471 | AB40: 0.182054 | AC40: 0.182054 | AD40: 0.182054 | AE40: 0.182054 | AF40: 0.182054 | AG40: 0.248248 | AH40: 0.286467 | AI40: 0.286467 | AJ40: 0.271555 | AK40: 0.256306 | AL40: 0.256306 | AM40: 0.256306 | AN40: 0.256306 | AO40: 0.327984 | AP40: 0.327984 | AQ40: 0.327984 | AR40: 0.327984 | AS40: 0.387483 | AT40: 0.387483 | AU40: 0.480872 | AV40: 0.520572 | AW40: 0.597823 | AX40: 0.597823 | AY40: 0.597823 | AZ40: 0.597823 | BA40: 0 | BB40: 0 | BC40: 0 | BD40: 0 | BE40: -0.066194 | BF40: -0.038219 | BG40: 0 | BH40: 0.014912 | BI40: 0.015249 | BJ40: 0 | BK40: 0 | BL40: 0 | BM40: -0.071678 | BN40: 0 | BO40: 0 | BP40: 0 | BQ40: -0.059499 | BR40: 0 | BS40: -0.093389 | BT40: -0.0397 | BU40: -0.077251 | BV40: 0 | BW40: 0 | BX40: 0 | BY40: 0 | BZ40: 5.0505353 | CA40: 5.0505353 | CB40: 5.0505353 | CC40: 5.3021454 | CD40: 5.6099776 | CE40: 9.1234577 | CF40: 10.286136 | CG40: 10.124388 | CH40: 8.8438966 | CI40: 8.3497546 | CJ40: 7.9951263 | CK40: 7.8511711 | CL40: 7.6023449 | CM40: 9.4615141 | CN40: 7.7857235 | CO40: 7.7857235 | CP40: 8.2555936 | CQ40: 11.81344 | CR40: 11.278052 | CS40: 12.825351 | CT40: 12.713319 | CU40: 13.843373 | CV40: 12.310129 | CW40: 12.81244 | CX40: 11.297324 | CY40: 46112 | CZ40: 46112 | DA40: 46112 | DB40: 46081 | DC40: 46053 | DD40: 46022 | DE40: 45991 | DF40: 45961 | DG40: 45930 | DH40: 45900 | DI40: 45869 | DJ40: 45838 | DK40: 45808 | DL40: 45777 | DM40: 45716 | DN40: 45716 | DO40: 45688 | DP40: 45657 | DQ40: 45626 | DR40: 45596 | DS40: 45565 | DT40: 45535 | DU40: 45504 | DV40: 45473 | DW40: 45443 | DX40: Aggregate MFs | DY40: Aggregate MFs | DZ40: Aggregate MFs | EA40: Aggregate MFs | EB40: Aggregate MFs | EC40: Aggregate MFs | ED40: Aggregate MFs | EE40: Aggregate MFs | EF40: Aggregate MFs | EG40: Aggregate MFs | EH40: Aggregate MFs | EI40: Aggregate MFs | EJ40: Aggregate MFs | EK40: Aggregate MFs | EL40: Aggregate MFs | EM40: Aggregate MFs | EN40: Aggregate MFs | EO40: Aggregate MFs | EP40: Aggregate MFs | EQ40: Aggregate MFs | ER40: Aggregate MFs | ES40: Aggregate MFs | ET40: Aggregate MFs | EU40: Aggregate MFs | EV40: Aggregate MFs | EW40: Investment Managers | EX40: Investment Advisor | EY40: 7478.4911 | EZ40: Growth | FA40: Moderate | FB40: Moderate | FC40: Moderate | FD40: Moderate | FE40: Moderate | FF40: Moderate | FG40: Moderate | FH40: Moderate | FI40: Moderate | FJ40: Moderate | FK40: Moderate | FL40: Moderate | FM40: Moderate | FN40: Moderate | FO40: Moderate | FP40: Moderate | FQ40: Moderate | FR40: Moderate | FS40: Moderate | FT40: Moderate | FU40: Moderate | FV40: Moderate | FW40: Moderate | FX40: Moderate | FY40: Moderate | FZ40: Sydney | GA40: Australia
A41: 39 | B41: Causeway Capital Management LLC | C41: 0.001308 | D41: 0.001308 | E41: 0.001308 | F41: 0.001311 | G41: 0.001311 | H41: 0.001311 | AB41: 0.175175 | AC41: 0.175175 | AD41: 0.175175 | AE41: 0.175591 | AF41: 0.175591 | AG41: 0.175591 | BA41: 0 | BB41: 0 | BC41: -0.000416 | BD41: 0 | BE41: 0 | BF41: 0.175591 | BZ41: 4.8596983 | CA41: 4.8596983 | CB41: 4.8596983 | CC41: 6.4532123 | CD41: 6.4532123 | CE41: 6.4532123 | CY41: 46112 | CZ41: 46112 | DA41: 46112 | DB41: 46022 | DC41: 46022 | DD41: 46022 | DX41: Aggregate MFs | DY41: Aggregate MFs | DZ41: Aggregate MFs | EA41: Aggregate MFs | EB41: Aggregate MFs | EC41: Aggregate MFs | EW41: Investment Managers | EX41: Investment Advisor | EY41: 41079.635 | EZ41: Core Value | FA41: Low | FB41: Low | FC41: Low | FD41: Low | FE41: Low | FF41: Moderate | FZ41: Los Angeles | GA41: United States
A42: 40 | B42: Manulife Investment Management (Singapore) Pte. Ltd. | C42: 0.001307 | D42: 0.001307 | E42: 0.001307 | F42: 0.001419 | G42: 0.001382 | H42: 0.001307 | I42: 0.00112 | AB42: 0.175 | AC42: 0.175 | AD42: 0.175 | AE42: 0.19 | AF42: 0.185 | AG42: 0.175 | AH42: 0.15 | BA42: 0 | BB42: 0 | BC42: -0.015 | BD42: 0.005 | BE42: 0.01 | BF42: 0.025 | BG42: 0.15 | BZ42: 4.8548435 | CA42: 4.8548435 | CB42: 4.8548435 | CC42: 5.5335649 | CD42: 5.7007584 | CE42: 6.4314923 | CF42: 5.3860317 | CY42: 46112 | CZ42: 46112 | DA42: 46112 | DB42: 46081 | DC42: 46053 | DD42: 46022 | DE42: 45991 | DX42: Aggregate MFs | DY42: Aggregate MFs | DZ42: Aggregate MFs | EA42: Aggregate MFs | EB42: Aggregate MFs | EC42: Aggregate MFs | ED42: Aggregate MFs | EW42: Investment Managers | EX42: Investment Advisor | EY42: 932.45548 | FA42: Moderate | FB42: Moderate | FC42: Moderate | FD42: Moderate | FE42: Moderate | FF42: Moderate | FG42: Moderate | FZ42: Singapore | GA42: Singapore
A43: 41 | B43: UTI Asset Management Co. Ltd. | C43: 0.00116 | D43: 0.00116 | E43: 0.001117 | F43: 0.00119 | G43: 0.00119 | H43: 0.00119 | I43: 0.00119 | J43: 0.001115 | K43: 0.001072 | L43: 0.000883 | M43: 0.000883 | N43: 0.000884 | O43: 0.000884 | P43: 0.000862 | Q43: 0.000862 | R43: 0.000862 | S43: 0.000862 | T43: 0.000862 | U43: 0.000862 | V43: 0.000264 | W43: 0 | X43: 0 | Y43: 0 | Z43: 0 | AA43: 0 | AB43: 0.155359 | AC43: 0.155359 | AD43: 0.149551 | AE43: 0.159269 | AF43: 0.159269 | AG43: 0.159269 | AH43: 0.159269 | AI43: 0.149269 | AJ43: 0.143455 | AK43: 0.118257 | AL43: 0.118257 | AM43: 0.118257 | AN43: 0.118257 | AO43: 0.115294 | AP43: 0.115294 | AQ43: 0.115294 | AR43: 0.115294 | AS43: 0.115294 | AT43: 0.115294 | AU43: 0.035294 | AV43: 0 | AW43: 0 | AX43: 0 | AY43: 0 | AZ43: 0 | BA43: 0 | BB43: 0.005808 | BC43: -0.009718 | BD43: 0 | BE43: 0 | BF43: 0 | BG43: 0.01 | BH43: 0.005814 | BI43: 0.025198 | BJ43: 0 | BK43: 0 | BL43: 0 | BM43: 0.002963 | BN43: 0 | BO43: 0 | BP43: 0 | BQ43: 0 | BR43: 0 | BS43: 0.08 | BT43: 0.035294 | BU43: 0 | BV43: 0 | BW43: 0 | BX43: 0 | BY43: 0 | BZ43: 5.6068465 | CA43: 5.6068465 | CB43: 4.1488383 | CC43: 4.6385545 | CD43: 4.9078599 | CE43: 5.8533562 | CF43: 5.7188525 | CG43: 5.2755022 | CH43: 4.6719861 | CI43: 3.8524925 | CJ43: 3.6888705 | CK43: 3.6224511 | CL43: 3.5076452 | CM43: 3.3259421 | CN43: 3.2700066 | CO43: 2.7368628 | CP43: 2.902033 | CQ43: 3.5150412 | CR43: 3.3557387 | CS43: 0.94132728 | CT43: 0 | CU43: 0 | CV43: 0 | CW43: 0 | CX43: 0 | CY43: 46142 | CZ43: 46142 | DA43: 46112 | DB43: 46081 | DC43: 46053 | DD43: 46022 | DE43: 45991 | DF43: 45961 | DG43: 45930 | DH43: 45900 | DI43: 45869 | DJ43: 45838 | DK43: 45808 | DL43: 45777 | DM43: 45747 | DN43: 45716 | DO43: 45688 | DP43: 45657 | DQ43: 45626 | DR43: 45596 | DS43: 45138 | DT43: 45138 | DU43: 45138 | DV43: 45138 | DW43: 45138 | DX43: Aggregate MFs | DY43: Aggregate MFs | DZ43: Aggregate MFs | EA43: Aggregate MFs | EB43: Aggregate MFs | EC43: Aggregate MFs | ED43: Aggregate MFs | EE43: Aggregate MFs | EF43: Aggregate MFs | EG43: Aggregate MFs | EH43: Aggregate MFs | EI43: Aggregate MFs | EJ43: Aggregate MFs | EK43: Aggregate MFs | EL43: Aggregate MFs | EM43: Aggregate MFs | EN43: Aggregate MFs | EO43: Aggregate MFs | EP43: Aggregate MFs | EQ43: Aggregate MFs | ER43: Aggregate MFs | ES43: Aggregate MFs | ET43: Aggregate MFs | EU43: Aggregate MFs | EV43: Aggregate MFs | EW43: Investment Managers | EX43: Investment Advisor | EY43: 39439.372 | EZ43: Core Value | FA43: Low | FB43: Low | FC43: Low | FD43: Low | FE43: Low | FF43: Low | FG43: Low | FH43: Low | FI43: Low | FJ43: Low | FK43: Low | FL43: Low | FM43: Low | FN43: Low | FO43: Low | FP43: Low | FQ43: Low | FR43: Low | FS43: Low | FT43: Low | FU43: Low | FV43: Low | FW43: Low | FX43: Low | FY43: Low | FZ43: Mumbai | GA43: India
A44: 42 | B44: Samsung Asset Management Co., Ltd. | C44: 0.001124 | D44: 0.001124 | E44: 0.001106 | F44: 0.001106 | G44: 0.001106 | H44: 0.001106 | I44: 0.000144 | J44: 0.000144 | K44: 0.000144 | L44: 0.000144 | M44: 0.000144 | N44: 0.000145 | O44: 0.000463 | P44: 0.000463 | Q44: 0.000463 | R44: 0.000583 | S44: 0.000583 | T44: 0.000583 | U44: 0 | V44: 0 | W44: 0 | X44: 0.001017 | Y44: 0.001017 | Z44: 0.001017 | AA44: 0.000643 | AB44: 0.150536 | AC44: 0.150536 | AD44: 0.148128 | AE44: 0.148128 | AF44: 0.148128 | AG44: 0.148128 | AH44: 0.01934 | AI44: 0.01934 | AJ44: 0.01934 | AK44: 0.01934 | AL44: 0.01934 | AM44: 0.01934 | AN44: 0.062 | AO44: 0.062 | AP44: 0.062 | AQ44: 0.078 | AR44: 0.078 | AS44: 0.078 | AT44: 0 | AU44: 0 | AV44: 0 | AW44: 0.136 | AX44: 0.136 | AY44: 0.136 | AZ44: 0.085979 | BA44: 0 | BB44: 0.002408 | BC44: 0 | BD44: 0 | BE44: 0 | BF44: 0.128788 | BG44: 0 | BH44: 0 | BI44: 0 | BJ44: 0 | BK44: 0 | BL44: -0.04266 | BM44: 0 | BN44: 0 | BO44: -0.016 | BP44: 0 | BQ44: 0 | BR44: 0.078 | BS44: 0 | BT44: 0 | BU44: -0.136 | BV44: 0 | BW44: 0 | BX44: 0.050021 | BY44: 0 | BZ44: 5.4327863 | CA44: 5.4327863 | CB44: 5.4439091 | CC44: 5.4439091 | CD44: 5.4439091 | CE44: 5.4439091 | CF44: 0.62985752 | CG44: 0.62985752 | CH44: 0.62985752 | CI44: 0.59242331 | CJ44: 0.59242331 | CK44: 0.59242331 | CL44: 1.7584645 | CM44: 1.7584645 | CN44: 1.7584645 | CO44: 2.3780354 | CP44: 2.3780354 | CQ44: 2.3780354 | CR44: 0 | CS44: 0 | CT44: 0 | CU44: 2.9147286 | CV44: 2.9147286 | CW44: 2.9147286 | CX44: 1.1020974 | CY44: 46142 | CZ44: 46142 | DA44: 46022 | DB44: 46022 | DC44: 46022 | DD44: 46022 | DE44: 45930 | DF44: 45930 | DG44: 45930 | DH44: 45838 | DI44: 45838 | DJ44: 45838 | DK44: 45747 | DL44: 45747 | DM44: 45747 | DN44: 45657 | DO44: 45657 | DP44: 45657 | DQ44: 45565 | DR44: 45565 | DS44: 45565 | DT44: 45473 | DU44: 45473 | DV44: 45473 | DW44: 44834 | DX44: Aggregate MFs | DY44: Aggregate MFs | DZ44: Aggregate MFs | EA44: Aggregate MFs | EB44: Aggregate MFs | EC44: Aggregate MFs | ED44: Aggregate MFs | EE44: Aggregate MFs | EF44: Aggregate MFs | EG44: Aggregate MFs | EH44: Aggregate MFs | EI44: Aggregate MFs | EJ44: Aggregate MFs | EK44: Aggregate MFs | EL44: Aggregate MFs | EM44: Aggregate MFs | EN44: Aggregate MFs | EO44: Aggregate MFs | EP44: Aggregate MFs | EQ44: Aggregate MFs | ER44: Aggregate MFs | ES44: Aggregate MFs | ET44: Aggregate MFs | EU44: Aggregate MFs | EV44: Aggregate MFs | EW44: Investment Managers | EX44: Investment Advisor | EY44: 83986.002 | EZ44: Core Value | FA44: Moderate | FB44: Moderate | FC44: Moderate | FD44: Moderate | FE44: Moderate | FF44: Moderate | FG44: Moderate | FH44: Moderate | FI44: Moderate | FJ44: Moderate | FK44: Moderate | FL44: Moderate | FM44: Low | FN44: Low | FO44: Moderate | FP44: Moderate | FQ44: Moderate | FR44: Moderate | FS44: Moderate | FT44: Moderate | FU44: Moderate | FV44: Moderate | FW44: Low | FX44: Low | FY44: Low | FZ44: Seoul | GA44: South Korea
A45: 43 | B45: Trust Asset Management Private Limited | C45: 0.001114 | D45: 0.001114 | E45: 0.00106 | F45: 0.000861 | G45: 0.000805 | H45: 0.000935 | I45: 0.001032 | J45: 0.001033 | K45: 0.001033 | L45: 0.001244 | M45: 0.001101 | N45: 0.001025 | O45: 0.001025 | P45: 0.000975 | Q45: 0.000975 | R45: 0.000795 | S45: 0.000741 | T45: 0.000699 | U45: 0.000699 | V45: 0.000368 | W45: 0.000368 | AB45: 0.14917 | AC45: 0.14917 | AD45: 0.141894 | AE45: 0.115345 | AF45: 0.107756 | AG45: 0.125146 | AH45: 0.138232 | AI45: 0.138232 | AJ45: 0.138232 | AK45: 0.166558 | AL45: 0.14737 | AM45: 0.137222 | AN45: 0.137222 | AO45: 0.130444 | AP45: 0.130444 | AQ45: 0.106405 | AR45: 0.099123 | AS45: 0.093562 | AT45: 0.093562 | AU45: 0.049179 | AV45: 0.049179 | BA45: 0 | BB45: 0.007276 | BC45: 0.026549 | BD45: 0.007589 | BE45: -0.01739 | BF45: -0.013086 | BG45: 0 | BH45: 0 | BI45: -0.028326 | BJ45: 0.019188 | BK45: 0.010148 | BL45: 0 | BM45: 0.006778 | BN45: 0 | BO45: 0.024039 | BP45: 0.007282 | BQ45: 0.005561 | BR45: 0 | BS45: 0.044383 | BT45: 0 | BU45: 0.049179 | BZ45: 5.3834879 | CA45: 5.3834879 | CB45: 3.9364181 | CC45: 3.3593108 | CD45: 3.3204915 | CE45: 4.5992888 | CF45: 4.9634795 | CG45: 4.8854298 | CH45: 4.5018855 | CI45: 5.4260081 | CJ45: 4.597012 | CK45: 4.2033874 | CL45: 4.0701699 | CM45: 3.7629816 | CN45: 3.6996959 | CO45: 2.5258546 | CP45: 2.4949973 | CQ45: 2.852484 | CR45: 2.7232087 | CS45: 1.3116545 | CT45: 1.201041 | CY45: 46142 | CZ45: 46142 | DA45: 46112 | DB45: 46081 | DC45: 46053 | DD45: 46022 | DE45: 45991 | DF45: 45961 | DG45: 45930 | DH45: 45900 | DI45: 45869 | DJ45: 45838 | DK45: 45808 | DL45: 45777 | DM45: 45747 | DN45: 45716 | DO45: 45688 | DP45: 45657 | DQ45: 45626 | DR45: 45596 | DS45: 45565 | DX45: Aggregate MFs | DY45: Aggregate MFs | DZ45: Aggregate MFs | EA45: Aggregate MFs | EB45: Aggregate MFs | EC45: Aggregate MFs | ED45: Aggregate MFs | EE45: Aggregate MFs | EF45: Aggregate MFs | EG45: Aggregate MFs | EH45: Aggregate MFs | EI45: Aggregate MFs | EJ45: Aggregate MFs | EK45: Aggregate MFs | EL45: Aggregate MFs | EM45: Aggregate MFs | EN45: Aggregate MFs | EO45: Aggregate MFs | EP45: Aggregate MFs | EQ45: Aggregate MFs | ER45: Aggregate MFs | EW45: Investment Managers | EX45: Investment Advisor | EY45: 266.03077 | FA45: High | FB45: High | FC45: High | FD45: High | FE45: High | FF45: High | FG45: High | FH45: High | FI45: High | FJ45: High | FK45: High | FL45: High | FM45: Low | FN45: High | FO45: High | FP45: High | FQ45: High | FR45: High | FS45: High | FT45: High | FU45: High | FZ45: Mumbai | GA45: India
A46: 44 | B46: Bank of India Investment Managers Private Limited | C46: 0.001039 | D46: 0.00104 | E46: 0.000904 | F46: 0.00069 | G46: 0.00069 | H46: 0.002057 | I46: 0.002057 | J46: 0.002233 | K46: 0.002205 | L46: 0.002039 | M46: 0.002039 | N46: 0.00204 | O46: 0.00242 | P46: 0.002817 | Q46: 0.002817 | R46: 0.002818 | S46: 0.002623 | T46: 0.002814 | U46: 0.002466 | V46: 0.002123 | W46: 0.002231 | X46: 0.002314 | Y46: 0.002523 | Z46: 0.002524 | AA46: 0.002476 | AB46: 0.139194 | AC46: 0.139194 | AD46: 0.121057 | AE46: 0.092384 | AF46: 0.092384 | AG46: 0.275384 | AH46: 0.275384 | AI46: 0.298998 | AJ46: 0.295198 | AK46: 0.273 | AL46: 0.273 | AM46: 0.273 | AN46: 0.323893 | AO46: 0.377 | AP46: 0.377 | AQ46: 0.377 | AR46: 0.351 | AS46: 0.376465 | AT46: 0.329974 | AU46: 0.283974 | AV46: 0.298474 | AW46: 0.309474 | AX46: 0.337474 | AY46: 0.337474 | AZ46: 0.331045 | BA46: 0 | BB46: 0.018137 | BC46: 0.028673 | BD46: 0 | BE46: -0.183 | BF46: 0 | BG46: -0.023614 | BH46: 0.0038 | BI46: 0.022198 | BJ46: 0 | BK46: 0 | BL46: -0.050893 | BM46: -0.053107 | BN46: 0 | BO46: 0 | BP46: 0.026 | BQ46: -0.025465 | BR46: 0.046491 | BS46: 0.046 | BT46: -0.0145 | BU46: -0.011 | BV46: -0.028 | BW46: 0 | BX46: 0.006429 | BY46: 0.022 | BZ46: 5.0234579 | CA46: 5.0234579 | CB46: 3.3583588 | CC46: 2.690594 | CD46: 2.8468047 | CE46: 10.120743 | CF46: 9.8881796 | CG46: 10.567262 | CH46: 9.6138925 | CI46: 8.8935999 | CJ46: 8.5158735 | CK46: 8.3625421 | CL46: 9.6070568 | CM46: 10.875502 | CN46: 10.692599 | CO46: 8.9492712 | CP46: 8.8349229 | CQ46: 11.477527 | CR46: 9.6041991 | CS46: 7.5738786 | CT46: 7.28928 | CU46: 7.166275 | CV46: 6.9491278 | CW46: 7.2326846 | CX46: 6.2559029 | CY46: 46142 | CZ46: 46142 | DA46: 46112 | DB46: 46081 | DC46: 46053 | DD46: 46022 | DE46: 45991 | DF46: 45961 | DG46: 45930 | DH46: 45900 | DI46: 45869 | DJ46: 45838 | DK46: 45808 | DL46: 45777 | DM46: 45747 | DN46: 45716 | DO46: 45688 | DP46: 45657 | DQ46: 45626 | DR46: 45596 | DS46: 45565 | DT46: 45535 | DU46: 45504 | DV46: 45473 | DW46: 45443 | DX46: Aggregate MFs | DY46: Aggregate MFs | DZ46: Aggregate MFs | EA46: Aggregate MFs | EB46: Aggregate MFs | EC46: Aggregate MFs | ED46: Aggregate MFs | EE46: Aggregate MFs | EF46: Aggregate MFs | EG46: Aggregate MFs | EH46: Aggregate MFs | EI46: Aggregate MFs | EJ46: Aggregate MFs | EK46: Aggregate MFs | EL46: Aggregate MFs | EM46: Aggregate MFs | EN46: Aggregate MFs | EO46: Aggregate MFs | EP46: Aggregate MFs | EQ46: Aggregate MFs | ER46: Aggregate MFs | ES46: Aggregate MFs | ET46: Aggregate MFs | EU46: Aggregate MFs | EV46: Aggregate MFs | EW46: Investment Managers | EX46: Investment Advisor | EY46: 950.11342 | FA46: Moderate | FB46: Moderate | FC46: Moderate | FD46: Moderate | FE46: Moderate | FF46: Moderate | FG46: Moderate | FH46: Moderate | FI46: Moderate | FJ46: Moderate | FK46: Moderate | FL46: Moderate | FM46: Moderate | FN46: Moderate | FO46: Moderate | FP46: Moderate | FQ46: Moderate | FR46: High | FS46: High | FT46: High | FU46: High | FV46: Moderate | FW46: Moderate | FX46: High | FY46: High | FZ46: Mumbai | GA46: India
A47: 45 | B47: Mirae Asset Global Investments (India) Pvt. Ltd. | C47: 0.001026 | D47: 0.001026 | E47: 0.001009 | F47: 0.000698 | G47: 0.000672 | H47: 0.000627 | I47: 3e-06 | J47: 0 | K47: 0 | L47: 0 | M47: 0 | N47: 0 | O47: 0.000677 | P47: 0.000677 | Q47: 0.000661 | R47: 0.000616 | S47: 0.000558 | T47: 0.000473 | U47: 0 | V47: 0 | W47: 0 | X47: 0 | Y47: 0 | Z47: 0 | AA47: 0.000146 | AB47: 0.137402 | AC47: 0.137402 | AD47: 0.135127 | AE47: 0.093411 | AF47: 0.089994 | AG47: 0.083966 | AH47: 0.00035 | AI47: 0 | AJ47: 0 | AK47: 0 | AL47: 0 | AM47: 0 | AN47: 0.090627 | AO47: 0.09058 | AP47: 0.088404 | AQ47: 0.082386 | AR47: 0.074598 | AS47: 0.063343 | AT47: 0 | AU47: 0 | AV47: 0 | AW47: 0 | AX47: 0 | AY47: 0 | AZ47: 0.019487 | BA47: 0 | BB47: 0.002275 | BC47: 0.041716 | BD47: 0.003417 | BE47: 0.006028 | BF47: 0.083616 | BG47: 0.00035 | BH47: 0 | BI47: 0 | BJ47: 0 | BK47: 0 | BL47: -0.090627 | BM47: 4.7e-05 | BN47: 0.002176 | BO47: 0.006018 | BP47: 0.007788 | BQ47: 0.011255 | BR47: 0.063343 | BS47: 0 | BT47: 0 | BU47: 0 | BV47: 0 | BW47: 0 | BX47: -0.019487 | BY47: 0.003539 | BZ47: 4.9587853 | CA47: 4.9587853 | CB47: 3.7486882 | CC47: 2.7205044 | CD47: 2.773157 | CE47: 3.0858667 | CF47: 0.01256741 | CG47: 0 | CH47: 0 | CI47: 0 | CJ47: 0 | CK47: 0 | CL47: 2.6881061 | CM47: 2.6130053 | CN47: 2.5073435 | CO47: 1.9556887 | CP47: 1.8776854 | CQ47: 1.9311782 | CR47: 0 | CS47: 0 | CT47: 0 | CU47: 0 | CV47: 0 | CW47: 0 | CX47: 0.36825441 | CY47: 46142 | CZ47: 46142 | DA47: 46112 | DB47: 46081 | DC47: 46053 | DD47: 46022 | DE47: 45991 | DF47: 45838 | DG47: 45838 | DH47: 45838 | DI47: 45838 | DJ47: 45838 | DK47: 45808 | DL47: 45777 | DM47: 45747 | DN47: 45716 | DO47: 45688 | DP47: 45657 | DQ47: 45473 | DR47: 45473 | DS47: 45473 | DT47: 45473 | DU47: 45473 | DV47: 45473 | DW47: 45443 | DX47: Aggregate MFs | DY47: Aggregate MFs | DZ47: Aggregate MFs | EA47: Aggregate MFs | EB47: Aggregate MFs | EC47: Aggregate MFs | ED47: Aggregate MFs | EE47: Aggregate MFs | EF47: Aggregate MFs | EG47: Aggregate MFs | EH47: Aggregate MFs | EI47: Aggregate MFs | EJ47: Aggregate MFs | EK47: Aggregate MFs | EL47: Aggregate MFs | EM47: Aggregate MFs | EN47: Aggregate MFs | EO47: Aggregate MFs | EP47: Aggregate MFs | EQ47: Aggregate MFs | ER47: Aggregate MFs | ES47: Aggregate MFs | ET47: Aggregate MFs | EU47: Aggregate MFs | EV47: Aggregate MFs | EW47: Investment Managers | EX47: Investment Advisor | EY47: 20882.036 | FA47: Low | FB47: Low | FC47: Low | FD47: Low | FE47: Low | FF47: Low | FG47: Low | FH47: Low | FI47: Low | FJ47: Low | FK47: Low | FL47: Moderate | FM47: Moderate | FN47: Moderate | FO47: Moderate | FP47: Moderate | FQ47: Moderate | FR47: Moderate | FS47: Moderate | FT47: Moderate | FU47: Moderate | FV47: Moderate | FW47: Moderate | FX47: Moderate | FY47: Low | FZ47: Mumbai | GA47: India
A48: 46 | B48: LIC Mutual Fund Asset Management Company Ltd. | C48: 0.000946 | D48: 0.000946 | E48: 0.000339 | F48: 0.000237 | G48: 0.000237 | H48: 0.000166 | I48: 0.00011 | J48: 1.2e-05 | K48: 4e-06 | L48: 3e-06 | M48: 3e-06 | N48: 0 | O48: 0 | P48: 0 | Q48: 0 | R48: 0 | S48: 0 | T48: 0 | U48: 3e-06 | V48: 3e-06 | W48: 4e-06 | X48: 4e-06 | AB48: 0.126666 | AC48: 0.126666 | AD48: 0.045433 | AE48: 0.031752 | AF48: 0.031769 | AG48: 0.022238 | AH48: 0.01476 | AI48: 0.001567 | AJ48: 0.000566 | AK48: 0.000408 | AL48: 0.000408 | AM48: 0 | AN48: 0 | AO48: 0 | AP48: 0 | AQ48: 0 | AR48: 0 | AS48: 0 | AT48: 0.000431 | AU48: 0.000431 | AV48: 0.000574 | AW48: 0.000574 | BA48: 0 | BB48: 0.081233 | BC48: 0.013681 | BD48: -1.7e-05 | BE48: 0.009531 | BF48: 0.007478 | BG48: 0.013193 | BH48: 0.001001 | BI48: 0.000158 | BJ48: 0 | BK48: 0.000408 | BL48: 0 | BM48: 0 | BN48: 0 | BO48: 0 | BP48: 0 | BQ48: 0 | BR48: -0.000431 | BS48: 0 | BT48: -0.000143 | BU48: 0 | BV48: 0.000574 | BZ48: 4.5713272 | CA48: 4.5713272 | CB48: 1.2604006 | CC48: 0.92474607 | CD48: 0.97895888 | CE48: 0.81727729 | CF48: 0.52998552 | CG48: 0.0553813 | CH48: 0.01843327 | CI48: 0.01329153 | CJ48: 0.01272702 | CK48: 0 | CL48: 0 | CM48: 0 | CN48: 0 | CO48: 0 | CP48: 0 | CQ48: 0 | CR48: 0.01149521 | CS48: 0.01149521 | CT48: 0.01401813 | CU48: 0.01329172 | CY48: 46142 | CZ48: 46142 | DA48: 46112 | DB48: 46081 | DC48: 46053 | DD48: 46022 | DE48: 45991 | DF48: 45961 | DG48: 45930 | DH48: 45900 | DI48: 45869 | DJ48: 45657 | DK48: 45657 | DL48: 45657 | DM48: 45657 | DN48: 45657 | DO48: 45657 | DP48: 45657 | DQ48: 45596 | DR48: 45596 | DS48: 45565 | DT48: 45535 | DX48: Aggregate MFs | DY48: Aggregate MFs | DZ48: Aggregate MFs | EA48: Aggregate MFs | EB48: Aggregate MFs | EC48: Aggregate MFs | ED48: Aggregate MFs | EE48: Aggregate MFs | EF48: Aggregate MFs | EG48: Aggregate MFs | EH48: Aggregate MFs | EI48: Aggregate MFs | EJ48: Aggregate MFs | EK48: Aggregate MFs | EL48: Aggregate MFs | EM48: Aggregate MFs | EN48: Aggregate MFs | EO48: Aggregate MFs | EP48: Aggregate MFs | EQ48: Aggregate MFs | ER48: Aggregate MFs | ES48: Aggregate MFs | EW48: Investment Managers | EX48: Investment Advisor | EY48: 10996.457 | EZ48: Core Value | FA48: Low | FB48: Low | FC48: Low | FD48: Low | FE48: Low | FF48: Low | FG48: Low | FH48: Low | FI48: Low | FJ48: Low | FK48: Low | FL48: Low | FM48: Low | FN48: Low | FO48: Low | FP48: Moderate | FQ48: Moderate | FR48: Low | FS48: Low | FT48: Low | FU48: Moderate | FV48: Moderate | FZ48: Mumbai | GA48: India
A49: 47 | B49: Invesco Hong Kong Limited | C49: 0.000896 | D49: 0.000896 | E49: 0.000896 | F49: 0.001718 | G49: 0.001867 | H49: 0.001568 | AB49: 0.12 | AC49: 0.12 | AD49: 0.12 | AE49: 0.23 | AF49: 0.25 | AG49: 0.21 | BA49: 0 | BB49: 0 | BC49: -0.11 | BD49: -0.02 | BE49: 0.04 | BF49: 0.21 | BZ49: 3.3290355 | CA49: 3.3290355 | CB49: 3.3290355 | CC49: 6.6985259 | CD49: 7.7037275 | CE49: 7.7177907 | CY49: 46112 | CZ49: 46112 | DA49: 46112 | DB49: 46081 | DC49: 46053 | DD49: 46022 | DX49: Aggregate MFs | DY49: Aggregate MFs | DZ49: Aggregate MFs | EA49: Aggregate MFs | EB49: Aggregate MFs | EC49: Aggregate MFs | EW49: Investment Managers | EX49: Investment Advisor | EY49: 4045.2246 | EZ49: GARP | FA49: Moderate | FB49: Moderate | FC49: Moderate | FD49: Moderate | FE49: Moderate | FF49: Moderate | FZ49: Central (Hong Kong) | GA49: Hong Kong
A50: 48 | B50: First Sentier Investors (Singapore) | C50: 0.000827 | D50: 0.000827 | E50: 0.000827 | F50: 0.000815 | G50: 0.000815 | H50: 0.001545 | I50: 0.001947 | J50: 0.001947 | K50: 0.001838 | L50: 0.001838 | M50: 0.002142 | N50: 0.002143 | O50: 0.002143 | P50: 0.00269 | Q50: 0.00269 | R50: 0.00269 | S50: 0.00269 | T50: 0.003178 | U50: 0.003178 | V50: 0.003178 | W50: 0.003528 | X50: 0.003725 | Y50: 0.003725 | Z50: 0.00361 | AA50: 0.00361 | AB50: 0.110788 | AC50: 0.110788 | AD50: 0.110788 | AE50: 0.109126 | AF50: 0.109126 | AG50: 0.20692 | AH50: 0.260685 | AI50: 0.260685 | AJ50: 0.246024 | AK50: 0.246024 | AL50: 0.286746 | AM50: 0.286746 | AN50: 0.286746 | AO50: 0.359992 | AP50: 0.359992 | AQ50: 0.359992 | AR50: 0.359992 | AS50: 0.425209 | AT50: 0.425209 | AU50: 0.425209 | AV50: 0.471974 | AW50: 0.498313 | AX50: 0.498313 | AY50: 0.482738 | AZ50: 0.482738 | BA50: 0 | BB50: 0 | BC50: 0.001662 | BD50: 0 | BE50: -0.097794 | BF50: -0.053765 | BG50: 0 | BH50: 0.014661 | BI50: 0 | BJ50: -0.040722 | BK50: 0 | BL50: 0 | BM50: -0.073246 | BN50: 0 | BO50: 0 | BP50: 0 | BQ50: -0.065217 | BR50: 0 | BS50: 0 | BT50: -0.046765 | BU50: -0.026339 | BV50: 0 | BW50: 0.015575 | BX50: 0 | BY50: 0 | BZ50: 3.0734766 | CA50: 3.0734766 | CB50: 3.0734766 | CC50: 3.1781884 | CD50: 3.3627079 | CE50: 7.6045965 | CF50: 9.3603844 | CG50: 9.2131943 | CH50: 8.012413 | CI50: 8.0147949 | CJ50: 8.9446617 | CK50: 8.7836099 | CL50: 8.505232 | CM50: 10.210212 | CN50: 10.210212 | CO50: 8.5455332 | CP50: 9.061258 | CQ50: 12.963616 | CR50: 12.376102 | CS50: 11.340761 | CT50: 11.526467 | CU50: 11.539089 | CV50: 10.261059 | CW50: 9.1225122 | CX50: 9.1225122 | CY50: 46112 | CZ50: 46112 | DA50: 46112 | DB50: 46081 | DC50: 46053 | DD50: 46022 | DE50: 45991 | DF50: 45961 | DG50: 45930 | DH50: 45900 | DI50: 45869 | DJ50: 45838 | DK50: 45808 | DL50: 45747 | DM50: 45747 | DN50: 45716 | DO50: 45688 | DP50: 45657 | DQ50: 45626 | DR50: 45596 | DS50: 45565 | DT50: 45535 | DU50: 45504 | DV50: 45443 | DW50: 45443 | DX50: Aggregate MFs | DY50: Aggregate MFs | DZ50: Aggregate MFs | EA50: Aggregate MFs | EB50: Aggregate MFs | EC50: Aggregate MFs | ED50: Aggregate MFs | EE50: Aggregate MFs | EF50: Aggregate MFs | EG50: Aggregate MFs | EH50: Aggregate MFs | EI50: Aggregate MFs | EJ50: Aggregate MFs | EK50: Aggregate MFs | EL50: Aggregate MFs | EM50: Aggregate MFs | EN50: Aggregate MFs | EO50: Aggregate MFs | EP50: Aggregate MFs | EQ50: Aggregate MFs | ER50: Aggregate MFs | ES50: Aggregate MFs | ET50: Aggregate MFs | EU50: Aggregate MFs | EV50: Aggregate MFs | EW50: Investment Managers | EX50: Investment Advisor | EY50: 9335.1541 | EZ50: GARP | FA50: Low | FB50: Low | FC50: Low | FD50: Low | FE50: Low | FF50: Low | FG50: Low | FH50: Low | FI50: Low | FJ50: Low | FK50: Low | FL50: Low | FM50: Low | FN50: Low | FO50: Low | FP50: Low | FQ50: Low | FR50: Low | FS50: Low | FT50: Low | FU50: Low | FV50: Low | FW50: Low | FX50: Low | FY50: Low | FZ50: Singapore | GA50: Singapore
A51: 49 | B51: Mellon Investments Corporation | C51: 0.000819 | D51: 0.000819 | E51: 0.000833 | F51: 0.000906 | G51: 0.000911 | H51: 0.000215 | I51: 0.000951 | J51: 0.000242 | K51: 0.000993 | L51: 0.001021 | M51: 0.000247 | N51: 0.000253 | O51: 0.000253 | P51: 0.001012 | Q51: 0.000148 | R51: 0.000145 | S51: 0.000148 | T51: 0.000149 | U51: 0.000153 | V51: 0.000165 | W51: 0.00104 | X51: 0.00104 | Y51: 0.001033 | Z51: 0.000979 | AA51: 0.000916 | AB51: 0.109729 | AC51: 0.109729 | AD51: 0.111596 | AE51: 0.121318 | AF51: 0.121984 | AG51: 0.028854 | AH51: 0.127267 | AI51: 0.032439 | AJ51: 0.132982 | AK51: 0.136642 | AL51: 0.033003 | AM51: 0.033861 | AN51: 0.033861 | AO51: 0.13537 | AP51: 0.01987 | AQ51: 0.01942 | AR51: 0.01977 | AS51: 0.019915 | AT51: 0.020475 | AU51: 0.02214 | AV51: 0.139121 | AW51: 0.139121 | AX51: 0.138143 | AY51: 0.130844 | AZ51: 0.122479 | BA51: 0 | BB51: -0.001867 | BC51: -0.009722 | BD51: -0.000666 | BE51: 0.09313 | BF51: -0.098413 | BG51: 0.094828 | BH51: -0.100543 | BI51: -0.00366 | BJ51: 0.103639 | BK51: -0.000858 | BL51: 0 | BM51: -0.101509 | BN51: 0.1155 | BO51: 0.00045 | BP51: -0.00035 | BQ51: -0.000145 | BR51: -0.00056 | BS51: -0.001665 | BT51: -0.116981 | BU51: 0 | BV51: 0.000978 | BW51: 0.007299 | BX51: 0.008365 | BY51: 0.004721 | BZ51: 3.9600774 | CA51: 3.9600774 | CB51: 3.0958921 | CC51: 3.5332686 | CD51: 3.758926 | CE51: 1.0604244 | CF51: 4.5697606 | CG51: 1.1464672 | CH51: 4.3309055 | CI51: 4.4514259 | CJ51: 1.0294849 | CK51: 1.0372309 | CL51: 1.0043581 | CM51: 3.9050843 | CN51: 0.56355951 | CO51: 0.46099429 | CP51: 0.49762514 | CQ51: 0.60716122 | CR51: 0.59594385 | CS51: 0.59049657 | CT51: 3.3975888 | CU51: 3.2215286 | CV51: 2.8445847 | CW51: 2.8042261 | CX51: 2.3145395 | CY51: 46142 | CZ51: 46142 | DA51: 46112 | DB51: 46081 | DC51: 46053 | DD51: 46022 | DE51: 45991 | DF51: 45961 | DG51: 45930 | DH51: 45900 | DI51: 45869 | DJ51: 45838 | DK51: 45808 | DL51: 45777 | DM51: 45747 | DN51: 45716 | DO51: 45688 | DP51: 45657 | DQ51: 45626 | DR51: 45596 | DS51: 45565 | DT51: 45535 | DU51: 45504 | DV51: 45473 | DW51: 45443 | DX51: Aggregate MFs | DY51: Aggregate MFs | DZ51: Aggregate MFs | EA51: Aggregate MFs | EB51: Aggregate MFs | EC51: Aggregate MFs | ED51: Aggregate MFs | EE51: Aggregate MFs | EF51: Aggregate MFs | EG51: Aggregate MFs | EH51: Aggregate MFs | EI51: Aggregate MFs | EJ51: Aggregate MFs | EK51: Aggregate MFs | EL51: Aggregate MFs | EM51: Aggregate MFs | EN51: Aggregate MFs | EO51: Aggregate MFs | EP51: Aggregate MFs | EQ51: Aggregate MFs | ER51: Aggregate MFs | ES51: Aggregate MFs | ET51: Aggregate MFs | EU51: Aggregate MFs | EV51: Aggregate MFs | EW51: Investment Managers | EX51: Investment Advisor/Hedge Fund | EY51: 328992.26 | EZ51: GARP | FA51: Low | FB51: Low | FC51: Low | FD51: Low | FE51: Low | FF51: Low | FG51: Low | FH51: Low | FI51: Low | FJ51: Low | FK51: Low | FL51: Low | FM51: Low | FN51: Low | FO51: Low | FP51: Low | FQ51: Low | FR51: Low | FS51: Low | FT51: Low | FU51: Low | FV51: Low | FW51: Low | FX51: Low | FY51: Low | FZ51: Boston | GA51: United States
A52: 50 | B52: California Public Employees' Retirement System | C52: 0.000767 | D52: 0.000767 | E52: 0.000767 | F52: 0.000767 | G52: 0.000767 | H52: 0.000767 | I52: 0.000767 | J52: 0.000767 | K52: 0.000767 | L52: 0.000767 | M52: 0.000767 | N52: 0.000767 | O52: 0.000893 | P52: 0.000893 | Q52: 0.000893 | R52: 0.000893 | S52: 0.000893 | T52: 0.000893 | U52: 0.000893 | V52: 0.000893 | W52: 0.000893 | X52: 0.000893 | Y52: 0.000893 | Z52: 0.000894 | AA52: 0.001079 | AB52: 0.102697 | AC52: 0.102697 | AD52: 0.102697 | AE52: 0.102697 | AF52: 0.102697 | AG52: 0.102697 | AH52: 0.102697 | AI52: 0.102697 | AJ52: 0.102697 | AK52: 0.102697 | AL52: 0.102697 | AM52: 0.102697 | AN52: 0.1195 | AO52: 0.1195 | AP52: 0.1195 | AQ52: 0.1195 | AR52: 0.1195 | AS52: 0.1195 | AT52: 0.1195 | AU52: 0.1195 | AV52: 0.1195 | AW52: 0.1195 | AX52: 0.1195 | AY52: 0.1195 | AZ52: 0.144241 | BA52: 0 | BB52: 0 | BC52: 0 | BD52: 0 | BE52: 0 | BF52: 0 | BG52: 0 | BH52: 0 | BI52: 0 | BJ52: 0 | BK52: 0 | BL52: -0.016803 | BM52: 0 | BN52: 0 | BO52: 0 | BP52: 0 | BQ52: 0 | BR52: 0 | BS52: 0 | BT52: 0 | BU52: 0 | BV52: 0 | BW52: 0 | BX52: -0.024741 | BY52: 0 | BZ52: 3.1458168 | CA52: 3.1458168 | CB52: 3.1458168 | CC52: 3.1458168 | CD52: 3.1458168 | CE52: 3.1458168 | CF52: 3.1458168 | CG52: 3.1458168 | CH52: 3.1458168 | CI52: 3.1458168 | CJ52: 3.1458168 | CK52: 3.1458168 | CL52: 2.5611034 | CM52: 2.5611034 | CN52: 2.5611034 | CO52: 2.5611034 | CP52: 2.5611034 | CQ52: 2.5611034 | CR52: 2.5611034 | CS52: 2.5611034 | CT52: 2.5611034 | CU52: 2.5611034 | CV52: 2.5611034 | CW52: 2.5611034 | CX52: 2.1236149 | CY52: 45838 | CZ52: 45838 | DA52: 45838 | DB52: 45838 | DC52: 45838 | DD52: 45838 | DE52: 45838 | DF52: 45838 | DG52: 45838 | DH52: 45838 | DI52: 45838 | DJ52: 45838 | DK52: 45473 | DL52: 45473 | DM52: 45473 | DN52: 45473 | DO52: 45473 | DP52: 45473 | DQ52: 45473 | DR52: 45473 | DS52: 45473 | DT52: 45473 | DU52: 45473 | DV52: 45473 | DW52: 45107 | DX52: Shareholder Report | DY52: Shareholder Report | DZ52: Shareholder Report | EA52: Shareholder Report | EB52: Shareholder Report | EC52: Shareholder Report | ED52: Shareholder Report | EE52: Shareholder Report | EF52: Shareholder Report | EG52: Shareholder Report | EH52: Shareholder Report | EI52: Shareholder Report | EJ52: Shareholder Report | EK52: Shareholder Report | EL52: Shareholder Report | EM52: Shareholder Report | EN52: Shareholder Report | EO52: Shareholder Report | EP52: Shareholder Report | EQ52: Shareholder Report | ER52: Shareholder Report | ES52: Shareholder Report | ET52: Shareholder Report | EU52: Shareholder Report | EV52: Shareholder Report | EW52: Investment Managers | EX52: Pension Fund | EY52: 248443.4 | EZ52: Index | FA52: Low | FB52: Low | FC52: Low | FD52: Low | FE52: Low | FF52: Low | FG52: Low | FH52: Low | FI52: Low | FJ52: Low | FK52: Low | FL52: Low | FM52: Low | FN52: Low | FO52: Low | FP52: Low | FQ52: Low | FR52: Low | FS52: Low | FT52: Low | FU52: Low | FV52: Low | FW52: Low | FX52: Low | FY52: Low | FZ52: Sacramento | GA52: United States
A53: 51 | B53: Abhishek Fiscal Services Pvt. Ltd. | C53: 0.00074 | D53: 0.00074 | E53: 0.00074 | F53: 0.00074 | G53: 0.00074 | H53: 0.00074 | I53: 0.00074 | J53: 0.00074 | K53: 0.00074 | L53: 0.00074 | M53: 0.00074 | N53: 0.00074 | O53: 0.00074 | P53: 0.00074 | Q53: 0.00074 | R53: 0.00074 | S53: 0.00074 | T53: 0.00074 | U53: 0.00074 | V53: 0.00074 | W53: 0.00074 | X53: 0.00074 | Y53: 0.00074 | Z53: 0.000741 | AA53: 0.000741 | AB53: 0.09905 | AC53: 0.09905 | AD53: 0.09905 | AE53: 0.09905 | AF53: 0.09905 | AG53: 0.09905 | AH53: 0.09905 | AI53: 0.09905 | AJ53: 0.09905 | AK53: 0.09905 | AL53: 0.09905 | AM53: 0.09905 | AN53: 0.09905 | AO53: 0.09905 | AP53: 0.09905 | AQ53: 0.09905 | AR53: 0.09905 | AS53: 0.09905 | AT53: 0.09905 | AU53: 0.09905 | AV53: 0.09905 | AW53: 0.09905 | AX53: 0.09905 | AY53: 0.09905 | AZ53: 0.09905 | BA53: 0 | BB53: 0 | BC53: 0 | BD53: 0 | BE53: 0 | BF53: 0 | BG53: 0 | BH53: 0 | BI53: 0 | BJ53: 0 | BK53: 0 | BL53: 0 | BM53: 0 | BN53: 0 | BO53: 0 | BP53: 0 | BQ53: 0 | BR53: 0 | BS53: 0 | BT53: 0 | BU53: 0 | BV53: 0 | BW53: 0 | BX53: 0 | BY53: 0 | BZ53: 3.6402246 | CA53: 3.6402246 | CB53: 3.6402246 | CC53: 3.6402246 | CD53: 3.6402246 | CE53: 3.6402246 | CF53: 3.2258215 | CG53: 3.2258215 | CH53: 3.2258215 | CI53: 3.0341018 | CJ53: 3.0341018 | CK53: 3.0341018 | CL53: 2.8092889 | CM53: 2.8092889 | CN53: 2.8092889 | CO53: 3.0198001 | CP53: 3.0198001 | CQ53: 3.0198001 | CR53: 2.4189818 | CS53: 2.4189818 | CT53: 2.4189818 | CU53: 2.1228225 | CV53: 2.1228225 | CW53: 2.1228225 | CX53: 2.0531437 | CY53: 46022 | CZ53: 46022 | DA53: 46022 | DB53: 46022 | DC53: 46022 | DD53: 46022 | DE53: 45930 | DF53: 45930 | DG53: 45930 | DH53: 45838 | DI53: 45838 | DJ53: 45838 | DK53: 45747 | DL53: 45747 | DM53: 45747 | DN53: 45657 | DO53: 45657 | DP53: 45657 | DQ53: 45565 | DR53: 45565 | DS53: 45565 | DT53: 45473 | DU53: 45473 | DV53: 45473 | DW53: 45382 | DX53: Shareholder Report | DY53: Shareholder Report | DZ53: Shareholder Report | EA53: Shareholder Report | EB53: Shareholder Report | EC53: Shareholder Report | ED53: Shareholder Report | EE53: Shareholder Report | EF53: Shareholder Report | EG53: Shareholder Report | EH53: Shareholder Report | EI53: Shareholder Report | EJ53: Shareholder Report | EK53: Shareholder Report | EL53: Shareholder Report | EM53: Shareholder Report | EN53: Shareholder Report | EO53: Shareholder Report | EP53: Shareholder Report | EQ53: Shareholder Report | ER53: Shareholder Report | ES53: Shareholder Report | ET53: Shareholder Report | EU53: Shareholder Report | EV53: Shareholder Report | EW53: Strategic Entities | EX53: Corporation | EY53: 3.6402246 | FA53: Low | FB53: Low | FC53: Low | FD53: Low | FE53: Low | FF53: Low | FG53: Low | FH53: Low | FI53: Low | FJ53: Low | FK53: Low | FL53: Low | FM53: Low | FN53: Low | FO53: Low | FP53: Low | FQ53: Low | FR53: Low | FS53: Low | FT53: Low | FU53: Low | FV53: Low | FW53: Low | FX53: Low | FY53: Low | FZ53: Kolkata | GA53: India
A54: 52 | B54: Bandhan Asset Management Company Limited | C54: 0.000686 | D54: 0.000686 | E54: 0.000642 | F54: 0.000177 | G54: 0.000176 | H54: 0.000174 | I54: 1.8e-05 | J54: 0.000522 | K54: 0.001002 | L54: 0.001187 | M54: 0.001499 | N54: 0.001624 | O54: 0.001777 | P54: 0.001832 | Q54: 0.001832 | R54: 0.002391 | S54: 0.003352 | T54: 0.005305 | U54: 0.005816 | V54: 0.005816 | W54: 0.005815 | X54: 0.006318 | Y54: 0.006547 | Z54: 0.007156 | AA54: 0.007214 | AB54: 0.091884 | AC54: 0.091884 | AD54: 0.08598 | AE54: 0.023671 | AF54: 0.023557 | AG54: 0.02326 | AH54: 0.002421 | AI54: 0.06985 | AJ54: 0.134094 | AK54: 0.158926 | AL54: 0.200715 | AM54: 0.217338 | AN54: 0.23781 | AO54: 0.245167 | AP54: 0.245101 | AQ54: 0.319959 | AR54: 0.448509 | AS54: 0.709782 | AT54: 0.778078 | AU54: 0.777995 | AV54: 0.777864 | AW54: 0.845176 | AX54: 0.875716 | AY54: 0.956807 | AZ54: 0.964641 | BA54: 0 | BB54: 0.005904 | BC54: 0.062309 | BD54: 0.000114 | BE54: 0.000297 | BF54: 0.020839 | BG54: -0.067429 | BH54: -0.064244 | BI54: -0.024832 | BJ54: -0.041789 | BK54: -0.016623 | BL54: -0.020472 | BM54: -0.007357 | BN54: 6.6e-05 | BO54: -0.074858 | BP54: -0.12855 | BQ54: -0.261273 | BR54: -0.068296 | BS54: 8.3e-05 | BT54: 0.000131 | BU54: -0.067312 | BV54: -0.03054 | BW54: -0.081091 | BX54: -0.007834 | BY54: 6.8e-05 | BZ54: 3.3160582 | CA54: 3.3160582 | CB54: 2.385254 | CC54: 0.68939481 | CD54: 0.72590684 | CE54: 0.8548372 | CF54: 0.08693055 | CG54: 2.4686561 | CH54: 4.3671207 | CI54: 5.1773782 | CJ54: 6.2610386 | CK54: 6.6575025 | CL54: 7.0537313 | CM54: 7.0724518 | CN54: 6.9516356 | CO54: 7.5952251 | CP54: 11.289295 | CQ54: 21.639574 | CR54: 22.646681 | CS54: 20.749927 | CT54: 18.996859 | CU54: 19.571155 | CV54: 18.032389 | CW54: 20.506123 | CX54: 18.229245 | CY54: 46142 | CZ54: 46142 | DA54: 46112 | DB54: 46081 | DC54: 46053 | DD54: 46022 | DE54: 45991 | DF54: 45961 | DG54: 45930 | DH54: 45900 | DI54: 45869 | DJ54: 45838 | DK54: 45808 | DL54: 45777 | DM54: 45747 | DN54: 45716 | DO54: 45688 | DP54: 45657 | DQ54: 45626 | DR54: 45596 | DS54: 45565 | DT54: 45535 | DU54: 45504 | DV54: 45473 | DW54: 45443 | DX54: Aggregate MFs | DY54: Aggregate MFs | DZ54: Aggregate MFs | EA54: Aggregate MFs | EB54: Aggregate MFs | EC54: Aggregate MFs | ED54: Aggregate MFs | EE54: Aggregate MFs | EF54: Aggregate MFs | EG54: Aggregate MFs | EH54: Aggregate MFs | EI54: Aggregate MFs | EJ54: Aggregate MFs | EK54: Aggregate MFs | EL54: Aggregate MFs | EM54: Aggregate MFs | EN54: Aggregate MFs | EO54: Aggregate MFs | EP54: Aggregate MFs | EQ54: Aggregate MFs | ER54: Aggregate MFs | ES54: Aggregate MFs | ET54: Aggregate MFs | EU54: Aggregate MFs | EV54: Aggregate MFs | EW54: Investment Managers | EX54: Investment Advisor | EY54: 10095.886 | EZ54: Growth | FA54: Moderate | FB54: Moderate | FC54: Moderate | FD54: Moderate | FE54: Moderate | FF54: Moderate | FG54: Moderate | FH54: Moderate | FI54: Moderate | FJ54: Moderate | FK54: Moderate | FL54: Moderate | FM54: Moderate | FN54: Moderate | FO54: Moderate | FP54: Moderate | FQ54: Moderate | FR54: Moderate | FS54: Moderate | FT54: Moderate | FU54: Moderate | FV54: Moderate | FW54: Moderate | FX54: Moderate | FY54: Moderate | FZ54: Mumbai | GA54: India
A55: 53 | B55: William Blair Investment Management, LLC | C55: 0.000591 | D55: 0.000591 | E55: 0.000591 | F55: 0.000603 | G55: 0.000869 | H55: 0.001397 | I55: 0.001429 | J55: 0.000652 | K55: 0.000452 | L55: 0.000454 | M55: 0.00046 | N55: 0.00047 | O55: 0 | P55: 0 | Q55: 0 | R55: 0 | S55: 0 | T55: 0 | U55: 0 | V55: 0 | W55: 0 | X55: 0 | Y55: 0 | Z55: 1.1e-05 | AA55: 6.4e-05 | AB55: 0.079099 | AC55: 0.079099 | AD55: 0.079099 | AE55: 0.080718 | AF55: 0.116287 | AG55: 0.187107 | AH55: 0.191305 | AI55: 0.087237 | AJ55: 0.060571 | AK55: 0.060793 | AL55: 0.061643 | AM55: 0.06289 | AN55: 0 | AO55: 0 | AP55: 0 | AQ55: 0 | AR55: 0 | AS55: 0 | AT55: 0 | AU55: 0 | AV55: 0 | AW55: 0 | AX55: 0 | AY55: 0.00152 | AZ55: 0.0085 | BA55: 0 | BB55: 0 | BC55: -0.001619 | BD55: -0.035569 | BE55: -0.07082 | BF55: -0.004198 | BG55: 0.104068 | BH55: 0.026666 | BI55: -0.000222 | BJ55: -0.00085 | BK55: -0.001247 | BL55: 0.06289 | BM55: 0 | BN55: 0 | BO55: 0 | BP55: 0 | BQ55: 0 | BR55: 0 | BS55: 0 | BT55: 0 | BU55: 0 | BV55: 0 | BW55: -0.00152 | BX55: -0.00698 | BY55: -0.014601 | BZ55: 2.1943615 | CA55: 2.1943615 | CB55: 2.1943615 | CC55: 2.3508331 | CD55: 3.5833734 | CE55: 6.8764413 | CF55: 6.8691653 | CG55: 3.0831518 | CH55: 1.9726525 | CI55: 1.9804711 | CJ55: 1.9228718 | CK55: 1.9264479 | CL55: 0 | CM55: 0 | CN55: 0 | CO55: 0 | CP55: 0 | CQ55: 0 | CR55: 0 | CS55: 0 | CT55: 0 | CU55: 0 | CV55: 0 | CW55: 0.03257638 | CX55: 0.16062824 | CY55: 46112 | CZ55: 46112 | DA55: 46112 | DB55: 46081 | DC55: 46053 | DD55: 46022 | DE55: 45991 | DF55: 45961 | DG55: 45930 | DH55: 45900 | DI55: 45869 | DJ55: 45838 | DK55: 45504 | DL55: 45504 | DM55: 45504 | DN55: 45504 | DO55: 45504 | DP55: 45504 | DQ55: 45504 | DR55: 45504 | DS55: 45504 | DT55: 45504 | DU55: 45504 | DV55: 45473 | DW55: 45443 | DX55: Aggregate MFs | DY55: Aggregate MFs | DZ55: Aggregate MFs | EA55: Aggregate MFs | EB55: Aggregate MFs | EC55: Aggregate MFs | ED55: Aggregate MFs | EE55: Aggregate MFs | EF55: Aggregate MFs | EG55: Aggregate MFs | EH55: Aggregate MFs | EI55: Aggregate MFs | EJ55: Aggregate MFs | EK55: Aggregate MFs | EL55: Aggregate MFs | EM55: Aggregate MFs | EN55: Aggregate MFs | EO55: Aggregate MFs | EP55: Aggregate MFs | EQ55: Aggregate MFs | ER55: Aggregate MFs | ES55: Aggregate MFs | ET55: Aggregate MFs | EU55: Aggregate MFs | EV55: Aggregate MFs | EW55: Investment Managers | EX55: Investment Advisor/Hedge Fund | EY55: 43504.498 | EZ55: GARP | FA55: Moderate | FB55: Moderate | FC55: Moderate | FD55: Moderate | FE55: Moderate | FF55: Moderate | FG55: Moderate | FH55: Moderate | FI55: Moderate | FJ55: Moderate | FK55: Moderate | FL55: Moderate | FM55: Moderate | FN55: Moderate | FO55: Moderate | FP55: Moderate | FQ55: Low | FR55: Low | FS55: Low | FT55: Low | FU55: Low | FV55: Low | FW55: Low | FX55: Low | FY55: Low | FZ55: Chicago | GA55: United States
A56: 54 | B56: Elkay Fiscal Services Pvt. Ltd. | C56: 0.000493 | D56: 0.000493 | E56: 0.000493 | F56: 0.000493 | G56: 0.000493 | H56: 0.000493 | I56: 0.000493 | J56: 0.000493 | K56: 0.000493 | L56: 0.000493 | M56: 0.000493 | N56: 0.000493 | O56: 0.000493 | P56: 0.000493 | Q56: 0.000493 | R56: 0.000493 | S56: 0.000493 | T56: 0.000493 | U56: 0.000493 | V56: 0.000493 | W56: 0.000493 | X56: 0.000493 | Y56: 0.000493 | Z56: 0.000494 | AA56: 0.000494 | AB56: 0.066 | AC56: 0.066 | AD56: 0.066 | AE56: 0.066 | AF56: 0.066 | AG56: 0.066 | AH56: 0.066 | AI56: 0.066 | AJ56: 0.066 | AK56: 0.066 | AL56: 0.066 | AM56: 0.066 | AN56: 0.066 | AO56: 0.066 | AP56: 0.066 | AQ56: 0.066 | AR56: 0.066 | AS56: 0.066 | AT56: 0.066 | AU56: 0.066 | AV56: 0.066 | AW56: 0.066 | AX56: 0.066 | AY56: 0.066 | AZ56: 0.066 | BA56: 0 | BB56: 0 | BC56: 0 | BD56: 0 | BE56: 0 | BF56: 0 | BG56: 0 | BH56: 0 | BI56: 0 | BJ56: 0 | BK56: 0 | BL56: 0 | BM56: 0 | BN56: 0 | BO56: 0 | BP56: 0 | BQ56: 0 | BR56: 0 | BS56: 0 | BT56: 0 | BU56: 0 | BV56: 0 | BW56: 0 | BX56: 0 | BY56: 0 | BZ56: 2.4255914 | CA56: 2.4255914 | CB56: 2.4255914 | CC56: 2.4255914 | CD56: 2.4255914 | CE56: 2.4255914 | CF56: 2.1494621 | CG56: 2.1494621 | CH56: 2.1494621 | CI56: 2.0217135 | CJ56: 2.0217135 | CK56: 2.0217135 | CL56: 1.8719138 | CM56: 1.8719138 | CN56: 1.8719138 | CO56: 2.0121838 | CP56: 2.0121838 | CQ56: 2.0121838 | CR56: 1.6118405 | CS56: 1.6118405 | CT56: 1.6118405 | CU56: 1.4145006 | CV56: 1.4145006 | CW56: 1.4145006 | CX56: 1.3680716 | CY56: 46022 | CZ56: 46022 | DA56: 46022 | DB56: 46022 | DC56: 46022 | DD56: 46022 | DE56: 45930 | DF56: 45930 | DG56: 45930 | DH56: 45838 | DI56: 45838 | DJ56: 45838 | DK56: 45747 | DL56: 45747 | DM56: 45747 | DN56: 45657 | DO56: 45657 | DP56: 45657 | DQ56: 45565 | DR56: 45565 | DS56: 45565 | DT56: 45473 | DU56: 45473 | DV56: 45473 | DW56: 45382 | DX56: Shareholder Report | DY56: Shareholder Report | DZ56: Shareholder Report | EA56: Shareholder Report | EB56: Shareholder Report | EC56: Shareholder Report | ED56: Shareholder Report | EE56: Shareholder Report | EF56: Shareholder Report | EG56: Shareholder Report | EH56: Shareholder Report | EI56: Shareholder Report | EJ56: Shareholder Report | EK56: Shareholder Report | EL56: Shareholder Report | EM56: Shareholder Report | EN56: Shareholder Report | EO56: Shareholder Report | EP56: Shareholder Report | EQ56: Shareholder Report | ER56: Shareholder Report | ES56: Shareholder Report | ET56: Shareholder Report | EU56: Shareholder Report | EV56: Shareholder Report | EW56: Strategic Entities | EX56: Corporation | EY56: 2.4255914 | FA56: Low | FB56: Low | FC56: Low | FD56: Low | FE56: Low | FF56: Low | FG56: Low | FH56: Low | FI56: Low | FJ56: Low | FK56: Low | FL56: Low | FM56: Low | FN56: Low | FO56: Low | FP56: Low | FQ56: Low | FR56: Low | FS56: Low | FT56: Low | FU56: Low | FV56: Low | FW56: Low | FX56: Low | FY56: Low | FZ56: Kolkata | GA56: India
A57: 55 | B57: Charles Schwab Investment Management, Inc. | C57: 0.00049 | D57: 0.00049 | E57: 0.00049 | F57: 0.000547 | G57: 0.000547 | H57: 0.000547 | I57: 0.000487 | J57: 0.000487 | K57: 0.000487 | L57: 0.000297 | M57: 0.000297 | N57: 0.000297 | AB57: 0.065564 | AC57: 0.065564 | AD57: 0.065564 | AE57: 0.073227 | AF57: 0.073227 | AG57: 0.073227 | AH57: 0.065234 | AI57: 0.065234 | AJ57: 0.065234 | AK57: 0.039699 | AL57: 0.039699 | AM57: 0.039699 | BA57: 0 | BB57: 0 | BC57: -0.007663 | BD57: 0 | BE57: 0 | BF57: 0.007993 | BG57: 0 | BH57: 0 | BI57: 0.025535 | BJ57: 0 | BK57: 0 | BL57: 0.039699 | BZ57: 1.818874 | CA57: 1.818874 | CB57: 1.818874 | CC57: 2.6911936 | CD57: 2.6911936 | CE57: 2.6911936 | CF57: 2.1245153 | CG57: 2.1245153 | CH57: 2.1245153 | CI57: 1.2160607 | CJ57: 1.2160607 | CK57: 1.2160607 | CY57: 46112 | CZ57: 46112 | DA57: 46112 | DB57: 46022 | DC57: 46022 | DD57: 46022 | DE57: 45930 | DF57: 45930 | DG57: 45930 | DH57: 45838 | DI57: 45838 | DJ57: 45838 | DX57: Aggregate MFs | DY57: Aggregate MFs | DZ57: Aggregate MFs | EA57: Aggregate MFs | EB57: Aggregate MFs | EC57: Aggregate MFs | ED57: Aggregate MFs | EE57: Aggregate MFs | EF57: Aggregate MFs | EG57: Aggregate MFs | EH57: Aggregate MFs | EI57: Aggregate MFs | EW57: Investment Managers | EX57: Investment Advisor | EY57: 880179.49 | EZ57: Index | FA57: Low | FB57: Low | FC57: Low | FD57: Low | FE57: Low | FF57: Low | FG57: Low | FH57: Low | FI57: Low | FJ57: Low | FK57: Low | FL57: Low | FZ57: San Francisco | GA57: United States
A58: 56 | B58: Driehaus Capital Management, LLC | C58: 0.000477 | D58: 0.000477 | E58: 0.000477 | F58: 0.000478 | G58: 0.000478 | H58: 0.000478 | I58: 0.000478 | J58: 0.000478 | K58: 0.000478 | L58: 0.000478 | M58: 0.000478 | N58: 0.000478 | O58: 0.000478 | P58: 0.000478 | Q58: 0.000478 | R58: 0.000478 | S58: 0 | T58: 0 | U58: 0 | V58: 0 | W58: 0 | X58: 0 | Y58: 0 | Z58: 0 | AA58: 0 | AB58: 0.063935 | AC58: 0.063935 | AD58: 0.063935 | AE58: 0.063935 | AF58: 0.063935 | AG58: 0.063935 | AH58: 0.063935 | AI58: 0.063935 | AJ58: 0.063935 | AK58: 0.063935 | AL58: 0.063935 | AM58: 0.063935 | AN58: 0.063935 | AO58: 0.063935 | AP58: 0.063935 | AQ58: 0.063935 | AR58: 0 | AS58: 0 | AT58: 0 | AU58: 0 | AV58: 0 | AW58: 0 | AX58: 0 | AY58: 0 | AZ58: 0 | BA58: 0 | BB58: 0 | BC58: 0 | BD58: 0 | BE58: 0 | BF58: 0 | BG58: 0 | BH58: 0 | BI58: 0 | BJ58: 0 | BK58: 0 | BL58: 0 | BM58: 0 | BN58: 0 | BO58: 0 | BP58: 0.063935 | BQ58: 0 | BR58: 0 | BS58: 0 | BT58: 0 | BU58: 0 | BV58: 0 | BW58: 0 | BX58: 0 | BY58: 0 | BZ58: 1.7736824 | CA58: 1.7736824 | CB58: 1.7736824 | CC58: 1.8620446 | CD58: 1.9701513 | CE58: 2.3496998 | CF58: 2.2957062 | CG58: 2.2596067 | CH58: 2.08221 | CI58: 2.082829 | CJ58: 1.9943677 | CK58: 1.9584584 | CL58: 1.8963892 | CM58: 1.8443641 | CN58: 1.8133456 | CO58: 1.5176967 | CP58: 0 | CQ58: 0 | CR58: 0 | CS58: 0 | CT58: 0 | CU58: 0 | CV58: 0 | CW58: 0 | CX58: 0 | CY58: 46112 | CZ58: 46112 | DA58: 46112 | DB58: 46081 | DC58: 46053 | DD58: 46022 | DE58: 45991 | DF58: 45961 | DG58: 45930 | DH58: 45900 | DI58: 45869 | DJ58: 45838 | DK58: 45808 | DL58: 45777 | DM58: 45747 | DN58: 45716 | DO58: 45199 | DP58: 45199 | DQ58: 45199 | DR58: 45199 | DS58: 45199 | DT58: 45199 | DU58: 45199 | DV58: 45199 | DW58: 45199 | DX58: Aggregate MFs | DY58: Aggregate MFs | DZ58: Aggregate MFs | EA58: Aggregate MFs | EB58: Aggregate MFs | EC58: Aggregate MFs | ED58: Aggregate MFs | EE58: Aggregate MFs | EF58: Aggregate MFs | EG58: Aggregate MFs | EH58: Aggregate MFs | EI58: Aggregate MFs | EJ58: Aggregate MFs | EK58: Aggregate MFs | EL58: Aggregate MFs | EM58: Aggregate MFs | EN58: Aggregate MFs | EO58: Aggregate MFs | EP58: Aggregate MFs | EQ58: Aggregate MFs | ER58: Aggregate MFs | ES58: Aggregate MFs | ET58: Aggregate MFs | EU58: Aggregate MFs | EV58: Aggregate MFs | EW58: Investment Managers | EX58: Investment Advisor/Hedge Fund | EY58: 20856.783 | EZ58: Aggressive Growth | FA58: Moderate | FB58: Moderate | FC58: High | FD58: High | FE58: High | FF58: High | FG58: High | FH58: High | FI58: High | FJ58: High | FK58: High | FL58: High | FM58: Moderate | FN58: Moderate | FO58: Moderate | FP58: Moderate | FQ58: Moderate | FR58: Moderate | FS58: Moderate | FT58: Moderate | FU58: Moderate | FV58: Moderate | FW58: Moderate | FX58: Moderate | FY58: Moderate | FZ58: Chicago | GA58: United States
A59: 57 | B59: Nuveen LLC | C59: 0.00045 | D59: 0.00045 | E59: 0.00045 | F59: 0.00045 | G59: 0.00045 | H59: 0.00045 | I59: 0.00045 | J59: 0.00045 | K59: 0.00045 | L59: 0.00045 | M59: 0.00045 | N59: 0.00045 | O59: 0.00045 | P59: 0.00045 | Q59: 0.00045 | R59: 0.00045 | S59: 0.00045 | T59: 0.00045 | U59: 0.00045 | V59: 0.000451 | W59: 0.000451 | X59: 0.000451 | Y59: 0.000451 | Z59: 0.000451 | AA59: 0.000451 | AB59: 0.060269 | AC59: 0.060269 | AD59: 0.060269 | AE59: 0.060269 | AF59: 0.060269 | AG59: 0.060269 | AH59: 0.060269 | AI59: 0.060269 | AJ59: 0.060269 | AK59: 0.060269 | AL59: 0.060269 | AM59: 0.060269 | AN59: 0.060269 | AO59: 0.060269 | AP59: 0.060269 | AQ59: 0.060269 | AR59: 0.060269 | AS59: 0.060269 | AT59: 0.060269 | AU59: 0.060269 | AV59: 0.060269 | AW59: 0.060269 | AX59: 0.060269 | AY59: 0.060269 | AZ59: 0.060269 | BA59: 0 | BB59: 0 | BC59: 0 | BD59: 0 | BE59: 0 | BF59: 0 | BG59: 0 | BH59: 0 | BI59: 0 | BJ59: 0 | BK59: 0 | BL59: 0 | BM59: 0 | BN59: 0 | BO59: 0 | BP59: 0 | BQ59: 0 | BR59: 0 | BS59: 0 | BT59: 0 | BU59: 0 | BV59: 0 | BW59: 0 | BX59: 0 | BY59: 0 | BZ59: 2.175085 | CA59: 2.175085 | CB59: 1.6719803 | CC59: 1.7552759 | CD59: 1.8571838 | CE59: 2.2149692 | CF59: 2.1640716 | CG59: 2.130042 | CH59: 1.9628171 | CI59: 1.8800116 | CJ59: 1.8800116 | CK59: 1.8461614 | CL59: 1.7876512 | CM59: 1.7386092 | CN59: 1.7093693 | CO59: 1.4306727 | CP59: 1.5170142 | CQ59: 1.8374592 | CR59: 1.7541851 | CS59: 1.6074362 | CT59: 1.471879 | CU59: 1.3956075 | CV59: 1.2410348 | CW59: 1.2916748 | CX59: 1.1389298 | CY59: 46142 | CZ59: 46142 | DA59: 46112 | DB59: 46081 | DC59: 46053 | DD59: 46022 | DE59: 45991 | DF59: 45961 | DG59: 45930 | DH59: 45869 | DI59: 45869 | DJ59: 45838 | DK59: 45808 | DL59: 45777 | DM59: 45747 | DN59: 45716 | DO59: 45688 | DP59: 45657 | DQ59: 45626 | DR59: 45596 | DS59: 45565 | DT59: 45535 | DU59: 45504 | DV59: 45473 | DW59: 45443 | DX59: Aggregate MFs | DY59: Aggregate MFs | DZ59: Aggregate MFs | EA59: Aggregate MFs | EB59: Aggregate MFs | EC59: Aggregate MFs | ED59: Aggregate MFs | EE59: Aggregate MFs | EF59: Aggregate MFs | EG59: Aggregate MFs | EH59: Aggregate MFs | EI59: Aggregate MFs | EJ59: Aggregate MFs | EK59: Aggregate MFs | EL59: Aggregate MFs | EM59: Aggregate MFs | EN59: Aggregate MFs | EO59: Aggregate MFs | EP59: Aggregate MFs | EQ59: Aggregate MFs | ER59: Aggregate MFs | ES59: Aggregate MFs | ET59: Aggregate MFs | EU59: Aggregate MFs | EV59: Aggregate MFs | EW59: Investment Managers | EX59: Investment Advisor | EY59: 572820.37 | EZ59: GARP | FA59: Low | FB59: Low | FC59: Low | FD59: Low | FE59: Low | FF59: Low | FG59: Low | FH59: Low | FI59: Low | FJ59: Low | FK59: Low | FL59: Low | FM59: Low | FN59: Low | FO59: Low | FP59: Low | FQ59: Low | FR59: Low | FS59: Low | FT59: Low | FU59: Low | FV59: Low | FW59: Low | FX59: Low | FY59: Low | FZ59: New York | GA59: United States
A60: 58 | B60: Florida State Board of Administration | C60: 0.00043 | D60: 0.00043 | E60: 0.00043 | F60: 0.00102 | G60: 0.00102 | H60: 0.00102 | I60: 0.000358 | J60: 0.000358 | K60: 0.000358 | L60: 0.000358 | M60: 0.000358 | N60: 0.000358 | O60: 0 | P60: 0 | Q60: 0 | R60: 0 | S60: 0 | T60: 0 | U60: 1.8e-05 | V60: 1.8e-05 | W60: 1.8e-05 | X60: 1.8e-05 | Y60: 1.8e-05 | Z60: 1.8e-05 | AA60: 0.000789 | AB60: 0.057628 | AC60: 0.057628 | AD60: 0.057628 | AE60: 0.136551 | AF60: 0.136551 | AG60: 0.136551 | AH60: 0.047902 | AI60: 0.047902 | AJ60: 0.047902 | AK60: 0.047902 | AL60: 0.047902 | AM60: 0.047902 | AN60: 0 | AO60: 0 | AP60: 0 | AQ60: 0 | AR60: 0 | AS60: 0 | AT60: 0.002402 | AU60: 0.002402 | AV60: 0.002402 | AW60: 0.002402 | AX60: 0.002402 | AY60: 0.002402 | AZ60: 0.105451 | BA60: 0 | BB60: 0 | BC60: -0.078923 | BD60: 0 | BE60: 0 | BF60: 0.088649 | BG60: 0 | BH60: 0 | BI60: 0 | BJ60: 0 | BK60: 0 | BL60: 0.047902 | BM60: 0 | BN60: 0 | BO60: 0 | BP60: 0 | BQ60: 0 | BR60: -0.002402 | BS60: 0 | BT60: 0 | BU60: 0 | BV60: 0 | BW60: 0 | BX60: -0.103049 | BY60: 0 | BZ60: 1.5987138 | CA60: 1.5987138 | CB60: 1.5987138 | CC60: 5.0184383 | CD60: 5.0184383 | CE60: 5.0184383 | CF60: 1.5600535 | CG60: 1.5600535 | CH60: 1.5600535 | CI60: 1.4673351 | CJ60: 1.4673351 | CK60: 1.4673351 | CL60: 0 | CM60: 0 | CN60: 0 | CO60: 0 | CP60: 0 | CQ60: 0 | CR60: 0.05147925 | CS60: 0.05147925 | CT60: 0.05147925 | CU60: 0.05147925 | CV60: 0.05147925 | CW60: 0.05147925 | CX60: 2.1019849 | CY60: 46112 | CZ60: 46112 | DA60: 46112 | DB60: 46022 | DC60: 46022 | DD60: 46022 | DE60: 45930 | DF60: 45930 | DG60: 45930 | DH60: 45838 | DI60: 45838 | DJ60: 45838 | DK60: 45657 | DL60: 45657 | DM60: 45657 | DN60: 45657 | DO60: 45657 | DP60: 45657 | DQ60: 45473 | DR60: 45473 | DS60: 45473 | DT60: 45473 | DU60: 45473 | DV60: 45473 | DW60: 45291 | DX60: Aggregate MFs | DY60: Aggregate MFs | DZ60: Aggregate MFs | EA60: Aggregate MFs | EB60: Aggregate MFs | EC60: Aggregate MFs | ED60: Aggregate MFs | EE60: Aggregate MFs | EF60: Aggregate MFs | EG60: Aggregate MFs | EH60: Aggregate MFs | EI60: Aggregate MFs | EJ60: Aggregate MFs | EK60: Aggregate MFs | EL60: Aggregate MFs | EM60: Aggregate MFs | EN60: Aggregate MFs | EO60: Aggregate MFs | EP60: Aggregate MFs | EQ60: Aggregate MFs | ER60: Aggregate MFs | ES60: Aggregate MFs | ET60: Aggregate MFs | EU60: Aggregate MFs | EV60: Aggregate MFs | EW60: Investment Managers | EX60: Pension Fund | EY60: 92449.744 | EZ60: Index | FA60: Low | FB60: Low | FC60: Low | FD60: Low | FE60: Low | FF60: Low | FG60: Low | FH60: Low | FI60: Low | FJ60: Low | FK60: Low | FL60: Low | FM60: Low | FN60: Low | FO60: Low | FP60: Low | FQ60: Low | FR60: Low | FS60: Low | FT60: Low | FU60: Low | FW60: Low | FX60: Low | FY60: Low | FZ60: Tallahassee | GA60: United States
A61: 59 | B61: WhiteOak Capital Asset Management Limited | C61: 0.000398 | D61: 0.000398 | AB61: 0.053322 | AC61: 0.053322 | BA61: 0 | BB61: 0.053322 | BZ61: 1.9243705 | CA61: 1.9243705 | CY61: 46142 | CZ61: 46142 | DX61: Aggregate MFs | DY61: Aggregate MFs | EW61: Investment Managers | EX61: Investment Advisor | EY61: 1055.9162 | FA61: Moderate | FB61: Moderate | FZ61: Mumbai | GA61: India
A62: 60 | B62: Khaitan (Deepshikha) | C62: 0.000373 | D62: 0.000373 | E62: 0.000373 | F62: 0.000373 | G62: 0.000373 | H62: 0.000373 | I62: 0.000373 | J62: 0.000373 | K62: 0.000373 | L62: 0.000374 | M62: 0.000374 | N62: 0.000374 | O62: 0.000374 | P62: 0.000374 | Q62: 0.000374 | R62: 0.000374 | S62: 0.000374 | T62: 0.000374 | U62: 0.000374 | V62: 0.000374 | W62: 0.000374 | X62: 0.000374 | Y62: 0.000374 | Z62: 0.000374 | AA62: 0.000374 | AB62: 0.05 | AC62: 0.05 | AD62: 0.05 | AE62: 0.05 | AF62: 0.05 | AG62: 0.05 | AH62: 0.05 | AI62: 0.05 | AJ62: 0.05 | AK62: 0.05 | AL62: 0.05 | AM62: 0.05 | AN62: 0.05 | AO62: 0.05 | AP62: 0.05 | AQ62: 0.05 | AR62: 0.05 | AS62: 0.05 | AT62: 0.05 | AU62: 0.05 | AV62: 0.05 | AW62: 0.05 | AX62: 0.05 | AY62: 0.05 | AZ62: 0.05 | BA62: 0 | BB62: 0 | BC62: 0 | BD62: 0 | BE62: 0 | BF62: 0 | BG62: 0 | BH62: 0 | BI62: 0 | BJ62: 0 | BK62: 0 | BL62: 0 | BM62: 0 | BN62: 0 | BO62: 0 | BP62: 0 | BQ62: 0 | BR62: 0 | BS62: 0 | BT62: 0 | BU62: 0 | BV62: 0 | BW62: 0 | BX62: 0 | BY62: 0 | BZ62: 1.8375692 | CA62: 1.8375692 | CB62: 1.8375692 | CC62: 1.8375692 | CD62: 1.8375692 | CE62: 1.8375692 | CF62: 1.6283804 | CG62: 1.6283804 | CH62: 1.6283804 | CI62: 1.5316011 | CJ62: 1.5316011 | CK62: 1.5316011 | CL62: 1.4181165 | CM62: 1.4181165 | CN62: 1.4181165 | CO62: 1.5243817 | CP62: 1.5243817 | CQ62: 1.5243817 | CR62: 1.2210913 | CS62: 1.2210913 | CT62: 1.2210913 | CU62: 1.0715914 | CV62: 1.0715914 | CW62: 1.0715914 | CX62: 1.0364178 | CY62: 46022 | CZ62: 46022 | DA62: 46022 | DB62: 46022 | DC62: 46022 | DD62: 46022 | DE62: 45930 | DF62: 45930 | DG62: 45930 | DH62: 45838 | DI62: 45838 | DJ62: 45838 | DK62: 45747 | DL62: 45747 | DM62: 45747 | DN62: 45657 | DO62: 45657 | DP62: 45657 | DQ62: 45565 | DR62: 45565 | DS62: 45565 | DT62: 45473 | DU62: 45473 | DV62: 45473 | DW62: 45382 | DX62: Shareholder Report | DY62: Shareholder Report | DZ62: Shareholder Report | EA62: Shareholder Report | EB62: Shareholder Report | EC62: Shareholder Report | ED62: Shareholder Report | EE62: Shareholder Report | EF62: Shareholder Report | EG62: Shareholder Report | EH62: Shareholder Report | EI62: Shareholder Report | EJ62: Shareholder Report | EK62: Shareholder Report | EL62: Shareholder Report | EM62: Shareholder Report | EN62: Shareholder Report | EO62: Shareholder Report | EP62: Shareholder Report | EQ62: Shareholder Report | ER62: Shareholder Report | ES62: Shareholder Report | ET62: Shareholder Report | EU62: Shareholder Report | EV62: Shareholder Report | EW62: Strategic Entities | EX62: Individual Investor | EY62: 22.165353 | FA62: Low | FB62: Low | FC62: Low | FD62: Low | FE62: Low | FF62: Low | FG62: Low | FH62: Low | FI62: Low | FJ62: Low | FK62: Low | FL62: Low | FM62: Low | FN62: Low | FO62: Low | FP62: Low | FQ62: Low | FR62: Low | FS62: Low | FT62: Low | FU62: Low | FV62: Low | FW62: Low | FX62: Low | FY62: Low | GA62: India
A63: 61 | B63: Tokio Marine Asset Management International Pte. Ltd. | C63: 0.000373 | D63: 0.000373 | E63: 0.000373 | F63: 0.000373 | G63: 0.000373 | H63: 0.000373 | I63: 0.000373 | J63: 0.000373 | K63: 0.000373 | L63: 0.000374 | M63: 0.000374 | N63: 0.000374 | O63: 0.000374 | P63: 0.000374 | Q63: 0.000374 | R63: 0.000179 | S63: 0.000179 | T63: 0.000179 | U63: 0.000179 | V63: 0.000179 | W63: 0.000179 | X63: 0.000179 | Y63: 0.000179 | Z63: 0.000179 | AA63: 0.000179 | AB63: 0.05 | AC63: 0.05 | AD63: 0.05 | AE63: 0.05 | AF63: 0.05 | AG63: 0.05 | AH63: 0.05 | AI63: 0.05 | AJ63: 0.05 | AK63: 0.05 | AL63: 0.05 | AM63: 0.05 | AN63: 0.05 | AO63: 0.05 | AP63: 0.05 | AQ63: 0.024 | AR63: 0.024 | AS63: 0.024 | AT63: 0.024 | AU63: 0.024 | AV63: 0.024 | AW63: 0.024 | AX63: 0.024 | AY63: 0.024 | AZ63: 0.024 | BA63: 0 | BB63: 0 | BC63: 0 | BD63: 0 | BE63: 0 | BF63: 0 | BG63: 0 | BH63: 0 | BI63: 0 | BJ63: 0 | BK63: 0 | BL63: 0 | BM63: 0 | BN63: 0 | BO63: 0.026 | BP63: 0 | BQ63: 0 | BR63: 0 | BS63: 0 | BT63: 0 | BU63: 0 | BV63: 0 | BW63: 0 | BX63: 0 | BY63: 0 | BZ63: 1.4181165 | CA63: 1.4181165 | CB63: 1.4181165 | CC63: 1.4181165 | CD63: 1.4181165 | CE63: 1.4181165 | CF63: 1.4181165 | CG63: 1.4181165 | CH63: 1.4181165 | CI63: 1.4181165 | CJ63: 1.4181165 | CK63: 1.4181165 | CL63: 1.4181165 | CM63: 1.4181165 | CN63: 1.4181165 | CO63: 0.49748056 | CP63: 0.49748056 | CQ63: 0.49748056 | CR63: 0.49748056 | CS63: 0.49748056 | CT63: 0.49748056 | CU63: 0.49748056 | CV63: 0.49748056 | CW63: 0.49748056 | CX63: 0.49748056 | CY63: 45747 | CZ63: 45747 | DA63: 45747 | DB63: 45747 | DC63: 45747 | DD63: 45747 | DE63: 45747 | DF63: 45747 | DG63: 45747 | DH63: 45747 | DI63: 45747 | DJ63: 45747 | DK63: 45747 | DL63: 45747 | DM63: 45747 | DN63: 45382 | DO63: 45382 | DP63: 45382 | DQ63: 45382 | DR63: 45382 | DS63: 45382 | DT63: 45382 | DU63: 45382 | DV63: 45382 | DW63: 45382 | DX63: Aggregate MFs | DY63: Aggregate MFs | DZ63: Aggregate MFs | EA63: Aggregate MFs | EB63: Aggregate MFs | EC63: Aggregate MFs | ED63: Aggregate MFs | EE63: Aggregate MFs | EF63: Aggregate MFs | EG63: Aggregate MFs | EH63: Aggregate MFs | EI63: Aggregate MFs | EJ63: Aggregate MFs | EK63: Aggregate MFs | EL63: Aggregate MFs | EM63: Aggregate MFs | EN63: Aggregate MFs | EO63: Aggregate MFs | EP63: Aggregate MFs | EQ63: Aggregate MFs | ER63: Aggregate MFs | ES63: Aggregate MFs | ET63: Aggregate MFs | EU63: Aggregate MFs | EV63: Aggregate MFs | EW63: Investment Managers | EX63: Investment Advisor/Hedge Fund | EY63: 54.41391 | EZ63: GARP | FA63: Low | FB63: Low | FC63: Low | FD63: Low | FE63: Low | FF63: Moderate | FG63: Moderate | FH63: Moderate | FI63: Moderate | FJ63: Moderate | FK63: Moderate | FM63: Low | FN63: Low | FO63: Moderate | FP63: Moderate | FQ63: Moderate | FR63: Moderate | FS63: Moderate | FT63: Moderate | FU63: Moderate | FV63: Moderate | FW63: Moderate | FX63: Moderate | FY63: Moderate | FZ63: Singapore | GA63: Singapore
A64: 62 | B64: Fidelity Management & Research Company LLC | C64: 0.000333 | D64: 0.000333 | E64: 0.000333 | F64: 0.000333 | G64: 0.000346 | H64: 0.000362 | I64: 0.000271 | AB64: 0.044595 | AC64: 0.044595 | AD64: 0.044595 | AE64: 0.044595 | AF64: 0.046281 | AG64: 0.048441 | AH64: 0.036337 | BA64: 0 | BB64: 0 | BC64: 0 | BD64: -0.001686 | BE64: -0.00216 | BF64: 0.012104 | BG64: 0.036337 | BZ64: 1.2371528 | CA64: 1.2371528 | CB64: 1.2371528 | CC64: 1.2987859 | CD64: 1.4261449 | CE64: 1.7802738 | CF64: 1.3047482 | CY64: 46112 | CZ64: 46112 | DA64: 46112 | DB64: 46081 | DC64: 46053 | DD64: 46022 | DE64: 45991 | DX64: Aggregate MFs | DY64: Aggregate MFs | DZ64: Aggregate MFs | EA64: Aggregate MFs | EB64: Aggregate MFs | EC64: Aggregate MFs | ED64: Aggregate MFs | EW64: Investment Managers | EX64: Investment Advisor | EY64: 2853985.3 | EZ64: GARP | FA64: Low | FB64: Low | FC64: Low | FD64: Low | FE64: Low | FF64: Low | FG64: Low | FZ64: Boston | GA64: United States
A65: 63 | B65: Smita Fiscal Pvt. Ltd. | C65: 0.000323 | D65: 0.000323 | E65: 0.000323 | F65: 0.000323 | G65: 0.000323 | H65: 0.000323 | I65: 0.000323 | J65: 0.000323 | K65: 0.000323 | L65: 0.000323 | M65: 0.000323 | N65: 0.000323 | O65: 0.000323 | P65: 0.000323 | Q65: 0.000323 | R65: 0.000323 | S65: 0.000323 | T65: 0.000323 | U65: 0.000323 | V65: 0.000323 | W65: 0.000324 | X65: 0.000324 | Y65: 0.000324 | Z65: 0.000324 | AA65: 0.000324 | AB65: 0.043275 | AC65: 0.043275 | AD65: 0.043275 | AE65: 0.043275 | AF65: 0.043275 | AG65: 0.043275 | AH65: 0.043275 | AI65: 0.043275 | AJ65: 0.043275 | AK65: 0.043275 | AL65: 0.043275 | AM65: 0.043275 | AN65: 0.043275 | AO65: 0.043275 | AP65: 0.043275 | AQ65: 0.043275 | AR65: 0.043275 | AS65: 0.043275 | AT65: 0.043275 | AU65: 0.043275 | AV65: 0.043275 | AW65: 0.043275 | AX65: 0.043275 | AY65: 0.043275 | AZ65: 0.043275 | BA65: 0 | BB65: 0 | BC65: 0 | BD65: 0 | BE65: 0 | BF65: 0 | BG65: 0 | BH65: 0 | BI65: 0 | BJ65: 0 | BK65: 0 | BL65: 0 | BM65: 0 | BN65: 0 | BO65: 0 | BP65: 0 | BQ65: 0 | BR65: 0 | BS65: 0 | BT65: 0 | BU65: 0 | BV65: 0 | BW65: 0 | BX65: 0 | BY65: 0 | BZ65: 1.5904162 | CA65: 1.5904162 | CB65: 1.5904162 | CC65: 1.5904162 | CD65: 1.5904162 | CE65: 1.5904162 | CF65: 1.4093632 | CG65: 1.4093632 | CH65: 1.4093632 | CI65: 1.3256008 | CJ65: 1.3256008 | CK65: 1.3256008 | CL65: 1.2273799 | CM65: 1.2273799 | CN65: 1.2273799 | CO65: 1.3193523 | CP65: 1.3193523 | CQ65: 1.3193523 | CR65: 1.0568545 | CS65: 1.0568545 | CT65: 1.0568545 | CU65: 0.92746234 | CV65: 0.92746234 | CW65: 0.92746234 | CX65: 0.89701964 | CY65: 46022 | CZ65: 46022 | DA65: 46022 | DB65: 46022 | DC65: 46022 | DD65: 46022 | DE65: 45930 | DF65: 45930 | DG65: 45930 | DH65: 45838 | DI65: 45838 | DJ65: 45838 | DK65: 45747 | DL65: 45747 | DM65: 45747 | DN65: 45657 | DO65: 45657 | DP65: 45657 | DQ65: 45565 | DR65: 45565 | DS65: 45565 | DT65: 45473 | DU65: 45473 | DV65: 45473 | DW65: 45382 | DX65: Shareholder Report | DY65: Shareholder Report | DZ65: Shareholder Report | EA65: Shareholder Report | EB65: Shareholder Report | EC65: Shareholder Report | ED65: Shareholder Report | EE65: Shareholder Report | EF65: Shareholder Report | EG65: Shareholder Report | EH65: Shareholder Report | EI65: Shareholder Report | EJ65: Shareholder Report | EK65: Shareholder Report | EL65: Shareholder Report | EM65: Shareholder Report | EN65: Shareholder Report | EO65: Shareholder Report | EP65: Shareholder Report | EQ65: Shareholder Report | ER65: Shareholder Report | ES65: Shareholder Report | ET65: Shareholder Report | EU65: Shareholder Report | EV65: Shareholder Report | EW65: Strategic Entities | EX65: Corporation | EY65: 1.5904162 | FA65: Low | FB65: Low | FC65: Low | FD65: Low | FE65: Low | FF65: Low | FG65: Low | FH65: Low | FI65: Low | FJ65: Low | FK65: Low | FL65: Low | FM65: Low | FN65: Low | FO65: Low | FP65: Low | FQ65: Low | FR65: Low | FS65: Low | FT65: Low | FU65: Low | FV65: Low | FW65: Low | FX65: Low | FY65: Low | FZ65: New Delhi | GA65: India
A66: 64 | B66: Geode Capital Management, L.L.C. | C66: 0.000314 | D66: 0.000314 | E66: 0.000314 | F66: 0.000314 | G66: 0.000314 | H66: 0.00028 | I66: 0.00028 | J66: 0.00028 | K66: 0.00028 | L66: 0.000267 | M66: 0.000267 | N66: 0.000267 | O66: 0.000271 | P66: 0.000253 | Q66: 0.000253 | R66: 0.000253 | S66: 0.000248 | T66: 0.000248 | U66: 0.000248 | V66: 0.000248 | W66: 0.00025 | X66: 0.000254 | Y66: 0.000253 | Z66: 0.000236 | AA66: 0.00024 | AB66: 0.042109 | AC66: 0.042109 | AD66: 0.042109 | AE66: 0.042109 | AF66: 0.042109 | AG66: 0.037548 | AH66: 0.037548 | AI66: 0.037548 | AJ66: 0.037548 | AK66: 0.035734 | AL66: 0.035734 | AM66: 0.035734 | AN66: 0.036206 | AO66: 0.033875 | AP66: 0.033875 | AQ66: 0.033875 | AR66: 0.033202 | AS66: 0.033202 | AT66: 0.033202 | AU66: 0.033202 | AV66: 0.033451 | AW66: 0.033915 | AX66: 0.033779 | AY66: 0.031556 | AZ66: 0.032069 | BA66: 0 | BB66: 0 | BC66: 0 | BD66: 0 | BE66: 0.004561 | BF66: 0 | BG66: 0 | BH66: 0 | BI66: 0.001814 | BJ66: 0 | BK66: 0 | BL66: -0.000472 | BM66: 0.002331 | BN66: 0 | BO66: 0 | BP66: 0.000673 | BQ66: 0 | BR66: 0 | BS66: 0 | BT66: -0.000249 | BU66: -0.000464 | BV66: 0.000136 | BW66: 0.002223 | BX66: -0.000513 | BY66: 0.001353 | BZ66: 1.1681863 | CA66: 1.1681863 | CB66: 1.1681863 | CC66: 1.2263836 | CD66: 1.297585 | CE66: 1.379941 | CF66: 1.3482315 | CG66: 1.3270308 | CH66: 1.2228485 | CI66: 1.1641168 | CJ66: 1.1146748 | CK66: 1.0946047 | CL66: 1.0739136 | CM66: 0.97720861 | CN66: 0.96077395 | CO66: 0.80412881 | CP66: 0.83571826 | CQ66: 1.0122504 | CR66: 0.96637499 | CS66: 0.88553148 | CT66: 0.81693449 | CU66: 0.78534615 | CV66: 0.69556348 | CW66: 0.67630276 | CX66: 0.60602199 | CY66: 46112 | CZ66: 46112 | DA66: 46112 | DB66: 46081 | DC66: 46053 | DD66: 46022 | DE66: 45991 | DF66: 45961 | DG66: 45930 | DH66: 45900 | DI66: 45869 | DJ66: 45838 | DK66: 45808 | DL66: 45777 | DM66: 45747 | DN66: 45716 | DO66: 45688 | DP66: 45657 | DQ66: 45626 | DR66: 45596 | DS66: 45565 | DT66: 45535 | DU66: 45504 | DV66: 45473 | DW66: 45443 | DX66: Aggregate MFs | DY66: Aggregate MFs | DZ66: Aggregate MFs | EA66: Aggregate MFs | EB66: Aggregate MFs | EC66: Aggregate MFs | ED66: Aggregate MFs | EE66: Aggregate MFs | EF66: Aggregate MFs | EG66: Aggregate MFs | EH66: Aggregate MFs | EI66: Aggregate MFs | EJ66: Aggregate MFs | EK66: Aggregate MFs | EL66: Aggregate MFs | EM66: Aggregate MFs | EN66: Aggregate MFs | EO66: Aggregate MFs | EP66: Aggregate MFs | EQ66: Aggregate MFs | ER66: Aggregate MFs | ES66: Aggregate MFs | ET66: Aggregate MFs | EU66: Aggregate MFs | EV66: Aggregate MFs | EW66: Investment Managers | EX66: Investment Advisor/Hedge Fund | EY66: 1907125.6 | EZ66: Index | FA66: Low | FB66: Low | FC66: Low | FD66: Low | FE66: Low | FF66: Low | FG66: Low | FH66: Low | FI66: Low | FJ66: Low | FK66: Low | FL66: Low | FM66: Low | FN66: Low | FO66: Low | FP66: Low | FQ66: Low | FR66: Low | FS66: Low | FT66: Low | FU66: Low | FV66: Low | FW66: Low | FX66: Low | FY66: Low | FZ66: Boston | GA66: United States
A67: 65 | B67: BlackRock Investment Management, LLC | C67: 0.000277 | D67: 0.000277 | E67: 0.000277 | F67: 0.000277 | G67: 0.000277 | H67: 0.000277 | I67: 0.000246 | J67: 6.3e-05 | K67: 6.3e-05 | L67: 6.3e-05 | M67: 6.3e-05 | N67: 6.3e-05 | O67: 6.3e-05 | AB67: 0.037052 | AC67: 0.037052 | AD67: 0.037052 | AE67: 0.037052 | AF67: 0.037052 | AG67: 0.037052 | AH67: 0.032913 | AI67: 0.008397 | AJ67: 0.008397 | AK67: 0.008397 | AL67: 0.008397 | AM67: 0.008397 | AN67: 0.008397 | BA67: 0 | BB67: 0 | BC67: 0 | BD67: 0 | BE67: 0 | BF67: 0.004139 | BG67: 0.024516 | BH67: 0 | BI67: 0 | BJ67: 0 | BK67: 0 | BL67: 0 | BM67: 0.008397 | BZ67: 1.1417541 | CA67: 1.1417541 | CB67: 1.1417541 | CC67: 1.1417541 | CD67: 1.1417541 | CE67: 1.3617123 | CF67: 1.1818031 | CG67: 0.29676887 | CH67: 0.2734702 | CI67: 0.2735515 | CJ67: 0.26193329 | CK67: 0.25721709 | CL67: 0.24906514 | CY67: 46053 | CZ67: 46053 | DA67: 46053 | DB67: 46053 | DC67: 46053 | DD67: 46022 | DE67: 45991 | DF67: 45961 | DG67: 45930 | DH67: 45900 | DI67: 45869 | DJ67: 45838 | DK67: 45808 | DX67: Aggregate MFs | DY67: Aggregate MFs | DZ67: Aggregate MFs | EA67: Aggregate MFs | EB67: Aggregate MFs | EC67: Aggregate MFs | ED67: Aggregate MFs | EE67: Aggregate MFs | EF67: Aggregate MFs | EG67: Aggregate MFs | EH67: Aggregate MFs | EI67: Aggregate MFs | EJ67: Aggregate MFs | EW67: Investment Managers | EX67: Investment Advisor/Hedge Fund | EY67: 222919.41 | EZ67: Deep Value | FA67: Low | FB67: Low | FC67: Low | FD67: Low | FE67: Low | FF67: Low | FG67: Low | FH67: Low | FI67: Low | FJ67: Low | FK67: Low | FL67: Low | FM67: Low | FZ67: Princeton | GA67: United States
A68: 66 | B68: Manulife Investment Management (Hong Kong) Limited | C68: 0.00026 | D68: 0.00026 | E68: 0.00026 | F68: 0.00026 | G68: 0.00026 | H68: 0.00026 | I68: 0.00026 | J68: 0.00026 | K68: 0.00026 | L68: 0.00026 | M68: 0.00026 | N68: 0.00026 | O68: 0.00026 | P68: 0.00026 | Q68: 0.00026 | R68: 0.00026 | AB68: 0.03485 | AC68: 0.03485 | AD68: 0.03485 | AE68: 0.03485 | AF68: 0.03485 | AG68: 0.03485 | AH68: 0.03485 | AI68: 0.03485 | AJ68: 0.03485 | AK68: 0.03485 | AL68: 0.03485 | AM68: 0.03485 | AN68: 0.03485 | AO68: 0.03485 | AP68: 0.03485 | AQ68: 0.03485 | BA68: 0 | BB68: 0 | BC68: 0 | BD68: 0 | BE68: 0 | BF68: 0 | BG68: 0 | BH68: 0 | BI68: 0 | BJ68: 0 | BK68: 0 | BL68: 0 | BM68: 0 | BN68: 0 | BO68: 0 | BP68: 0.03485 | BZ68: 0.9668074 | CA68: 0.9668074 | CB68: 0.9668074 | CC68: 1.0149723 | CD68: 1.0738996 | CE68: 1.2807857 | CF68: 1.1349811 | CG68: 1.1349811 | CH68: 1.1349811 | CI68: 1.1353185 | CJ68: 1.0870996 | CK68: 1.067526 | CL68: 1.033693 | CM68: 1.0053349 | CN68: 0.98842722 | CO68: 0.82727347 | CY68: 46112 | CZ68: 46112 | DA68: 46112 | DB68: 46081 | DC68: 46053 | DD68: 46022 | DE68: 45930 | DF68: 45930 | DG68: 45930 | DH68: 45900 | DI68: 45869 | DJ68: 45838 | DK68: 45808 | DL68: 45777 | DM68: 45747 | DN68: 45716 | DX68: Aggregate MFs | DY68: Aggregate MFs | DZ68: Aggregate MFs | EA68: Aggregate MFs | EB68: Aggregate MFs | EC68: Aggregate MFs | ED68: Aggregate MFs | EE68: Aggregate MFs | EF68: Aggregate MFs | EG68: Aggregate MFs | EH68: Aggregate MFs | EI68: Aggregate MFs | EJ68: Aggregate MFs | EK68: Aggregate MFs | EL68: Aggregate MFs | EM68: Aggregate MFs | EW68: Investment Managers | EX68: Investment Advisor | EY68: 2923.1705 | EZ68: Deep Value | FA68: High | FB68: High | FC68: High | FD68: High | FE68: High | FF68: High | FG68: High | FH68: High | FI68: High | FJ68: High | FK68: Moderate | FL68: Moderate | FM68: Moderate | FP68: Moderate | FZ68: Causeway Bay (Hong Kong) | GA68: Hong Kong
